Workbook
Name CostInflation: 'Scearios(What if)'!$C$6
Name DiscountCap: 'Scearios(What if)'!$C$5
Name QtyUplift: 'Scearios(What if)'!$C$7
Name Slicer_Channel: #N/A
Name Slicer_Country: #N/A
Name Slicer_DiscountPct: #N/A
Name Slicer_Gross_Profit: #N/A
Name Slicer_Gross_Revenue: #N/A
Name Slicer_Leadtime_days: #N/A
Name Slicer_Month: #N/A
Name Slicer_OrderID: #N/A
Name Slicer_ProductCategory: #N/A
Name Slicer_Region: #N/A
Name Slicer_Salesperson: #N/A
Name Slicer_SKU: #N/A

Sheet Data
A1: ORD-2024-275203 | B1: 45362 | C1: 45388 | D1: =DATEDIF(B1,C1, "MD") -> 26 | E1: =TEXT(Data!B1,"MMM-YYYY") -> Mar-2024 | F1: ="Q"&ROUNDUP(MONTH(B1)/3,0)&"-"&YEAR(B1) -> Q1-2024 | G1: Africa | H1: Kenya | I1: Kisumu | J1: Corporate | K1: Retail | L1: C. Otieno | M1: Components | N1: CMP-8270 | O1: 279.24 | P1: =IF(Q1<50, "Low", IF(Q1<200, "Medium", "High")) -> High | Q1: 608.9 | R1: 0.112 | S1: 9 | T1: =(Q27*S1)*(1-R1) -> 1403.9546 | U1: =(O1*S1) -> 2513.16 | V1: =(T1-U1) -> -1109.2054 | W1: =IF(T1=0, 0, V1/T1) -> -0.79005783
A2: ORD-2024-358795 | B2: 45588 | C2: 45587 | D2: =DATEDIF(C2, B2, "MD") -> 1 | E2: =TEXT(Data!B2,"MMM-YYYY") -> Oct-2024 | F2: ="Q"&ROUNDUP(MONTH(B2)/3,0)&"-"&YEAR(B2) -> Q4-2024 | G2: Africa | H2: Nigeria | I2: Port Harcourt | J2: Education | K2: Online | L2: J. Njeri | M2: Printers | N2: PRN-9322 | O2: 1084.39 | P2: =IF(Q2<50, "Low", IF(Q2<200, "Medium", "High")) -> High | Q2: 759.33 | R2: 0.237 | S2: 31 | T2: =(Q28*S2)*(1-R2) -> 17934.414 | U2: =(O2*S2) -> 33616.09 | V2: =(T2-U2) -> -15681.676 | W2: =IF(T2=0, 0, V2/T2) -> -0.87439019
A3: ORD-2023-373538 | B3: 44985 | C3: 45010 | D3: =DATEDIF(B3,C3, "MD") -> 25 | E3: =TEXT(Data!B3,"MMM-YYYY") -> Feb-2023 | F3: ="Q"&ROUNDUP(MONTH(B3)/3,0)&"-"&YEAR(B3) -> Q1-2023 | G3: Africa | H3: Kenya | I3: Nairobi | J3: Corporate | K3: Retail | L3: I. Johnson | M3: Networking | N3: NET-9666 | O3: 1460.76 | P3: =IF(Q3<50, "Low", IF(Q3<200, "Medium", "High")) -> Low | Q3: -30.66 | R3: 0.131 | S3: 12 | T3: =(Q29*S3)*(1-R3) -> 4534.0944 | U3: =(O3*S3) -> 17529.12 | V3: =(T3-U3) -> -12995.026 | W3: =IF(T3=0, 0, V3/T3) -> -2.8660686
A4: ORD-2025-168148 | B4: 45745 | C4: 45749 | D4: =DATEDIF(B4,C4, "MD") -> 4 | E4: =TEXT(Data!B4,"MMM-YYYY") -> Mar-2025 | F4: ="Q"&ROUNDUP(MONTH(B4)/3,0)&"-"&YEAR(B4) -> Q1-2025 | G4: Africa | H4: Nigeria | I4: Lagos | J4: Non-Profit | K4: Marketplace | L4: G. Dubois | M4: Phones | N4: PHN-4556 | O4: 259.93 | P4: =IF(Q4<50, "Low", IF(Q4<200, "Medium", "High")) -> High | Q4: 255.94 | R4: 0.072 | S4: 22 | T4: =(Q30*S4)*(1-R4) -> 34016.731 | U4: =(O4*S4) -> 5718.46 | V4: =(T4-U4) -> 28298.271 | W4: =IF(T4=0, 0, V4/T4) -> 0.83189272
A5: ORD-2023-824839 | B5: 45266 | C5: 45291 | D5: =DATEDIF(B5,C5, "MD") -> 25 | E5: =TEXT(Data!B5,"MMM-YYYY") -> Dec-2023 | F5: ="Q"&ROUNDUP(MONTH(B5)/3,0)&"-"&YEAR(B5) -> Q4-2023 | G5: Asia | H5: Japan | I5: Osaka | J5: Consumer | K5: Retail | L5: L. Okafor | M5: Printers | N5: PRN-8041 | O5: 663.03 | P5: =IF(Q5<50, "Low", IF(Q5<200, "Medium", "High")) -> High | Q5: 813.51 | R5: 0.102 | S5: 15 | T5: =(Q31*S5)*(1-R5) -> 8510.0766 | U5: =(O5*S5) -> 9945.45 | V5: =(T5-U5) -> -1435.3734 | W5: =IF(T5=0, 0, V5/T5) -> -0.16866751
A6: ORD-2023-723587 | B6: 44928 | C6: 44931 | D6: =DATEDIF(B6,C6, "MD") -> 3 | E6: =TEXT(Data!B6,"MMM-YYYY") -> Jan-2023 | F6: ="Q"&ROUNDUP(MONTH(B6)/3,0)&"-"&YEAR(B6) -> Q1-2023 | G6: Americas | H6: Canada | I6: Toronto | J6: Corporate | K6: Distributor | L6: B. Chen | M6: Laptops | N6: LAP-8555 | O6: 315.87 | P6: =IF(Q6<50, "Low", IF(Q6<200, "Medium", "High")) -> High | Q6: 591.68 | R6: 0 | S6: 7 | T6: =(Q32*S6)*(1-R6) -> 12558.49 | U6: =(O6*S6) -> 2211.09 | V6: =(T6-U6) -> 10347.4 | W6: =IF(T6=0, 0, V6/T6) -> 0.82393664
A7: ORD-2024-336584 | B7: 45653 | C7: 45671 | D7: =DATEDIF(B7,C7, "MD") -> 18 | E7: =TEXT(Data!B7,"MMM-YYYY") -> Dec-2024 | F7: ="Q"&ROUNDUP(MONTH(B7)/3,0)&"-"&YEAR(B7) -> Q4-2024 | G7: Asia | H7: India | I7: Bengaluru | J7: Small Business | K7: Marketplace | L7: E. Garcia | M7: Monitors | N7: MON-8629 | O7: 586.07 | P7: =IF(Q7<50, "Low", IF(Q7<200, "Medium", "High")) -> High | Q7: 845.97 | R7: 0.147 | S7: 4 | T7: =(Q33*S7)*(1-R7) -> 8983.8642 | U7: =(O7*S7) -> 2344.28 | V7: =(T7-U7) -> 6639.5842 | W7: =IF(T7=0, 0, V7/T7) -> 0.73905661
A8: ORD-2023-112666 | B8: 44941 | C8: 44939 | D8: =DATEDIF(C8,B8, "MD") -> 2 | E8: =TEXT(Data!B8,"MMM-YYYY") -> Jan-2023 | F8: ="Q"&ROUNDUP(MONTH(B8)/3,0)&"-"&YEAR(B8) -> Q1-2023 | G8: Africa | H8: Nigeria | I8: Abuja | J8: Education | K8: Online | L8: O. Wang | M8: Printers | N8: PRN-6276 | O8: 28.38 | P8: =IF(Q8<50, "Low", IF(Q8<200, "Medium", "High")) -> Low | Q8: 47.22 | R8: 0.194 | S8: 18 | T8: =(Q34*S8)*(1-R8) -> 19177.4 | U8: =(O8*S8) -> 510.84 | V8: =(T8-U8) -> 18666.56 | W8: =IF(T8=0, 0, V8/T8) -> 0.9733624
A9: ORD-2024-589570 | B9: 45416 | C9: 45441 | D9: =DATEDIF(B9,C9, "MD") -> 25 | E9: =TEXT(Data!B9,"MMM-YYYY") -> May-2024 | F9: ="Q"&ROUNDUP(MONTH(B9)/3,0)&"-"&YEAR(B9) -> Q2-2024 | G9: Africa | H9: Nigeria | I9: Abuja | J9: Non-Profit | K9: Marketplace | L9: O. Wang | M9: Monitors | N9: MON-6892 | O9: 1295.34 | P9: =IF(Q9<50, "Low", IF(Q9<200, "Medium", "High")) -> High | Q9: 2530.81 | R9: 0.031 | S9: 6 | T9: =(Q35*S9)*(1-R9) -> 17656.362 | U9: =(O9*S9) -> 7772.04 | V9: =(T9-U9) -> 9884.3222 | W9: =IF(T9=0, 0, V9/T9) -> 0.55981646
A10: ORD-2025-997421 | B10: 45798 | C10: 45817 | D10: =DATEDIF(B10,C10, "MD") -> 19 | E10: =TEXT(Data!B10,"MMM-YYYY") -> May-2025 | F10: ="Q"&ROUNDUP(MONTH(B10)/3,0)&"-"&YEAR(B10) -> Q2-2025 | G10: Americas | H10: Brazil | I10: São Paulo | J10: Non-Profit | K10: Online | L10: A. Patel | M10: Components | N10: CMP-3731 | O10: 1331.38 | P10: =IF(Q10<50, "Low", IF(Q10<200, "Medium", "High")) -> High | Q10: 2309.56 | R10: 0.149 | S10: 31 | T10: =(Q36*S10)*(1-R10) -> 5259.58 | U10: =(O10*S10) -> 41272.78 | V10: =(T10-U10) -> -36013.2 | W10: =IF(T10=0, 0, V10/T10) -> -6.8471627
A11: ORD-2024-210687 | B11: 45319 | C11: 45331 | D11: =DATEDIF(B11,C11, "MD") -> 12 | E11: =TEXT(Data!B11,"MMM-YYYY") -> Jan-2024 | F11: ="Q"&ROUNDUP(MONTH(B11)/3,0)&"-"&YEAR(B11) -> Q1-2024 | G11: Europe | H11: Germany | I11: Berlin | J11: Corporate | K11: Online | L11: G. Dubois | M11: Accessories | N11: ACC-7938 | O11: 644.17 | P11: =IF(Q11<50, "Low", IF(Q11<200, "Medium", "High")) -> High | Q11: 700.12 | R11: 0.006 | S11: 23 | T11: =(Q37*S11)*(1-R11) -> 21204.734 | U11: =(O11*S11) -> 14815.91 | V11: =(T11-U11) -> 6388.8236 | W11: =IF(T11=0, 0, V11/T11) -> 0.30129233
A12: ORD-2025-515515 | B12: 45660 | C12: 45680 | D12: =DATEDIF(B12,C12, "MD") -> 20 | E12: =TEXT(Data!B12,"MMM-YYYY") -> Jan-2025 | F12: ="Q"&ROUNDUP(MONTH(B12)/3,0)&"-"&YEAR(B12) -> Q1-2025 | G12: Asia | H12: Japan | I12: Osaka | J12: Corporate | K12: Distributor | L12: F. Müller | M12: Phones | N12: PHN-7019 | O12: 908.6 | P12: =IF(Q12<50, "Low", IF(Q12<200, "Medium", "High")) -> High | Q12: 691.37 | R12: 0.25 | S12: 20 | T12: =(Q38*S12)*(1-R12) -> 26031.15 | U12: =(O12*S12) -> 18172 | V12: =(T12-U12) -> 7859.15 | W12: =IF(T12=0, 0, V12/T12) -> 0.30191328
A13: ORD-2025-487261 | B13: 45722 | C13: 45747 | D13: =DATEDIF(B13,C13, "MD") -> 25 | E13: =TEXT(Data!B13,"MMM-YYYY") -> Mar-2025 | F13: ="Q"&ROUNDUP(MONTH(B13)/3,0)&"-"&YEAR(B13) -> Q1-2025 | G13: Americas | H13: Brazil | I13: Brasília | J13: Non-Profit | K13: Online | L13: J. Njeri | M13: Components | N13: CMP-3693 | O13: 331.57 | P13: =IF(Q13<50, "Low", IF(Q13<200, "Medium", "High")) -> High | Q13: 548.4 | R13: 0.094 | S13: 10 | T13: =(Q39*S13)*(1-R13) -> 12644.498 | U13: =(O13*S13) -> 3315.7 | V13: =(T13-U13) -> 9328.7984 | W13: =IF(T13=0, 0, V13/T13) -> 0.73777528
A14: ORD-2024-890180 | B14: 45311 | C14: 45335 | D14: =DATEDIF(B14,C14, "MD") -> 24 | E14: =TEXT(Data!B14,"MMM-YYYY") -> Jan-2024 | F14: ="Q"&ROUNDUP(MONTH(B14)/3,0)&"-"&YEAR(B14) -> Q1-2024 | G14: Europe | H14: France | I14: Marseille | J14: Corporate | K14: Retail | L14: H. Kim | M14: Printers | N14: PRN-8392 | O14: 643.53 | P14: =IF(Q14<50, "Low", IF(Q14<200, "Medium", "High")) -> High | Q14: 1439.01 | R14: 0 | S14: 15 | T14: =(Q40*S14)*(1-R14) -> 6816.3 | U14: =(O14*S14) -> 9652.95 | V14: =(T14-U14) -> -2836.65 | W14: =IF(T14=0, 0, V14/T14) -> -0.41615686
A15: ORD-2025-840976 | B15: 45901 | C15: 45930 | D15: =DATEDIF(B15,C15, "MD") -> 29 | E15: =TEXT(Data!B15,"MMM-YYYY") -> Sep-2025 | F15: ="Q"&ROUNDUP(MONTH(B15)/3,0)&"-"&YEAR(B15) -> Q3-2025 | G15: Americas | H15: Brazil | I15: Brasília | J15: Education | K15: Retail | L15: K. Singh | M15: Accessories | N15: ACC-1663 | O15: 780.59 | P15: =IF(Q15<50, "Low", IF(Q15<200, "Medium", "High")) -> High | Q15: 631.57 | R15: 0 | S15: 12 | T15: =(Q41*S15)*(1-R15) -> 18971.64 | U15: =(O15*S15) -> 9367.08 | V15: =(T15-U15) -> 9604.56 | W15: =IF(T15=0, 0, V15/T15) -> 0.50625882
A16: ORD-2023-937291 | B16: 45039 | C16: 45038 | D16: =DATEDIF(C16, B16, "MD") -> 1 | E16: =TEXT(Data!B16,"MMM-YYYY") -> Apr-2023 | F16: ="Q"&ROUNDUP(MONTH(B16)/3,0)&"-"&YEAR(B16) -> Q2-2023 | G16: Africa | H16: Kenya | I16: Nairobi | J16: Small Business | K16: Direct | L16: E. Garcia | M16: Laptops | N16: LAP-1698 | O16: 756.51 | P16: =IF(Q16<50, "Low", IF(Q16<200, "Medium", "High")) -> High | Q16: 850.8 | R16: 0.074 | S16: 9 | T16: =(Q42*S16)*(1-R16) -> 14666.09 | U16: =(O16*S16) -> 6808.59 | V16: =(T16-U16) -> 7857.4999 | W16: =IF(T16=0, 0, V16/T16) -> 0.5357597
A17: ORD-2024-206081 | B17: 45636 | C17: 45665 | D17: =DATEDIF(B17,C17, "MD") -> 29 | E17: =TEXT(Data!B17,"MMM-YYYY") -> Dec-2024 | F17: ="Q"&ROUNDUP(MONTH(B17)/3,0)&"-"&YEAR(B17) -> Q4-2024 | G17: Europe | H17: France | I17: Marseille | J17: Small Business | K17: Retail | L17: K. Singh | M17: Printers | N17: PRN-6791 | O17: 891.08 | P17: =IF(Q17<50, "Low", IF(Q17<200, "Medium", "High")) -> High | Q17: 1040.1 | R17: 0.109 | S17: 28 | T17: =(Q43*S17)*(1-R17) -> 79945.866 | U17: =(O17*S17) -> 24950.24 | V17: =(T17-U17) -> 54995.626 | W17: =IF(T17=0, 0, V17/T17) -> 0.68791082
A18: ORD-2025-233883 | B18: 45908 | C18: 45916 | D18: =DATEDIF(B18,C18, "MD") -> 8 | E18: =TEXT(Data!B18,"MMM-YYYY") -> Sep-2025 | F18: ="Q"&ROUNDUP(MONTH(B18)/3,0)&"-"&YEAR(B18) -> Q3-2025 | G18: Asia | H18: Japan | I18: Osaka | J18: Corporate | K18: Distributor | L18: C. Otieno | M18: Phones | N18: PHN-1197 | O18: 1225.57 | P18: =IF(Q18<50, "Low", IF(Q18<200, "Medium", "High")) -> High | Q18: 2705.57 | R18: 0.183 | S18: 16 | T18: =(Q44*S18)*(1-R18) -> 14842.341 | U18: =(O18*S18) -> 19609.12 | V18: =(T18-U18) -> -4766.779 | W18: =IF(T18=0, 0, V18/T18) -> -0.32116086
A19: ORD-2025-843974 | B19: 45858 | C19: 45874 | D19: =DATEDIF(B19,C19, "MD") -> 16 | E19: =TEXT(Data!B19,"MMM-YYYY") -> Jul-2025 | F19: ="Q"&ROUNDUP(MONTH(B19)/3,0)&"-"&YEAR(B19) -> Q3-2025 | G19: Americas | H19: Brazil | I19: Brasília | J19: Enterprise | K19: Marketplace | L19: G. Dubois | M19: Accessories | N19: ACC-8098 | O19: 1068.17 | P19: =IF(Q19<50, "Low", IF(Q19<200, "Medium", "High")) -> High | Q19: 2375.37 | R19: 0.109 | S19: 18 | T19: =(Q45*S19)*(1-R19) -> 15979.622 | U19: =(O19*S19) -> 19227.06 | V19: =(T19-U19) -> -3247.4383 | W19: =IF(T19=0, 0, V19/T19) -> -0.20322373
A20: ORD-2025-745263 | B20: 45798 | C20: 45796 | D20: =DATEDIF(C20,B20, "MD") -> 2 | E20: =TEXT(Data!B20,"MMM-YYYY") -> May-2025 | F20: ="Q"&ROUNDUP(MONTH(B20)/3,0)&"-"&YEAR(B20) -> Q2-2025 | G20: Europe | H20: United Kingdom | I20: Birmingham | J20: Enterprise | K20: Online | L20: M. Rossi | M20: Laptops | N20: LAP-3385 | O20: 1015.16 | P20: =IF(Q20<50, "Low", IF(Q20<200, "Medium", "High")) -> High | Q20: 2148.14 | R20: 0.038 | S20: 19 | T20: =(Q46*S20)*(1-R20) -> 25535.28 | U20: =(O20*S20) -> 19288.04 | V20: =(T20-U20) -> 6247.2399 | W20: =IF(T20=0, 0, V20/T20) -> 0.24465132
A21: ORD-2024-798002 | B21: 45498 | C21: 45497 | D21: =DATEDIF(C21,B21, "MD") -> 1 | E21: =TEXT(Data!B21,"MMM-YYYY") -> Jul-2024 | F21: ="Q"&ROUNDUP(MONTH(B21)/3,0)&"-"&YEAR(B21) -> Q3-2024 | G21: Africa | H21: Kenya | I21: Mombasa | J21: Non-Profit | K21: Direct | L21: J. Njeri | M21: Laptops | N21: LAP-9815 | O21: 1494.4 | P21: =IF(Q21<50, "Low", IF(Q21<200, "Medium", "High")) -> High | Q21: 3661.07 | R21: 0.072 | S21: 7 | T21: =(Q47*S21)*(1-R21) -> 3565.5894 | U21: =(O21*S21) -> 10460.8 | V21: =(T21-U21) -> -6895.2106 | W21: =IF(T21=0, 0, V21/T21) -> -1.9338207
A22: ORD-2023-867836 | B22: 45057 | C22: 45074 | D22: =DATEDIF(B22,C22, "MD") -> 17 | E22: =TEXT(Data!B22,"MMM-YYYY") -> May-2023 | F22: ="Q"&ROUNDUP(MONTH(B22)/3,0)&"-"&YEAR(B22) -> Q2-2023 | G22: Asia | H22: China | I22: Shenzhen | J22: Enterprise | K22: Marketplace | L22: E. Garcia | M22: Networking | N22: NET-3255 | O22: 1331.19 | P22: =IF(Q22<50, "Low", IF(Q22<200, "Medium", "High")) -> High | Q22: 2903.09 | R22: 0.143 | S22: 8 | T22: =(Q48*S22)*(1-R22) -> 24160.544 | U22: =(O22*S22) -> 10649.52 | V22: =(T22-U22) -> 13511.024 | W22: =IF(T22=0, 0, V22/T22) -> 0.55921853
A23: ORD-2025-580047 | B23: 45822 | C23: 45837 | D23: =DATEDIF(B23,C23, "MD") -> 15 | E23: =TEXT(Data!B23,"MMM-YYYY") -> Jun-2025 | F23: ="Q"&ROUNDUP(MONTH(B23)/3,0)&"-"&YEAR(B23) -> Q2-2025 | G23: Africa | H23: Nigeria | I23: Port Harcourt | J23: Consumer | K23: Marketplace | L23: M. Rossi | M23: Accessories | N23: ACC-3961 | O23: 730.99 | P23: =IF(Q23<50, "Low", IF(Q23<200, "Medium", "High")) -> High | Q23: 1242.84 | R23: 0.12 | S23: 10 | T23: =(Q49*S23)*(1-R23) -> 16065.368 | U23: =(O23*S23) -> 7309.9 | V23: =(T23-U23) -> 8755.468 | W23: =IF(T23=0, 0, V23/T23) -> 0.54499019
A24: ORD-2024-500109 | B24: 45430 | C24: 45435 | D24: =DATEDIF(B24,C24, "MD") -> 5 | E24: =TEXT(Data!B24,"MMM-YYYY") -> May-2024 | F24: ="Q"&ROUNDUP(MONTH(B24)/3,0)&"-"&YEAR(B24) -> Q2-2024 | G24: Americas | H24: USA | I24: Chicago | J24: Enterprise | K24: Retail | L24: H. Kim | M24: Laptops | N24: LAP-4987 | O24: 1274.59 | P24: =IF(Q24<50, "Low", IF(Q24<200, "Medium", "High")) -> High | Q24: 2553.69 | R24: 0.01 | S24: 8 | T24: =(Q50*S24)*(1-R24) -> 14187.65 | U24: =(O24*S24) -> 10196.72 | V24: =(T24-U24) -> 3990.9304 | W24: =IF(T24=0, 0, V24/T24) -> 0.28129608
A25: ORD-2023-271836 | B25: 44964 | C25: 44969 | D25: =DATEDIF(B25,C25, "MD") -> 5 | E25: =TEXT(Data!B25,"MMM-YYYY") -> Feb-2023 | F25: ="Q"&ROUNDUP(MONTH(B25)/3,0)&"-"&YEAR(B25) -> Q1-2023 | G25: Americas | H25: Brazil | I25: São Paulo | J25: Education | K25: Online | L25: N. Brown | M25: Components | N25: CMP-2693 | O25: 948.55 | P25: =IF(Q25<50, "Low", IF(Q25<200, "Medium", "High")) -> High | Q25: 2089.16 | R25: 0.007 | S25: 12 | T25: =(Q51*S25)*(1-R25) -> 31336.101 | U25: =(O25*S25) -> 11382.6 | V25: =(T25-U25) -> 19953.501 | W25: =IF(T25=0, 0, V25/T25) -> 0.63675762
A26: ORD-2024-215294 | B26: 45473 | C26: 45487 | D26: =DATEDIF(B26,C26, "MD") -> 14 | E26: =TEXT(Data!B26,"MMM-YYYY") -> Jun-2024 | F26: ="Q"&ROUNDUP(MONTH(B26)/3,0)&"-"&YEAR(B26) -> Q2-2024 | G26: Americas | H26: Brazil | I26: Brasília | J26: Education | K26: Retail | L26: C. Otieno | M26: Accessories | N26: ACC-8683 | O26: 1491.85 | P26: =IF(Q26<50, "Low", IF(Q26<200, "Medium", "High")) -> High | Q26: 2583.02 | R26: 0.168 | S26: 4 | T26: =(Q52*S26)*(1-R26) -> 353.7664 | U26: =(O26*S26) -> 5967.4 | V26: =(T26-U26) -> -5613.6336 | W26: =IF(T26=0, 0, V26/T26) -> -15.868193
A27: ORD-2024-788105 | B27: 45626 | C27: 45656 | D27: =DATEDIF(B27,C27, "MD") -> 0 | E27: =TEXT(Data!B27,"MMM-YYYY") -> Nov-2024 | F27: ="Q"&ROUNDUP(MONTH(B27)/3,0)&"-"&YEAR(B27) -> Q4-2024 | G27: Europe | H27: France | I27: Marseille | J27: Consumer | K27: Marketplace | L27: F. Müller | M27: Printers | N27: PRN-4170 | O27: 117.64 | P27: =IF(Q27<50, "Low", IF(Q27<200, "Medium", "High")) -> Medium | Q27: 175.67 | R27: 0 | S27: 10 | T27: =(Q53*S27)*(1-R27) -> 3857.2 | U27: =(O27*S27) -> 1176.4 | V27: =(T27-U27) -> 2680.8 | W27: =IF(T27=0, 0, V27/T27) -> 0.69501193
A28: ORD-2024-855073 | B28: 45492 | C28: 45492 | D28: =DATEDIF(B28,C28, "MD") -> 0 | E28: =TEXT(Data!B28,"MMM-YYYY") -> Jul-2024 | F28: ="Q"&ROUNDUP(MONTH(B28)/3,0)&"-"&YEAR(B28) -> Q3-2024 | G28: Africa | H28: Kenya | I28: Kisumu | J28: Small Business | K28: Retail | L28: A. Patel | M28: Phones | N28: PHN-6854 | O28: 857.24 | P28: =IF(Q28<50, "Low", IF(Q28<200, "Medium", "High")) -> High | Q28: 758.23 | R28: 0.125 | S28: 6 | T28: =(Q54*S28)*(1-R28) -> 1243.5675 | U28: =(O28*S28) -> 5143.44 | V28: =(T28-U28) -> -3899.8725 | W28: =IF(T28=0, 0, V28/T28) -> -3.136036
A29: ORD-2023-897079 | B29: 45030 | C29: 45060 | D29: =DATEDIF(B29,C29, "MD") -> 0 | E29: =TEXT(Data!B29,"MMM-YYYY") -> Apr-2023 | F29: ="Q"&ROUNDUP(MONTH(B29)/3,0)&"-"&YEAR(B29) -> Q2-2023 | G29: Africa | H29: Kenya | I29: Nakuru | J29: Consumer | K29: Marketplace | L29: M. Rossi | M29: Phones | N29: PHN-1784 | O29: 209.25 | P29: =IF(Q29<50, "Low", IF(Q29<200, "Medium", "High")) -> High | Q29: 434.8 | R29: 0 | S29: 9 | T29: =(Q55*S29)*(1-R29) -> 377.1 | U29: =(O29*S29) -> 1883.25 | V29: =(T29-U29) -> -1506.15 | W29: =IF(T29=0, 0, V29/T29) -> -3.9940334
A30: ORD-2025-548982 | B30: 45754 | C30: 45758 | D30: =DATEDIF(B30,C30, "MD") -> 4 | E30: =TEXT(Data!B30,"MMM-YYYY") -> Apr-2025 | F30: ="Q"&ROUNDUP(MONTH(B30)/3,0)&"-"&YEAR(B30) -> Q2-2025 | G30: Europe | H30: France | I30: Lyon | J30: Education | K30: Retail | L30: E. Garcia | M30: Networking | N30: NET-9716 | O30: 754.77 | P30: =IF(Q30<50, "Low", IF(Q30<200, "Medium", "High")) -> High | Q30: 1666.18 | R30: 0.139 | S30: 14 | T30: =(Q56*S30)*(1-R30) -> 11781.339 | U30: =(O30*S30) -> 10566.78 | V30: =(T30-U30) -> 1214.5585 | W30: =IF(T30=0, 0, V30/T30) -> 0.10309173
A31: ORD-2024-170313 | B31: 45653 | C31: 45672 | D31: =DATEDIF(B31,C31, "MD") -> 19 | E31: =TEXT(Data!B31,"MMM-YYYY") -> Dec-2024 | F31: ="Q"&ROUNDUP(MONTH(B31)/3,0)&"-"&YEAR(B31) -> Q4-2024 | G31: Asia | H31: India | I31: Delhi | J31: Non-Profit | K31: Distributor | L31: G. Dubois | M31: Components | N31: CMP-6919 | O31: 495.59 | P31: =IF(Q31<50, "Low", IF(Q31<200, "Medium", "High")) -> High | Q31: 631.78 | R31: 0.087 | S31: 17 | T31: =(Q57*S31)*(1-R31) -> 43367.692 | U31: =(O31*S31) -> 8425.03 | V31: =(T31-U31) -> 34942.662 | W31: =IF(T31=0, 0, V31/T31) -> 0.80573026
A32: ORD-2023-562894 | B32: 44980 | C32: 45010 | D32: =DATEDIF(B32,C32, "MD") -> 2 | E32: =TEXT(Data!B32,"MMM-YYYY") -> Feb-2023 | F32: ="Q"&ROUNDUP(MONTH(B32)/3,0)&"-"&YEAR(B32) -> Q1-2023 | G32: Americas | H32: Canada | I32: Montreal | J32: Enterprise | K32: Online | L32: D. Smith | M32: Phones | N32: PHN-4854 | O32: 1242.66 | P32: =IF(Q32<50, "Low", IF(Q32<200, "Medium", "High")) -> High | Q32: 1794.07 | R32: 0.089 | S32: 16 | T32: =(Q58*S32)*(1-R32) -> 10231.623 | U32: =(O32*S32) -> 19882.56 | V32: =(T32-U32) -> -9650.9368 | W32: =IF(T32=0, 0, V32/T32) -> -0.94324592
A33: ORD-2025-474710 | B33: 45862 | C33: 45875 | D33: =DATEDIF(B33,C33, "MD") -> 13 | E33: =TEXT(Data!B33,"MMM-YYYY") -> Jul-2025 | F33: ="Q"&ROUNDUP(MONTH(B33)/3,0)&"-"&YEAR(B33) -> Q3-2025 | G33: Africa | H33: South Africa | I33: Johannesburg | J33: Education | K33: Marketplace | L33: D. Smith | M33: Networking | N33: NET-7966 | O33: 1463.9 | P33: =IF(Q33<50, "Low", IF(Q33<200, "Medium", "High")) -> High | Q33: 2633.02 | R33: 0.084 | S33: 4 | T33: =(Q59*S33)*(1-R33) -> -19.30928 | U33: =(O33*S33) -> 5855.6 | V33: =(T33-U33) -> -5874.9093 | W33: =IF(T33=0, 0, V33/T33) -> 304.25315
A34: ORD-2024-629525 | B34: 45400 | C34: 45420 | D34: =DATEDIF(B34,C34, "MD") -> 20 | E34: =TEXT(Data!B34,"MMM-YYYY") -> Apr-2024 | F34: ="Q"&ROUNDUP(MONTH(B34)/3,0)&"-"&YEAR(B34) -> Q2-2024 | G34: Europe | H34: United Kingdom | I34: London | J34: Non-Profit | K34: Not Provided | L34: D. Smith | M34: Laptops | N34: LAP-9932 | O34: 645.33 | P34: =IF(Q34<50, "Low", IF(Q34<200, "Medium", "High")) -> High | Q34: 1321.85 | R34: 0 | S34: 10 | T34: =(Q60*S34)*(1-R34) -> 14370.6 | U34: =(O34*S34) -> 6453.3 | V34: =(T34-U34) -> 7917.3 | W34: =IF(T34=0, 0, V34/T34) -> 0.55093733
A35: ORD-2024-167215 | B35: 45527 | C35: 45525 | D35: =DATEDIF(C35,B35, "MD") -> 2 | E35: =TEXT(Data!B35,"MMM-YYYY") -> Aug-2024 | F35: ="Q"&ROUNDUP(MONTH(B35)/3,0)&"-"&YEAR(B35) -> Q3-2024 | G35: Africa | H35: South Africa | I35: Johannesburg | J35: Education | K35: Retail | L35: E. Garcia | M35: Components | N35: CMP-1559 | O35: 1432.52 | P35: =IF(Q35<50, "Low", IF(Q35<200, "Medium", "High")) -> High | Q35: 3036.87 | R35: 0 | S35: 9 | T35: =(Q61*S35)*(1-R35) -> 17207.01 | U35: =(O35*S35) -> 12892.68 | V35: =(T35-U35) -> 4314.33 | W35: =IF(T35=0, 0, V35/T35) -> 0.25073095
A36: ORD-2023-864121 | B36: 45012 | C36: 45038 | D36: =DATEDIF(B36,C36, "MD") -> 26 | E36: =TEXT(Data!B36,"MMM-YYYY") -> Mar-2023 | F36: ="Q"&ROUNDUP(MONTH(B36)/3,0)&"-"&YEAR(B36) -> Q1-2023 | G36: Asia | H36: India | I36: Delhi | J36: Non-Profit | K36: Marketplace | L36: J. Njeri | M36: Printers | N36: PRN-4506 | O36: 178.53 | P36: =IF(Q36<50, "Low", IF(Q36<200, "Medium", "High")) -> Medium | Q36: 199.37 | R36: 0.101 | S36: 37 | T36: =(Q62*S36)*(1-R36) -> 86276.904 | U36: =(O36*S36) -> 6605.61 | V36: =(T36-U36) -> 79671.294 | W36: =IF(T36=0, 0, V36/T36) -> 0.9234371
A37: ORD-2024-692673 | B37: 45358 | C37: 45376 | D37: =DATEDIF(B37,C37, "MD") -> 18 | E37: =TEXT(Data!B37,"MMM-YYYY") -> Mar-2024 | F37: ="Q"&ROUNDUP(MONTH(B37)/3,0)&"-"&YEAR(B37) -> Q1-2024 | G37: Europe | H37: Germany | I37: Munich | J37: Corporate | K37: Online | L37: B. Chen | M37: Components | N37: CMP-7617 | O37: 712.84 | P37: =IF(Q37<50, "Low", IF(Q37<200, "Medium", "High")) -> High | Q37: 927.51 | R37: 0.243 | S37: 27 | T37: =(Q63*S37)*(1-R37) -> 25427.751 | U37: =(O37*S37) -> 19246.68 | V37: =(T37-U37) -> 6181.0711 | W37: =IF(T37=0, 0, V37/T37) -> 0.24308367
A38: ORD-2025-718992 | B38: 45832 | C38: 45848 | D38: =DATEDIF(B38,C38, "MD") -> 16 | E38: =TEXT(Data!B38,"MMM-YYYY") -> Jun-2025 | F38: ="Q"&ROUNDUP(MONTH(B38)/3,0)&"-"&YEAR(B38) -> Q2-2025 | G38: Asia | H38: China | I38: Shanghai | J38: Enterprise | K38: Direct | L38: N. Brown | M38: Components | N38: CMP-8390 | O38: 757.19 | P38: =IF(Q38<50, "Low", IF(Q38<200, "Medium", "High")) -> High | Q38: 1735.41 | R38: 0.136 | S38: 8 | T38: =(Q64*S38)*(1-R38) -> 13219.269 | U38: =(O38*S38) -> 6057.52 | V38: =(T38-U38) -> 7161.7491 | W38: =IF(T38=0, 0, V38/T38) -> 0.54176589
A39: ORD-2024-599522 | B39: 45401 | C39: 45418 | D39: =DATEDIF(B39,C39, "MD") -> 17 | E39: =TEXT(Data!B39,"MMM-YYYY") -> Apr-2024 | F39: ="Q"&ROUNDUP(MONTH(B39)/3,0)&"-"&YEAR(B39) -> Q2-2024 | G39: Africa | H39: Nigeria | I39: Port Harcourt | J39: Non-Profit | K39: Online | L39: A. Patel | M39: Printers | N39: PRN-7303 | O39: 865.33 | P39: =IF(Q39<50, "Low", IF(Q39<200, "Medium", "High")) -> High | Q39: 1395.64 | R39: 0.175 | S39: 13 | T39: =(Q65*S39)*(1-R39) -> 8106.7057 | U39: =(O39*S39) -> 11249.29 | V39: =(T39-U39) -> -3142.5843 | W39: =IF(T39=0, 0, V39/T39) -> -0.38765244
A40: ORD-2023-651638 | B40: 45094 | C40: 45101 | D40: =DATEDIF(B40,C40, "MD") -> 7 | E40: =TEXT(Data!B40,"MMM-YYYY") -> Jun-2023 | F40: ="Q"&ROUNDUP(MONTH(B40)/3,0)&"-"&YEAR(B40) -> Q2-2023 | G40: Americas | H40: USA | I40: San Francisco | J40: Corporate | K40: Retail | L40: I. Johnson | M40: Printers | N40: PRN-6536 | O40: 313.99 | P40: =IF(Q40<50, "Low", IF(Q40<200, "Medium", "High")) -> High | Q40: 454.42 | R40: 0.129 | S40: 9 | T40: =(Q66*S40)*(1-R40) -> 8980.9071 | U40: =(O40*S40) -> 2825.91 | V40: =(T40-U40) -> 6154.9971 | W40: =IF(T40=0, 0, V40/T40) -> 0.68534248
A41: ORD-2024-635626 | B41: 45531 | C41: 45554 | D41: =DATEDIF(B41,C41, "MD") -> 23 | E41: =TEXT(Data!B41,"MMM-YYYY") -> Aug-2024 | F41: ="Q"&ROUNDUP(MONTH(B41)/3,0)&"-"&YEAR(B41) -> Q3-2024 | G41: Europe | H41: Germany | I41: Berlin | J41: Small Business | K41: Direct | L41: D. Smith | M41: Monitors | N41: MON-9967 | O41: 1024.01 | P41: =IF(Q41<50, "Low", IF(Q41<200, "Medium", "High")) -> High | Q41: 1580.97 | R41: 0.037 | S41: 27 | T41: =(Q67*S41)*(1-R41) -> 32087.834 | U41: =(O41*S41) -> 27648.27 | V41: =(T41-U41) -> 4439.5641 | W41: =IF(T41=0, 0, V41/T41) -> 0.13835661
A42: ORD-2024-296582 | B42: 45302 | C42: 45324 | D42: =DATEDIF(B42,C42, "MD") -> 22 | E42: =TEXT(Data!B42,"MMM-YYYY") -> Jan-2024 | F42: ="Q"&ROUNDUP(MONTH(B42)/3,0)&"-"&YEAR(B42) -> Q1-2024 | G42: Africa | H42: South Africa | I42: Durban | J42: Consumer | K42: Online | L42: K. Singh | M42: Networking | N42: NET-1412 | O42: 1206.2 | P42: =IF(Q42<50, "Low", IF(Q42<200, "Medium", "High")) -> High | Q42: 1759.79 | R42: 0 | S42: 6 | T42: =(Q68*S42)*(1-R42) -> 7368.06 | U42: =(O42*S42) -> 7237.2 | V42: =(T42-U42) -> 130.86 | W42: =IF(T42=0, 0, V42/T42) -> 0.017760442
A43: ORD-2024-998320 | B43: 45590 | C43: 45610 | D43: =DATEDIF(B43,C43, "MD") -> 20 | E43: =TEXT(Data!B43,"MMM-YYYY") -> Oct-2024 | F43: ="Q"&ROUNDUP(MONTH(B43)/3,0)&"-"&YEAR(B43) -> Q4-2024 | G43: Africa | H43: Kenya | I43: Mombasa | J43: Corporate | K43: Direct | L43: H. Kim | M43: Printers | N43: PRN-3143 | O43: 1396.48 | P43: =IF(Q43<50, "Low", IF(Q43<200, "Medium", "High")) -> High | Q43: 3204.5 | R43: 0.318 | S43: 14 | T43: =(Q69*S43)*(1-R43) -> 5778.736 | U43: =(O43*S43) -> 19550.72 | V43: =(T43-U43) -> -13771.984 | W43: =IF(T43=0, 0, V43/T43) -> -2.3832173
A44: ORD-2025-820255 | B44: 45806 | C44: 45828 | D44: =DATEDIF(B44,C44, "MD") -> 22 | E44: =TEXT(Data!B44,"MMM-YYYY") -> May-2025 | F44: ="Q"&ROUNDUP(MONTH(B44)/3,0)&"-"&YEAR(B44) -> Q2-2025 | G44: Europe | H44: Germany | I44: Berlin | J44: Corporate | K44: Direct | L44: A. Patel | M44: Printers | N44: PRN-9787 | O44: 483.47 | P44: =IF(Q44<50, "Low", IF(Q44<200, "Medium", "High")) -> High | Q44: 1135.43 | R44: 0.146 | S44: 11 | T44: =(Q70*S44)*(1-R44) -> 17662.129 | U44: =(O44*S44) -> 5318.17 | V44: =(T44-U44) -> 12343.959 | W44: =IF(T44=0, 0, V44/T44) -> 0.69889417
A45: ORD-2024-389336 | B45: 45432 | C45: 45445 | D45: =DATEDIF(B45,C45, "MD") -> 13 | E45: =TEXT(Data!B45,"MMM-YYYY") -> May-2024 | F45: ="Q"&ROUNDUP(MONTH(B45)/3,0)&"-"&YEAR(B45) -> Q2-2024 | G45: Americas | H45: Canada | I45: Vancouver | J45: Enterprise | K45: Marketplace | L45: K. Singh | M45: Components | N45: CMP-5946 | O45: 675.43 | P45: =IF(Q45<50, "Low", IF(Q45<200, "Medium", "High")) -> High | Q45: 996.36 | R45: 0.182 | S45: 22 | T45: =(Q71*S45)*(1-R45) -> 22844.122 | U45: =(O45*S45) -> 14859.46 | V45: =(T45-U45) -> 7984.6624 | W45: =IF(T45=0, 0, V45/T45) -> 0.34952809
A46: ORD-2023-308124 | B46: 45035 | C46: 45046 | D46: =DATEDIF(B46,C46, "MD") -> 11 | E46: =TEXT(Data!B46,"MMM-YYYY") -> Apr-2023 | F46: ="Q"&ROUNDUP(MONTH(B46)/3,0)&"-"&YEAR(B46) -> Q2-2023 | G46: Asia | H46: India | I46: Delhi | J46: Small Business | K46: Retail | L46: A. Patel | M46: Networking | N46: NET-2062 | O46: 826.55 | P46: =IF(Q46<50, "Low", IF(Q46<200, "Medium", "High")) -> High | Q46: 1397.05 | R46: 0.169 | S46: 28 | T46: =(Q72*S46)*(1-R46) -> 14447.799 | U46: =(O46*S46) -> 23143.4 | V46: =(T46-U46) -> -8695.6008 | W46: =IF(T46=0, 0, V46/T46) -> -0.60186334
A47: ORD-2023-128295 | B47: 45100 | C47: 45110 | D47: =DATEDIF(B47,C47, "MD") -> 10 | E47: =TEXT(Data!B47,"MMM-YYYY") -> Jun-2023 | F47: ="Q"&ROUNDUP(MONTH(B47)/3,0)&"-"&YEAR(B47) -> Q2-2023 | G47: Africa | H47: Nigeria | I47: Abuja | J47: Consumer | K47: Online | L47: J. Njeri | M47: Printers | N47: PRN-2542 | O47: 337.75 | P47: =IF(Q47<50, "Low", IF(Q47<200, "Medium", "High")) -> High | Q47: 548.89 | R47: 0 | S47: 13 | T47: =(Q73*S47)*(1-R47) -> 18926.83 | U47: =(O47*S47) -> 4390.75 | V47: =(T47-U47) -> 14536.08 | W47: =IF(T47=0, 0, V47/T47) -> 0.76801451
... A74: ORD-2024-800947 | B74: 45641 | C74: 45646 | D74: =DATEDIF(B74,C74, "MD") -> 5 | E74: =TEXT(Data!B74,"MMM-YYYY") -> Dec-2024 | F74: ="Q"&ROUNDUP(MONTH(B74)/3,0)&"-"&YEAR(B74) -> Q4-2024 | G74: Asia | H74: China | I74: Shenzhen | J74: Small Business | K74: Direct | L74: J. Njeri | M74: Networking | N74: NET-1846 | O74: 717.55 | P74: =IF(Q74<50, "Low", IF(Q74<200, "Medium", "High")) -> High | Q74: 546.43 | R74: 0.047 | S74: 18 | T74: =(Q100*S74)*(1-R74) -> 34328.07 | U74: =(O74*S74) -> 12915.9 | V74: =(T74-U74) -> 21412.17 | W74: =IF(T74=0, 0, V74/T74) -> 0.62375106
A75: ORD-2023-382272 | B75: 45066 | C75: 45064 | D75: =DATEDIF(C75,B75, "MD") -> 2 | E75: =TEXT(Data!B75,"MMM-YYYY") -> May-2023 | F75: ="Q"&ROUNDUP(MONTH(B75)/3,0)&"-"&YEAR(B75) -> Q2-2023 | G75: Africa | H75: South Africa | I75: Durban | J75: Corporate | K75: Distributor | L75: A. Patel | M75: Components | N75: CMP-5208 | O75: 917.88 | P75: =IF(Q75<50, "Low", IF(Q75<200, "Medium", "High")) -> High | Q75: 1347.92 | R75: 0.343 | S75: 5 | T75: =(Q101*S75)*(1-R75) -> 10198.972 | U75: =(O75*S75) -> 4589.4 | V75: =(T75-U75) -> 5609.5724 | W75: =IF(T75=0, 0, V75/T75) -> 0.55001349
A76: ORD-2023-722117 | B76: 45187 | C76: 45207 | D76: =DATEDIF(B76,C76, "MD") -> 20 | E76: =TEXT(Data!B76,"MMM-YYYY") -> Sep-2023 | F76: ="Q"&ROUNDUP(MONTH(B76)/3,0)&"-"&YEAR(B76) -> Q3-2023 | G76: Asia | H76: India | I76: Delhi | J76: Small Business | K76: Direct | L76: B. Chen | M76: Components | N76: CMP-1009 | O76: 825.64 | P76: =IF(Q76<50, "Low", IF(Q76<200, "Medium", "High")) -> High | Q76: 1108.43 | R76: 0.114 | S76: 7 | T76: =(Q102*S76)*(1-R76) -> 2073.2046 | U76: =(O76*S76) -> 5779.48 | V76: =(T76-U76) -> -3706.2754 | W76: =IF(T76=0, 0, V76/T76) -> -1.7877037
A77: ORD-2024-446699 | B77: 45532 | C77: 45560 | D77: =DATEDIF(B77,C77, "MD") -> 28 | E77: =TEXT(Data!B77,"MMM-YYYY") -> Aug-2024 | F77: ="Q"&ROUNDUP(MONTH(B77)/3,0)&"-"&YEAR(B77) -> Q3-2024 | G77: Americas | H77: Brazil | I77: Rio de Janeiro | J77: Non-Profit | K77: Online | L77: Not Provided | M77: Accessories | N77: ACC-4490 | O77: 1394.65 | P77: =IF(Q77<50, "Low", IF(Q77<200, "Medium", "High")) -> High | Q77: 3144.1 | R77: 0.134 | S77: 13 | T77: =(Q103*S77)*(1-R77) -> 21984.96 | U77: =(O77*S77) -> 18130.45 | V77: =(T77-U77) -> 3854.5101 | W77: =IF(T77=0, 0, V77/T77) -> 0.17532486
A78: ORD-2024-451005 | B78: 45473 | C78: 45471 | D78: =DATEDIF(C78,B78, "MD") -> 2 | E78: =TEXT(Data!B78,"MMM-YYYY") -> Jun-2024 | F78: ="Q"&ROUNDUP(MONTH(B78)/3,0)&"-"&YEAR(B78) -> Q2-2024 | G78: Americas | H78: Brazil | I78: Rio de Janeiro | J78: Small Business | K78: Direct | L78: L. Okafor | M78: Accessories | N78: ACC-9162 | O78: 1112.98 | P78: =IF(Q78<50, "Low", IF(Q78<200, "Medium", "High")) -> High | Q78: 2095.73 | R78: 0.072 | S78: 17 | T78: =(Q104*S78)*(1-R78) -> 3822.367 | U78: =(O78*S78) -> 18920.66 | V78: =(T78-U78) -> -15098.293 | W78: =IF(T78=0, 0, V78/T78) -> -3.9499851
A79: ORD-2023-290279 | B79: 45091 | C79: 45093 | D79: =DATEDIF(B79,C79, "MD") -> 2 | E79: =TEXT(Data!B79,"MMM-YYYY") -> Jun-2023 | F79: ="Q"&ROUNDUP(MONTH(B79)/3,0)&"-"&YEAR(B79) -> Q2-2023 | G79: Europe | H79: United Kingdom | I79: Manchester | J79: Non-Profit | K79: Direct | L79: K. Singh | M79: Components | N79: CMP-5820 | O79: 357.36 | P79: =IF(Q79<50, "Low", IF(Q79<200, "Medium", "High")) -> High | Q79: 703.62 | R79: 0.257 | S79: 20 | T79: =(Q105*S79)*(1-R79) -> 44117.408 | U79: =(O79*S79) -> 7147.2 | V79: =(T79-U79) -> 36970.208 | W79: =IF(T79=0, 0, V79/T79) -> 0.83799592
A80: ORD-2024-192263 | B80: 45617 | C80: 45647 | D80: =DATEDIF(B80,C80, "MD") -> 0 | E80: =TEXT(Data!B80,"MMM-YYYY") -> Nov-2024 | F80: ="Q"&ROUNDUP(MONTH(B80)/3,0)&"-"&YEAR(B80) -> Q4-2024 | G80: Europe | H80: France | I80: Marseille | J80: Small Business | K80: Direct | L80: I. Johnson | M80: Monitors | N80: MON-7943 | O80: 1122.68 | P80: =IF(Q80<50, "Low", IF(Q80<200, "Medium", "High")) -> High | Q80: 1997.19 | R80: 0.186 | S80: 3 | T80: =(Q106*S80)*(1-R80) -> 3404.8806 | U80: =(O80*S80) -> 3368.04 | V80: =(T80-U80) -> 36.8406 | W80: =IF(T80=0, 0, V80/T80) -> 0.010819939
A81: ORD-2023-159379 | B81: 44965 | C81: 44968 | D81: =DATEDIF(B81,C81, "MD") -> 3 | E81: =TEXT(Data!B81,"MMM-YYYY") -> Feb-2023 | F81: ="Q"&ROUNDUP(MONTH(B81)/3,0)&"-"&YEAR(B81) -> Q1-2023 | G81: Africa | H81: South Africa | I81: Cape Town | J81: Corporate | K81: Direct | L81: M. Rossi | M81: Networking | N81: NET-5018 | O81: 1410.05 | P81: =IF(Q81<50, "Low", IF(Q81<200, "Medium", "High")) -> High | Q81: 2763.95 | R81: 0.161 | S81: 26 | T81: =(Q107*S81)*(1-R81) -> 336.15374 | U81: =(O81*S81) -> 36661.3 | V81: =(T81-U81) -> -36325.146 | W81: =IF(T81=0, 0, V81/T81) -> -108.06111
A82: ORD-2023-343322 | B82: 45157 | C82: 45181 | D82: =DATEDIF(B82,C82, "MD") -> 24 | E82: =TEXT(Data!B82,"MMM-YYYY") -> Aug-2023 | F82: ="Q"&ROUNDUP(MONTH(B82)/3,0)&"-"&YEAR(B82) -> Q3-2023 | G82: Americas | H82: Canada | I82: Vancouver | J82: Enterprise | K82: Retail | L82: I. Johnson | M82: Printers | N82: PRN-9669 | O82: 1183.95 | P82: =IF(Q82<50, "Low", IF(Q82<200, "Medium", "High")) -> High | Q82: 1503.53 | R82: 0.241 | S82: 16 | T82: =(Q108*S82)*(1-R82) -> 27333.837 | U82: =(O82*S82) -> 18943.2 | V82: =(T82-U82) -> 8390.6366 | W82: =IF(T82=0, 0, V82/T82) -> 0.30696886
A83: ORD-2025-114382 | B83: 45791 | C83: 45801 | D83: =DATEDIF(B83,C83, "MD") -> 10 | E83: =TEXT(Data!B83,"MMM-YYYY") -> May-2025 | F83: ="Q"&ROUNDUP(MONTH(B83)/3,0)&"-"&YEAR(B83) -> Q2-2025 | G83: Europe | H83: France | I83: Paris | J83: Small Business | K83: Marketplace | L83: K. Singh | M83: Components | N83: CMP-2865 | O83: 170.39 | P83: =IF(Q83<50, "Low", IF(Q83<200, "Medium", "High")) -> High | Q83: 388.04 | R83: 0.084 | S83: 15 | T83: =(Q109*S83)*(1-R83) -> 2281.3896 | U83: =(O83*S83) -> 2555.85 | V83: =(T83-U83) -> -274.4604 | W83: =IF(T83=0, 0, V83/T83) -> -0.12030405
A84: ORD-2025-488349 | B84: 45770 | C84: 45769 | D84: =DATEDIF(C84,B84, "MD") -> 1 | E84: =TEXT(Data!B84,"MMM-YYYY") -> Apr-2025 | F84: ="Q"&ROUNDUP(MONTH(B84)/3,0)&"-"&YEAR(B84) -> Q2-2025 | G84: Americas | H84: USA | I84: San Francisco | J84: Non-Profit | K84: Distributor | L84: D. Smith | M84: Monitors | N84: MON-3371 | O84: 23.24 | P84: =IF(Q84<50, "Low", IF(Q84<200, "Medium", "High")) -> Low | Q84: 44.57 | R84: 0.215 | S84: 15 | T84: =(Q110*S84)*(1-R84) -> 4198.3763 | U84: =(O84*S84) -> 348.6 | V84: =(T84-U84) -> 3849.7763 | W84: =IF(T84=0, 0, V84/T84) -> 0.9169679
A85: ORD-2025-330203 | B85: 45741 | C85: 45764 | D85: =DATEDIF(B85,C85, "MD") -> 23 | E85: =TEXT(Data!B85,"MMM-YYYY") -> Mar-2025 | F85: ="Q"&ROUNDUP(MONTH(B85)/3,0)&"-"&YEAR(B85) -> Q1-2025 | G85: Europe | H85: United Kingdom | I85: London | J85: Consumer | K85: Retail | L85: H. Kim | M85: Networking | N85: NET-7166 | O85: 1421.19 | P85: =IF(Q85<50, "Low", IF(Q85<200, "Medium", "High")) -> High | Q85: 1808.26 | R85: 0.104 | S85: 13 | T85: =(Q111*S85)*(1-R85) -> 11939.782 | U85: =(O85*S85) -> 18475.47 | V85: =(T85-U85) -> -6535.6876 | W85: =IF(T85=0, 0, V85/T85) -> -0.5473875
A86: ORD-2023-841426 | B86: 45282 | C86: 45283 | D86: =DATEDIF(B86,C86, "MD") -> 1 | E86: =TEXT(Data!B86,"MMM-YYYY") -> Dec-2023 | F86: ="Q"&ROUNDUP(MONTH(B86)/3,0)&"-"&YEAR(B86) -> Q4-2023 | G86: Africa | H86: South Africa | I86: Cape Town | J86: Non-Profit | K86: Marketplace | L86: D. Smith | M86: Components | N86: CMP-4531 | O86: 1186.18 | P86: =IF(Q86<50, "Low", IF(Q86<200, "Medium", "High")) -> High | Q86: 1285.09 | R86: 0.07 | S86: 11 | T86: =(Q112*S86)*(1-R86) -> 18364.589 | U86: =(O86*S86) -> 13047.98 | V86: =(T86-U86) -> 5316.6091 | W86: =IF(T86=0, 0, V86/T86) -> 0.2895033
A87: ORD-2024-594592 | B87: 45388 | C87: 45407 | D87: =DATEDIF(B87,C87, "MD") -> 19 | E87: =TEXT(Data!B87,"MMM-YYYY") -> Apr-2024 | F87: ="Q"&ROUNDUP(MONTH(B87)/3,0)&"-"&YEAR(B87) -> Q2-2024 | G87: Asia | H87: China | I87: Shanghai | J87: Corporate | K87: Retail | L87: K. Singh | M87: Components | N87: CMP-8196 | O87: 1366.48 | P87: =IF(Q87<50, "Low", IF(Q87<200, "Medium", "High")) -> High | Q87: 1678.14 | R87: 0.154 | S87: 10 | T87: =(Q113*S87)*(1-R87) -> 36.9702 | U87: =(O87*S87) -> 13664.8 | V87: =(T87-U87) -> -13627.83 | W87: =IF(T87=0, 0, V87/T87) -> -368.61661
A88: ORD-2025-863978 | B88: 45876 | C88: 45888 | D88: =DATEDIF(B88,C88, "MD") -> 12 | E88: =TEXT(Data!B88,"MMM-YYYY") -> Aug-2025 | F88: ="Q"&ROUNDUP(MONTH(B88)/3,0)&"-"&YEAR(B88) -> Q3-2025 | G88: Africa | H88: Kenya | I88: Nakuru | J88: Corporate | K88: Not Provided | L88: M. Rossi | M88: Components | N88: CMP-2854 | O88: 601.51 | P88: =IF(Q88<50, "Low", IF(Q88<200, "Medium", "High")) -> High | Q88: 679.35 | R88: 0.188 | S88: 3 | T88: =(Q114*S88)*(1-R88) -> 532.266 | U88: =(O88*S88) -> 1804.53 | V88: =(T88-U88) -> -1272.264 | W88: =IF(T88=0, 0, V88/T88) -> -2.3902785
A89: ORD-2024-604471 | B89: 45312 | C89: 45316 | D89: =DATEDIF(B89,C89, "MD") -> 4 | E89: =TEXT(Data!B89,"MMM-YYYY") -> Jan-2024 | F89: ="Q"&ROUNDUP(MONTH(B89)/3,0)&"-"&YEAR(B89) -> Q1-2024 | G89: Asia | H89: India | I89: Delhi | J89: Consumer | K89: Direct | L89: C. Otieno | M89: Monitors | N89: MON-8973 | O89: 523.7 | P89: =IF(Q89<50, "Low", IF(Q89<200, "Medium", "High")) -> High | Q89: 1109.92 | R89: 0.03 | S89: 11 | T89: =(Q115*S89)*(1-R89) -> 2666.1129 | U89: =(O89*S89) -> 5760.7 | V89: =(T89-U89) -> -3094.5871 | W89: =IF(T89=0, 0, V89/T89) -> -1.1607112
A90: ORD-2023-258768 | B90: 45106 | C90: 45109 | D90: =DATEDIF(B90,C90, "MD") -> 3 | E90: =TEXT(Data!B90,"MMM-YYYY") -> Jun-2023 | F90: ="Q"&ROUNDUP(MONTH(B90)/3,0)&"-"&YEAR(B90) -> Q2-2023 | G90: Asia | H90: Japan | I90: Nagoya | J90: Education | K90: Marketplace | L90: F. Müller | M90: Monitors | N90: MON-2990 | O90: 55.65 | P90: =IF(Q90<50, "Low", IF(Q90<200, "Medium", "High")) -> Medium | Q90: 83.57 | R90: 0.066 | S90: 8 | T90: =(Q116*S90)*(1-R90) -> 25677.677 | U90: =(O90*S90) -> 445.2 | V90: =(T90-U90) -> 25232.477 | W90: =IF(T90=0, 0, V90/T90) -> 0.98266198
A91: ORD-2025-626047 | B91: 45775 | C91: 45792 | D91: =DATEDIF(B91,C91, "MD") -> 17 | E91: =TEXT(Data!B91,"MMM-YYYY") -> Apr-2025 | F91: ="Q"&ROUNDUP(MONTH(B91)/3,0)&"-"&YEAR(B91) -> Q2-2025 | G91: Asia | H91: Japan | I91: Nagoya | J91: Education | K91: Direct | L91: N. Brown | M91: Networking | N91: NET-1966 | O91: 691.19 | P91: =IF(Q91<50, "Low", IF(Q91<200, "Medium", "High")) -> High | Q91: 1284.3 | R91: 0.074 | S91: 7 | T91: =(Q117*S91)*(1-R91) -> 346.4629 | U91: =(O91*S91) -> 4838.33 | V91: =(T91-U91) -> -4491.8671 | W91: =IF(T91=0, 0, V91/T91) -> -12.96493
A92: ORD-2025-526752 | B92: 45817 | C92: 45833 | D92: =DATEDIF(B92,C92, "MD") -> 16 | E92: =TEXT(Data!B92,"MMM-YYYY") -> Jun-2025 | F92: ="Q"&ROUNDUP(MONTH(B92)/3,0)&"-"&YEAR(B92) -> Q2-2025 | G92: Asia | H92: India | I92: Hyderabad | J92: Enterprise | K92: Distributor | L92: M. Rossi | M92: Phones | N92: PHN-3482 | O92: 527.33 | P92: =IF(Q92<50, "Low", IF(Q92<200, "Medium", "High")) -> High | Q92: 911.72 | R92: 0.144 | S92: 25 | T92: =(Q118*S92)*(1-R92) -> 74251.58 | U92: =(O92*S92) -> 13183.25 | V92: =(T92-U92) -> 61068.33 | W92: =IF(T92=0, 0, V92/T92) -> 0.82245159
A93: ORD-2023-374486 | B93: 45101 | C93: 45100 | D93: =DATEDIF(C93,B93, "MD") -> 1 | E93: =TEXT(Data!B93,"MMM-YYYY") -> Jun-2023 | F93: ="Q"&ROUNDUP(MONTH(B93)/3,0)&"-"&YEAR(B93) -> Q2-2023 | G93: Americas | H93: Brazil | I93: Rio de Janeiro | J93: Non-Profit | K93: Retail | L93: E. Garcia | M93: Printers | N93: PRN-6490 | O93: 804.01 | P93: =IF(Q93<50, "Low", IF(Q93<200, "Medium", "High")) -> High | Q93: 1405.07 | R93: 0.096 | S93: 8 | T93: =(Q119*S93)*(1-R93) -> 4491.2166 | U93: =(O93*S93) -> 6432.08 | V93: =(T93-U93) -> -1940.8634 | W93: =IF(T93=0, 0, V93/T93) -> -0.43214646
A94: ORD-2024-997336 | B94: 45569 | C94: 45598 | D94: =DATEDIF(B94,C94, "MD") -> 29 | E94: =TEXT(Data!B94,"MMM-YYYY") -> Oct-2024 | F94: ="Q"&ROUNDUP(MONTH(B94)/3,0)&"-"&YEAR(B94) -> Q4-2024 | G94: Africa | H94: Nigeria | I94: Abuja | J94: Corporate | K94: Distributor | L94: F. Müller | M94: Accessories | N94: ACC-9038 | O94: 412.09 | P94: =IF(Q94<50, "Low", IF(Q94<200, "Medium", "High")) -> High | Q94: 968.94 | R94: 0.099 | S94: 23 | T94: =(Q120*S94)*(1-R94) -> 1834.1927 | U94: =(O94*S94) -> 9478.07 | V94: =(T94-U94) -> -7643.8773 | W94: =IF(T94=0, 0, V94/T94) -> -4.1674341
A95: ORD-2025-725646 | B95: 45910 | C95: 45930 | D95: =DATEDIF(B95,C95, "MD") -> 20 | E95: =TEXT(Data!B95,"MMM-YYYY") -> Sep-2025 | F95: ="Q"&ROUNDUP(MONTH(B95)/3,0)&"-"&YEAR(B95) -> Q3-2025 | G95: Africa | H95: Kenya | I95: Mombasa | J95: Corporate | K95: Direct | L95: L. Okafor | M95: Phones | N95: PHN-6954 | O95: 1009.48 | P95: =IF(Q95<50, "Low", IF(Q95<200, "Medium", "High")) -> High | Q95: 1088.81 | R95: 0.16 | S95: 6 | T95: =(Q121*S95)*(1-R95) -> 9873.8136 | U95: =(O95*S95) -> 6056.88 | V95: =(T95-U95) -> 3816.9336 | W95: =IF(T95=0, 0, V95/T95) -> 0.38657136
A96: ORD-2023-868734 | B96: 45022 | C96: 45043 | D96: =DATEDIF(B96,C96, "MD") -> 21 | E96: =TEXT(Data!B96,"MMM-YYYY") -> Apr-2023 | F96: ="Q"&ROUNDUP(MONTH(B96)/3,0)&"-"&YEAR(B96) -> Q2-2023 | G96: Europe | H96: United Kingdom | I96: Manchester | J96: Enterprise | K96: Distributor | L96: I. Johnson | M96: Printers | N96: PRN-8970 | O96: 1084.79 | P96: =IF(Q96<50, "Low", IF(Q96<200, "Medium", "High")) -> High | Q96: 2484.99 | R96: 0.034 | S96: 18 | T96: =(Q122*S96)*(1-R96) -> 47694.762 | U96: =(O96*S96) -> 19526.22 | V96: =(T96-U96) -> 28168.542 | W96: =IF(T96=0, 0, V96/T96) -> 0.59060033
A97: ORD-2025-262491 | B97: 45870 | C97: 45885 | D97: =DATEDIF(B97,C97, "MD") -> 15 | E97: =TEXT(Data!B97,"MMM-YYYY") -> Aug-2025 | F97: ="Q"&ROUNDUP(MONTH(B97)/3,0)&"-"&YEAR(B97) -> Q3-2025 | G97: Asia | H97: India | I97: Not Provided | J97: Enterprise | K97: Direct | L97: O. Wang | M97: Monitors | N97: MON-1822 | O97: 24.44 | P97: =IF(Q97<50, "Low", IF(Q97<200, "Medium", "High")) -> Low | Q97: 28.69 | R97: 0.146 | S97: 6 | T97: =(Q123*S97)*(1-R97) -> 8605.3481 | U97: =(O97*S97) -> 146.64 | V97: =(T97-U97) -> 8458.7081 | W97: =IF(T97=0, 0, V97/T97) -> 0.98295943
A98: ORD-2024-638884 | B98: 45440 | C98: 45438 | D98: =DATEDIF(C98,B98, "MD") -> 2 | E98: =TEXT(Data!B98,"MMM-YYYY") -> May-2024 | F98: ="Q"&ROUNDUP(MONTH(B98)/3,0)&"-"&YEAR(B98) -> Q2-2024 | G98: Africa | H98: Nigeria | I98: Abuja | J98: Enterprise | K98: Online | L98: F. Müller | M98: Accessories | N98: ACC-5177 | O98: 1227.08 | P98: =IF(Q98<50, "Low", IF(Q98<200, "Medium", "High")) -> High | Q98: 1896.62 | R98: 0 | S98: 18 | T98: =(Q124*S98)*(1-R98) -> 25810.2 | U98: =(O98*S98) -> 22087.44 | V98: =(T98-U98) -> 3722.76 | W98: =IF(T98=0, 0, V98/T98) -> 0.144236
A99: ORD-2025-541501 | B99: 45860 | C99: 45887 | D99: =DATEDIF(B99,C99, "MD") -> 27 | E99: =TEXT(Data!B99,"MMM-YYYY") -> Jul-2025 | F99: ="Q"&ROUNDUP(MONTH(B99)/3,0)&"-"&YEAR(B99) -> Q3-2025 | G99: Asia | H99: China | I99: Shenzhen | J99: Non-Profit | K99: Marketplace | L99: M. Rossi | M99: Networking | N99: NET-1804 | O99: 547.32 | P99: =IF(Q99<50, "Low", IF(Q99<200, "Medium", "High")) -> High | Q99: 419.17 | R99: 0.092 | S99: 14 | T99: =(Q125*S99)*(1-R99) -> 3615.6742 | U99: =(O99*S99) -> 7662.48 | V99: =(T99-U99) -> -4046.8058 | W99: =IF(T99=0, 0, V99/T99) -> -1.1192396
A100: ORD-2023-422918 | B100: 44985 | C100: 45005 | D100: =DATEDIF(B100,C100, "MD") -> 20 | E100: =TEXT(Data!B100,"MMM-YYYY") -> Feb-2023 | F100: ="Q"&ROUNDUP(MONTH(B100)/3,0)&"-"&YEAR(B100) -> Q1-2023 | G100: Europe | H100: Germany | I100: Berlin | J100: Small Business | K100: Direct | L100: H. Kim | M100: Laptops | N100: LAP-3679 | O100: 1200.78 | P100: =IF(Q100<50, "Low", IF(Q100<200, "Medium", "High")) -> High | Q100: 2001.17 | R100: 0.292 | S100: 18 | T100: =(Q126*S100)*(1-R100) -> 8854.2763 | U100: =(O100*S100) -> 21614.04 | V100: =(T100-U100) -> -12759.764 | W100: =IF(T100=0, 0, V100/T100) -> -1.4410849
A101: ORD-2025-328504 | B101: 45684 | C101: 45703 | D101: =DATEDIF(B101,C101, "MD") -> 19 | E101: =TEXT(Data!B101,"MMM-YYYY") -> Jan-2025 | F101: ="Q"&ROUNDUP(MONTH(B101)/3,0)&"-"&YEAR(B101) -> Q1-2025 | G101: Asia | H101: China | I101: Shenzhen | J101: Non-Profit | K101: Direct | L101: L. Okafor | M101: Phones | N101: PHN-8368 | O101: 1253.22 | P101: =IF(Q101<50, "Low", IF(Q101<200, "Medium", "High")) -> High | Q101: 3104.71 | R101: 0 | S101: 17 | T101: =(Q127*S101)*(1-R101) -> 31422.63 | U101: =(O101*S101) -> 21304.74 | V101: =(T101-U101) -> 10117.89 | W101: =IF(T101=0, 0, V101/T101) -> 0.32199374
A102: ORD-2024-851883 | B102: 45304 | C102: 45313 | D102: =DATEDIF(B102,C102, "MD") -> 9 | E102: =TEXT(Data!B102,"MMM-YYYY") -> Jan-2024 | F102: ="Q"&ROUNDUP(MONTH(B102)/3,0)&"-"&YEAR(B102) -> Q1-2024 | G102: Asia | H102: India | I102: Mumbai | J102: Enterprise | K102: Marketplace | L102: J. Njeri | M102: Components | N102: CMP-8141 | O102: 313.6 | P102: =IF(Q102<50, "Low", IF(Q102<200, "Medium", "High")) -> High | Q102: 334.28 | R102: 0.14 | S102: 22 | T102: =(Q128*S102)*(1-R102) -> 854.9948 | U102: =(O102*S102) -> 6899.2 | V102: =(T102-U102) -> -6044.2052 | W102: =IF(T102=0, 0, V102/T102) -> -7.0692888
A103: ORD-2025-662997 | B103: 45747 | C103: 45751 | D103: =DATEDIF(B103,C103, "MD") -> 4 | E103: =TEXT(Data!B103,"MMM-YYYY") -> Mar-2025 | F103: ="Q"&ROUNDUP(MONTH(B103)/3,0)&"-"&YEAR(B103) -> Q1-2025 | G103: Africa | H103: Kenya | I103: Nakuru | J103: Corporate | K103: Direct | L103: C. Otieno | M103: Laptops | N103: LAP-7136 | O103: 862.08 | P103: =IF(Q103<50, "Low", IF(Q103<200, "Medium", "High")) -> High | Q103: 1952.83 | R103: 0 | S103: 7 | T103: =(Q129*S103)*(1-R103) -> 2527.7 | U103: =(O103*S103) -> 6034.56 | V103: =(T103-U103) -> -3506.86 | W103: =IF(T103=0, 0, V103/T103) -> -1.3873719
A104: ORD-2024-478165 | B104: 45631 | C104: 45654 | D104: =DATEDIF(B104,C104, "MD") -> 23 | E104: =TEXT(Data!B104,"MMM-YYYY") -> Dec-2024 | F104: ="Q"&ROUNDUP(MONTH(B104)/3,0)&"-"&YEAR(B104) -> Q4-2024 | G104: Americas | H104: Canada | I104: Vancouver | J104: Corporate | K104: Direct | L104: F. Müller | M104: Accessories | N104: ACC-2386 | O104: 107.03 | P104: =IF(Q104<50, "Low", IF(Q104<200, "Medium", "High")) -> High | Q104: 242.29 | R104: 0.18 | S104: 30 | T104: =(Q130*S104)*(1-R104) -> 24706.764 | U104: =(O104*S104) -> 3210.9 | V104: =(T104-U104) -> 21495.864 | W104: =IF(T104=0, 0, V104/T104) -> 0.87003964
A105: ORD-2024-771210 | B105: 45549 | C105: 45570 | D105: =DATEDIF(B105,C105, "MD") -> 21 | E105: =TEXT(Data!B105,"MMM-YYYY") -> Sep-2024 | F105: ="Q"&ROUNDUP(MONTH(B105)/3,0)&"-"&YEAR(B105) -> Q3-2024 | G105: Asia | H105: China | I105: Shanghai | J105: Small Business | K105: Online | L105: H. Kim | M105: Laptops | N105: LAP-5150 | O105: 1405.56 | P105: =IF(Q105<50, "Low", IF(Q105<200, "Medium", "High")) -> High | Q105: 2968.87 | R105: 0.169 | S105: 5 | T105: =(Q131*S105)*(1-R105) -> 4270.2181 | U105: =(O105*S105) -> 7027.8 | V105: =(T105-U105) -> -2757.5818 | W105: =IF(T105=0, 0, V105/T105) -> -0.64577072
A106: ORD-2024-155337 | B106: 45433 | C106: 45439 | D106: =DATEDIF(B106,C106, "MD") -> 6 | E106: =TEXT(Data!B106,"MMM-YYYY") -> May-2024 | F106: ="Q"&ROUNDUP(MONTH(B106)/3,0)&"-"&YEAR(B106) -> Q2-2024 | G106: Africa | H106: South Africa | I106: Johannesburg | J106: Non-Profit | K106: Online | L106: M. Rossi | M106: Components | N106: CMP-8101 | O106: 1157.51 | P106: =IF(Q106<50, "Low", IF(Q106<200, "Medium", "High")) -> High | Q106: 1394.3 | R106: 0.278 | S106: 12 | T106: =(Q132*S106)*(1-R106) -> 4055.5318 | U106: =(O106*S106) -> 13890.12 | V106: =(T106-U106) -> -9834.5882 | W106: =IF(T106=0, 0, V106/T106) -> -2.4249812
A107: ORD-2023-251563 | B107: 45057 | C107: 45084 | D107: =DATEDIF(B107,C107, "MD") -> 27 | E107: =TEXT(Data!B107,"MMM-YYYY") -> May-2023 | F107: ="Q"&ROUNDUP(MONTH(B107)/3,0)&"-"&YEAR(B107) -> Q2-2023 | G107: Africa | H107: Kenya | I107: Mombasa | J107: Corporate | K107: Online | L107: J. Njeri | M107: Phones | N107: PHN-8970 | O107: 12.85 | P107: =IF(Q107<50, "Low", IF(Q107<200, "Medium", "High")) -> Low | Q107: 15.41 | R107: 0.137 | S107: 39 | T107: =(Q133*S107)*(1-R107) -> 22483.549 | U107: =(O107*S107) -> 501.15 | V107: =(T107-U107) -> 21982.399 | W107: =IF(T107=0, 0, V107/T107) -> 0.97771037
A108: ORD-2024-286833 | B108: 45518 | C108: 45539 | D108: =DATEDIF(B108,C108, "MD") -> 21 | E108: =TEXT(Data!B108,"MMM-YYYY") -> Aug-2024 | F108: ="Q"&ROUNDUP(MONTH(B108)/3,0)&"-"&YEAR(B108) -> Q3-2024 | G108: Europe | H108: United Kingdom | I108: Manchester | J108: Non-Profit | K108: Online | L108: J. Njeri | M108: Phones | N108: PHN-2341 | O108: 1138.8 | P108: =IF(Q108<50, "Low", IF(Q108<200, "Medium", "High")) -> High | Q108: 2250.81 | R108: 0.123 | S108: 12 | T108: =(Q134*S108)*(1-R108) -> 5654.2295 | U108: =(O108*S108) -> 13665.6 | V108: =(T108-U108) -> -8011.3705 | W108: =IF(T108=0, 0, V108/T108) -> -1.416881
A109: ORD-2024-792558 | B109: 45581 | C109: 45604 | D109: =DATEDIF(B109,C109, "MD") -> 23 | E109: =TEXT(Data!B109,"MMM-YYYY") -> Oct-2024 | F109: ="Q"&ROUNDUP(MONTH(B109)/3,0)&"-"&YEAR(B109) -> Q4-2024 | G109: Asia | H109: Japan | I109: Osaka | J109: Small Business | K109: Retail | L109: J. Njeri | M109: Networking | N109: NET-6387 | O109: 82.14 | P109: =IF(Q109<50, "Low", IF(Q109<200, "Medium", "High")) -> Medium | Q109: 166.04 | R109: 0 | S109: 10 | T109: =(Q135*S109)*(1-R109) -> 5727.1 | U109: =(O109*S109) -> 821.4 | V109: =(T109-U109) -> 4905.7 | W109: =IF(T109=0, 0, V109/T109) -> 0.85657663
A110: ORD-2024-166150 | B110: 45445 | C110: 45451 | D110: =DATEDIF(B110,C110, "MD") -> 6 | E110: =TEXT(Data!B110,"MMM-YYYY") -> Jun-2024 | F110: ="Q"&ROUNDUP(MONTH(B110)/3,0)&"-"&YEAR(B110) -> Q2-2024 | G110: Africa | H110: Kenya | I110: Kisumu | J110: Consumer | K110: Marketplace | L110: A. Patel | M110: Accessories | N110: ACC-9820 | O110: 292.94 | P110: =IF(Q110<50, "Low", IF(Q110<200, "Medium", "High")) -> High | Q110: 356.55 | R110: 0.229 | S110: 2 | T110: =(Q136*S110)*(1-R110) -> 3583.4075 | U110: =(O110*S110) -> 585.88 | V110: =(T110-U110) -> 2997.5275 | W110: =IF(T110=0, 0, V110/T110) -> 0.83650199
... A145: ORD-2023-309373 | B145: 45112 | C145: 45121 | D145: =DATEDIF(B145,C145, "MD") -> 9 | E145: =TEXT(Data!B145,"MMM-YYYY") -> Jul-2023 | F145: ="Q"&ROUNDUP(MONTH(B145)/3,0)&"-"&YEAR(B145) -> Q3-2023 | G145: Americas | H145: Brazil | I145: Brasília | J145: Enterprise | K145: Direct | L145: B. Chen | M145: Networking | N145: NET-2394 | O145: 578.85 | P145: =IF(Q145<50, "Low", IF(Q145<200, "Medium", "High")) -> High | Q145: 998.76 | R145: 0.082 | S145: 28 | T145: =(Q171*S145)*(1-R145) -> 31331.12 | U145: =(O145*S145) -> 16207.8 | V145: =(T145-U145) -> 15123.32 | W145: =IF(T145=0, 0, V145/T145) -> 0.48269324
A146: ORD-2023-825495 | B146: 45260 | C146: 45259 | D146: =DATEDIF(C146,B146, "MD") -> 1 | E146: =TEXT(Data!B146,"MMM-YYYY") -> Nov-2023 | F146: ="Q"&ROUNDUP(MONTH(B146)/3,0)&"-"&YEAR(B146) -> Q4-2023 | G146: Africa | H146: South Africa | I146: Durban | J146: Small Business | K146: Marketplace | L146: E. Garcia | M146: Laptops | N146: LAP-1525 | O146: 275.56 | P146: =IF(Q146<50, "Low", IF(Q146<200, "Medium", "High")) -> High | Q146: 630.72 | R146: 0.107 | S146: 23 | T146: =(Q172*S146)*(1-R146) -> 42353.883 | U146: =(O146*S146) -> 6337.88 | V146: =(T146-U146) -> 36016.003 | W146: =IF(T146=0, 0, V146/T146) -> 0.85035894
A147: ORD-2025-244832 | B147: 45911 | C147: 45928 | D147: =DATEDIF(B147,C147, "MD") -> 17 | E147: =TEXT(Data!B147,"MMM-YYYY") -> Sep-2025 | F147: ="Q"&ROUNDUP(MONTH(B147)/3,0)&"-"&YEAR(B147) -> Q3-2025 | G147: Africa | H147: Kenya | I147: Nairobi | J147: Non-Profit | K147: Distributor | L147: J. Njeri | M147: Laptops | N147: LAP-3278 | O147: 891.46 | P147: =IF(Q147<50, "Low", IF(Q147<200, "Medium", "High")) -> High | Q147: 728.61 | R147: 0.185 | S147: 6 | T147: =(Q173*S147)*(1-R147) -> 49.7802 | U147: =(O147*S147) -> 5348.76 | V147: =(T147-U147) -> -5298.9798 | W147: =IF(T147=0, 0, V147/T147) -> -106.44754
A148: ORD-2024-211453 | B148: 45386 | C148: 45406 | D148: =DATEDIF(B148,C148, "MD") -> 20 | E148: =TEXT(Data!B148,"MMM-YYYY") -> Apr-2024 | F148: ="Q"&ROUNDUP(MONTH(B148)/3,0)&"-"&YEAR(B148) -> Q2-2024 | G148: Europe | H148: Germany | I148: Frankfurt | J148: Non-Profit | K148: Direct | L148: O. Wang | M148: Accessories | N148: ACC-6543 | O148: 683.42 | P148: =IF(Q148<50, "Low", IF(Q148<200, "Medium", "High")) -> High | Q148: 951.51 | R148: 0 | S148: 14 | T148: =(Q174*S148)*(1-R148) -> 31944.08 | U148: =(O148*S148) -> 9567.88 | V148: =(T148-U148) -> 22376.2 | W148: =IF(T148=0, 0, V148/T148) -> 0.70048034
A149: ORD-2023-192324 | B149: 45183 | C149: 45185 | D149: =DATEDIF(B149,C149, "MD") -> 2 | E149: =TEXT(Data!B149,"MMM-YYYY") -> Sep-2023 | F149: ="Q"&ROUNDUP(MONTH(B149)/3,0)&"-"&YEAR(B149) -> Q3-2023 | G149: Europe | H149: France | I149: Lyon | J149: Non-Profit | K149: Direct | L149: B. Chen | M149: Printers | N149: PRN-4432 | O149: 376.83 | P149: =IF(Q149<50, "Low", IF(Q149<200, "Medium", "High")) -> High | Q149: 732.88 | R149: 0.188 | S149: 25 | T149: =(Q175*S149)*(1-R149) -> 5066.271 | U149: =(O149*S149) -> 9420.75 | V149: =(T149-U149) -> -4354.479 | W149: =IF(T149=0, 0, V149/T149) -> -0.85950377
A150: ORD-2024-438404 | B150: 45558 | C150: 45583 | D150: =DATEDIF(B150,C150, "MD") -> 25 | E150: =TEXT(Data!B150,"MMM-YYYY") -> Sep-2024 | F150: ="Q"&ROUNDUP(MONTH(B150)/3,0)&"-"&YEAR(B150) -> Q3-2024 | G150: Americas | H150: Canada | I150: Vancouver | J150: Small Business | K150: Online | L150: N. Brown | M150: Phones | N150: PHN-4568 | O150: 1297 | P150: =IF(Q150<50, "Low", IF(Q150<200, "Medium", "High")) -> High | Q150: 2411.52 | R150: 0.021 | S150: 18 | T150: =(Q176*S150)*(1-R150) -> 57712.05 | U150: =(O150*S150) -> 23346 | V150: =(T150-U150) -> 34366.05 | W150: =IF(T150=0, 0, V150/T150) -> 0.59547443
A151: ORD-2025-246470 | B151: 45763 | C151: 45793 | D151: =DATEDIF(B151,C151, "MD") -> 0 | E151: =TEXT(Data!B151,"MMM-YYYY") -> Apr-2025 | F151: ="Q"&ROUNDUP(MONTH(B151)/3,0)&"-"&YEAR(B151) -> Q2-2025 | G151: Americas | H151: Canada | I151: Montreal | J151: Enterprise | K151: Distributor | L151: K. Singh | M151: Printers | N151: PRN-6178 | O151: 763.32 | P151: =IF(Q151<50, "Low", IF(Q151<200, "Medium", "High")) -> High | Q151: 568.29 | R151: 0.131 | S151: 16 | T151: =(Q177*S151)*(1-R151) -> 26608.919 | U151: =(O151*S151) -> 12213.12 | V151: =(T151-U151) -> 14395.799 | W151: =IF(T151=0, 0, V151/T151) -> 0.54101405
A152: ORD-2023-497686 | B152: 45110 | C152: 45130 | D152: =DATEDIF(B152,C152, "MD") -> 20 | E152: =TEXT(Data!B152,"MMM-YYYY") -> Jul-2023 | F152: ="Q"&ROUNDUP(MONTH(B152)/3,0)&"-"&YEAR(B152) -> Q3-2023 | G152: Africa | H152: South Africa | I152: Johannesburg | J152: Small Business | K152: Distributor | L152: F. Müller | M152: Laptops | N152: LAP-6342 | O152: 1001.96 | P152: =IF(Q152<50, "Low", IF(Q152<200, "Medium", "High")) -> High | Q152: 1254.95 | R152: 0.045 | S152: 18 | T152: =(Q178*S152)*(1-R152) -> 517.2471 | U152: =(O152*S152) -> 18035.28 | V152: =(T152-U152) -> -17518.033 | W152: =IF(T152=0, 0, V152/T152) -> -33.867822
A153: ORD-2023-596758 | B153: 45267 | C153: 45265 | D153: =DATEDIF(C153,B153, "MD") -> 2 | E153: =TEXT(Data!B153,"MMM-YYYY") -> Dec-2023 | F153: ="Q"&ROUNDUP(MONTH(B153)/3,0)&"-"&YEAR(B153) -> Q4-2023 | G153: Asia | H153: Japan | I153: Tokyo | J153: Non-Profit | K153: Marketplace | L153: H. Kim | M153: Printers | N153: PRN-8175 | O153: 1097.59 | P153: =IF(Q153<50, "Low", IF(Q153<200, "Medium", "High")) -> High | Q153: 845.55 | R153: 0.184 | S153: 6 | T153: =(Q179*S153)*(1-R153) -> 2454.4138 | U153: =(O153*S153) -> 6585.54 | V153: =(T153-U153) -> -4131.1262 | W153: =IF(T153=0, 0, V153/T153) -> -1.6831417
A154: ORD-2024-201376 | B154: 45340 | C154: 45355 | D154: =DATEDIF(B154,C154, "MD") -> 15 | E154: =TEXT(Data!B154,"MMM-YYYY") -> Feb-2024 | F154: ="Q"&ROUNDUP(MONTH(B154)/3,0)&"-"&YEAR(B154) -> Q1-2024 | G154: Africa | H154: Kenya | I154: Kisumu | J154: Education | K154: Direct | L154: K. Singh | M154: Printers | N154: PRN-7089 | O154: 928.68 | P154: =IF(Q154<50, "Low", IF(Q154<200, "Medium", "High")) -> High | Q154: 2145.17 | R154: 0.136 | S154: 16 | T154: =(Q180*S154)*(1-R154) -> 5684.1523 | U154: =(O154*S154) -> 14858.88 | V154: =(T154-U154) -> -9174.7277 | W154: =IF(T154=0, 0, V154/T154) -> -1.614089
A155: ORD-2023-842488 | B155: 45230 | C155: 45232 | D155: =DATEDIF(B155,C155, "MD") -> 2 | E155: =TEXT(Data!B155,"MMM-YYYY") -> Oct-2023 | F155: ="Q"&ROUNDUP(MONTH(B155)/3,0)&"-"&YEAR(B155) -> Q4-2023 | G155: Africa | H155: Kenya | I155: Kisumu | J155: Education | K155: Retail | L155: O. Wang | M155: Accessories | N155: ACC-4124 | O155: 867.89 | P155: =IF(Q155<50, "Low", IF(Q155<200, "Medium", "High")) -> High | Q155: 1349.94 | R155: 0.184 | S155: 10 | T155: =(Q181*S155)*(1-R155) -> 48.3072 | U155: =(O155*S155) -> 8678.9 | V155: =(T155-U155) -> -8630.5928 | W155: =IF(T155=0, 0, V155/T155) -> -178.66059
A156: ORD-2024-136321 | B156: 45511 | C156: 45521 | D156: =DATEDIF(B156,C156, "MD") -> 10 | E156: =TEXT(Data!B156,"MMM-YYYY") -> Aug-2024 | F156: ="Q"&ROUNDUP(MONTH(B156)/3,0)&"-"&YEAR(B156) -> Q3-2024 | G156: Asia | H156: Japan | I156: Osaka | J156: Consumer | K156: Online | L156: K. Singh | M156: Networking | N156: NET-7924 | O156: 436.58 | P156: =IF(Q156<50, "Low", IF(Q156<200, "Medium", "High")) -> High | Q156: 527.48 | R156: 0.111 | S156: 19 | T156: =(Q182*S156)*(1-R156) -> 37272.187 | U156: =(O156*S156) -> 8295.02 | V156: =(T156-U156) -> 28977.167 | W156: =IF(T156=0, 0, V156/T156) -> 0.77744746
A157: ORD-2024-764468 | B157: 45323 | C157: 45343 | D157: =DATEDIF(B157,C157, "MD") -> 20 | E157: =TEXT(Data!B157,"MMM-YYYY") -> Feb-2024 | F157: ="Q"&ROUNDUP(MONTH(B157)/3,0)&"-"&YEAR(B157) -> Q1-2024 | G157: Europe | H157: France | I157: Paris | J157: Small Business | K157: Marketplace | L157: A. Patel | M157: Networking | N157: NET-8761 | O157: 656.2 | P157: =IF(Q157<50, "Low", IF(Q157<200, "Medium", "High")) -> High | Q157: 1467.17 | R157: 0.018 | S157: 5 | T157: =(Q183*S157)*(1-R157) -> 9391.848 | U157: =(O157*S157) -> 3281 | V157: =(T157-U157) -> 6110.848 | W157: =IF(T157=0, 0, V157/T157) -> 0.65065448
A158: ORD-2024-553449 | B158: 45531 | C158: 45553 | D158: =DATEDIF(B158,C158, "MD") -> 22 | E158: =TEXT(Data!B158,"MMM-YYYY") -> Aug-2024 | F158: ="Q"&ROUNDUP(MONTH(B158)/3,0)&"-"&YEAR(B158) -> Q3-2024 | G158: Asia | H158: India | I158: Delhi | J158: Consumer | K158: Direct | L158: B. Chen | M158: Components | N158: CMP-3875 | O158: 896.75 | P158: =IF(Q158<50, "Low", IF(Q158<200, "Medium", "High")) -> High | Q158: 1651.14 | R158: 0.025 | S158: 15 | T158: =(Q184*S158)*(1-R158) -> 20216.284 | U158: =(O158*S158) -> 13451.25 | V158: =(T158-U158) -> 6765.0337 | W158: =IF(T158=0, 0, V158/T158) -> 0.3346329
A159: ORD-2025-766923 | B159: 45703 | C159: 45703 | D159: =DATEDIF(B159,C159, "MD") -> 0 | E159: =TEXT(Data!B159,"MMM-YYYY") -> Feb-2025 | F159: ="Q"&ROUNDUP(MONTH(B159)/3,0)&"-"&YEAR(B159) -> Q1-2025 | G159: Europe | H159: Germany | I159: Frankfurt | J159: Small Business | K159: Marketplace | L159: L. Okafor | M159: Accessories | N159: ACC-3989 | O159: 815.83 | P159: =IF(Q159<50, "Low", IF(Q159<200, "Medium", "High")) -> High | Q159: 1982.18 | R159: 0.127 | S159: 6 | T159: =(Q185*S159)*(1-R159) -> 7100.6852 | U159: =(O159*S159) -> 4894.98 | V159: =(T159-U159) -> 2205.7052 | W159: =IF(T159=0, 0, V159/T159) -> 0.31063272
A160: ORD-2025-418232 | B160: 45870 | C160: 45890 | D160: =DATEDIF(B160,C160, "MD") -> 20 | E160: =TEXT(Data!B160,"MMM-YYYY") -> Aug-2025 | F160: ="Q"&ROUNDUP(MONTH(B160)/3,0)&"-"&YEAR(B160) -> Q3-2025 | G160: Asia | H160: China | I160: Shanghai | J160: Corporate | K160: Direct | L160: I. Johnson | M160: Phones | N160: PHN-9234 | O160: 1220.41 | P160: =IF(Q160<50, "Low", IF(Q160<200, "Medium", "High")) -> High | Q160: 2552.22 | R160: 0.181 | S160: 14 | T160: =(Q186*S160)*(1-R160) -> 10180.661 | U160: =(O160*S160) -> 17085.74 | V160: =(T160-U160) -> -6905.0786 | W160: =IF(T160=0, 0, V160/T160) -> -0.67825442
...

Sheet Part A
A3: 1 | B3: Month
A5: 2 | B5: Quarter | C5: ="Q"&ROUNDUP(MONTH(Data!B2)/3,0)&"-"&YEAR(Data!B2) -> Q4-2024
A7: 3 | B7: Region Hierachy
A9: 4 | B9: Product Category
A11: 5 | B11: Derived Price Band

Sheet Standardised Dimension Table
A1: OrderDate | B1: Month | C1: Quarter | D1: Region | E1: Country | F1: City | G1: ProductCategory | H1: Price Band | I1: UnitPrice
A2: 45362 | B2: =TEXT(Data!B2,"MMM-YYYY") -> Oct-2024 | C2: ="Q"&ROUNDUP(MONTH(A2)/3,0)&"-"&YEAR(A2) -> Q1-2024 | D2: Africa | E2: Kenya | F2: Kisumu | G2: Components | H2: =IF(I2<50, "Low", IF(I2<200, "Medium", "High")) -> High | I2: 608.9
A3: 45363 | B3: =TEXT(Data!B3,"MMM-YYYY") -> Feb-2023 | C3: ="Q"&ROUNDUP(MONTH(A3)/3,0)&"-"&YEAR(A3) -> Q1-2024 | D3: Africa | E3: Nigeria | F3: Port Harcourt | G3: Printers | H3: =IF(I3<50, "Low", IF(I3<200, "Medium", "High")) -> High | I3: 759.33
A4: 45364 | B4: =TEXT(Data!B4,"MMM-YYYY") -> Mar-2025 | C4: ="Q"&ROUNDUP(MONTH(A4)/3,0)&"-"&YEAR(A4) -> Q1-2024 | D4: Africa | E4: Kenya | F4: Nairobi | G4: Networking | H4: =IF(I4<50, "Low", IF(I4<200, "Medium", "High")) -> Low | I4: -30.66
A5: 45365 | B5: =TEXT(Data!B5,"MMM-YYYY") -> Dec-2023 | C5: ="Q"&ROUNDUP(MONTH(A5)/3,0)&"-"&YEAR(A5) -> Q1-2024 | D5: Africa | E5: Nigeria | F5: Lagos | G5: Phones | H5: =IF(I5<50, "Low", IF(I5<200, "Medium", "High")) -> High | I5: 255.94
A6: 45366 | B6: =TEXT(Data!B6,"MMM-YYYY") -> Jan-2023 | C6: ="Q"&ROUNDUP(MONTH(A6)/3,0)&"-"&YEAR(A6) -> Q1-2024 | D6: Asia | E6: Japan | F6: Osaka | G6: Printers | H6: =IF(I6<50, "Low", IF(I6<200, "Medium", "High")) -> High | I6: 813.51
A7: 45367 | B7: =TEXT(Data!B7,"MMM-YYYY") -> Dec-2024 | C7: ="Q"&ROUNDUP(MONTH(A7)/3,0)&"-"&YEAR(A7) -> Q1-2024 | D7: Americas | E7: Canada | F7: Toronto | G7: Laptops | H7: =IF(I7<50, "Low", IF(I7<200, "Medium", "High")) -> High | I7: 591.68
A8: 45368 | B8: =TEXT(Data!B8,"MMM-YYYY") -> Jan-2023 | C8: ="Q"&ROUNDUP(MONTH(A8)/3,0)&"-"&YEAR(A8) -> Q1-2024 | D8: Asia | E8: India | F8: Bengaluru | G8: Monitors | H8: =IF(I8<50, "Low", IF(I8<200, "Medium", "High")) -> High | I8: 845.97
A9: 45369 | B9: =TEXT(Data!B9,"MMM-YYYY") -> May-2024 | C9: ="Q"&ROUNDUP(MONTH(A9)/3,0)&"-"&YEAR(A9) -> Q1-2024 | D9: Africa | E9: Nigeria | F9: Abuja | G9: Printers | H9: =IF(I9<50, "Low", IF(I9<200, "Medium", "High")) -> Low | I9: 47.22
A10: 45370 | B10: =TEXT(Data!B10,"MMM-YYYY") -> May-2025 | C10: ="Q"&ROUNDUP(MONTH(A10)/3,0)&"-"&YEAR(A10) -> Q1-2024 | D10: Africa | E10: Nigeria | F10: Abuja | G10: Monitors | H10: =IF(I10<50, "Low", IF(I10<200, "Medium", "High")) -> High | I10: 2530.81
A11: 45371 | B11: =TEXT(Data!B11,"MMM-YYYY") -> Jan-2024 | C11: ="Q"&ROUNDUP(MONTH(A11)/3,0)&"-"&YEAR(A11) -> Q1-2024 | D11: Americas | E11: Brazil | F11: São Paulo | G11: Components | H11: =IF(I11<50, "Low", IF(I11<200, "Medium", "High")) -> High | I11: 2309.56
A12: 45372 | B12: =TEXT(Data!B12,"MMM-YYYY") -> Jan-2025 | C12: ="Q"&ROUNDUP(MONTH(A12)/3,0)&"-"&YEAR(A12) -> Q1-2024 | D12: Europe | E12: Germany | F12: Berlin | G12: Accessories | H12: =IF(I12<50, "Low", IF(I12<200, "Medium", "High")) -> High | I12: 700.12
A13: 45373 | B13: =TEXT(Data!B13,"MMM-YYYY") -> Mar-2025 | C13: ="Q"&ROUNDUP(MONTH(A13)/3,0)&"-"&YEAR(A13) -> Q1-2024 | D13: Asia | E13: Japan | F13: Osaka | G13: Phones | H13: =IF(I13<50, "Low", IF(I13<200, "Medium", "High")) -> High | I13: 691.37
... A633: 45993 | B633: =TEXT(Data!B633,"MMM-YYYY") -> Feb-2025 | C633: ="Q"&ROUNDUP(MONTH(A633)/3,0)&"-"&YEAR(A633) -> Q4-2025 | D633: Asia | E633: Japan | F633: Osaka | G633: Laptops | H633: =IF(I633<50, "Low", IF(I633<200, "Medium", "High")) -> Low | I633: 45.98

Sheet Analysis
A1: OrderDate | B1: Order Month | C1: Cohort Month | D1: First Sale Date | E1: Quarter | F1: Region | G1: Country | H1: City | I1: ProductCategory | J1: Price Band | K1: UnitPrice | L1: UnitPrice | M1: DiscountPct | N1: Quantity | O1: Gross Revenue
A2: 45362 | B2: =TEXT(Data!B2,"MMM-YYYY") -> Oct-2024 | C2: =TEXT(D2, "MMM-YYYY") -> Mar-2024 | D2: =_xlfn.MINIFS(A2:A2, G2:G2,G2) -> 45362 | E2: ="Q"&ROUNDUP(MONTH(A2)/3,0)&"-"&YEAR(A2) -> Q1-2024 | F2: Africa | G2: Kenya | H2: Kisumu | I2: Components | J2: =IF(K2<50, "Low", IF(K2<200, "Medium", "High")) -> High | K2: 608.9 | L2: 608.9 | M2: 0.112 | N2: 9 | O2: =(L28*N2)*(1-M2) -> 1403.9546
A3: 45363 | B3: =TEXT(Data!B3,"MMM-YYYY") -> Feb-2023 | C3: =TEXT(D3, "MMM-YYYY") -> Mar-2024 | D3: =_xlfn.MINIFS(A3:A3, G3:G3,G3) -> 45363 | E3: ="Q"&ROUNDUP(MONTH(A3)/3,0)&"-"&YEAR(A3) -> Q1-2024 | F3: Africa | G3: Nigeria | H3: Port Harcourt | I3: Printers | J3: =IF(K3<50, "Low", IF(K3<200, "Medium", "High")) -> High | K3: 759.33 | L3: 759.33 | M3: 0.237 | N3: 31 | O3: =(L29*N3)*(1-M3) -> 17934.414
A4: 45364 | B4: =TEXT(Data!B4,"MMM-YYYY") -> Mar-2025 | C4: =TEXT(D4, "MMM-YYYY") -> Mar-2024 | D4: =_xlfn.MINIFS(A4:A4, G4:G4,G4) -> 45364 | E4: ="Q"&ROUNDUP(MONTH(A4)/3,0)&"-"&YEAR(A4) -> Q1-2024 | F4: Africa | G4: Kenya | H4: Nairobi | I4: Networking | J4: =IF(K4<50, "Low", IF(K4<200, "Medium", "High")) -> Low | K4: -30.66 | L4: -30.66 | M4: 0.131 | N4: 12 | O4: =(L30*N4)*(1-M4) -> 4534.0944
A5: 45365 | B5: =TEXT(Data!B5,"MMM-YYYY") -> Dec-2023 | C5: =TEXT(D5, "MMM-YYYY") -> Mar-2024 | D5: =_xlfn.MINIFS(A5:A5, G5:G5,G5) -> 45365 | E5: ="Q"&ROUNDUP(MONTH(A5)/3,0)&"-"&YEAR(A5) -> Q1-2024 | F5: Africa | G5: Nigeria | H5: Lagos | I5: Phones | J5: =IF(K5<50, "Low", IF(K5<200, "Medium", "High")) -> High | K5: 255.94 | L5: 255.94 | M5: 0.072 | N5: 22 | O5: =(L31*N5)*(1-M5) -> 34016.731
A6: 45366 | B6: =TEXT(Data!B6,"MMM-YYYY") -> Jan-2023 | C6: =TEXT(D6, "MMM-YYYY") -> Mar-2024 | D6: =_xlfn.MINIFS(A6:A6, G6:G6,G6) -> 45366 | E6: ="Q"&ROUNDUP(MONTH(A6)/3,0)&"-"&YEAR(A6) -> Q1-2024 | F6: Asia | G6: Japan | H6: Osaka | I6: Printers | J6: =IF(K6<50, "Low", IF(K6<200, "Medium", "High")) -> High | K6: 813.51 | L6: 813.51 | M6: 0.102 | N6: 15 | O6: =(L32*N6)*(1-M6) -> 8510.0766
A7: 45367 | B7: =TEXT(Data!B7,"MMM-YYYY") -> Dec-2024 | C7: =TEXT(D7, "MMM-YYYY") -> Mar-2024 | D7: =_xlfn.MINIFS(A7:A7, G7:G7,G7) -> 45367 | E7: ="Q"&ROUNDUP(MONTH(A7)/3,0)&"-"&YEAR(A7) -> Q1-2024 | F7: Americas | G7: Canada | H7: Toronto | I7: Laptops | J7: =IF(K7<50, "Low", IF(K7<200, "Medium", "High")) -> High | K7: 591.68 | L7: 591.68 | M7: 0 | N7: 7 | O7: =(L33*N7)*(1-M7) -> 12558.49
A8: 45368 | B8: =TEXT(Data!B8,"MMM-YYYY") -> Jan-2023 | C8: =TEXT(D8, "MMM-YYYY") -> Mar-2024 | D8: =_xlfn.MINIFS(A8:A8, G8:G8,G8) -> 45368 | E8: ="Q"&ROUNDUP(MONTH(A8)/3,0)&"-"&YEAR(A8) -> Q1-2024 | F8: Asia | G8: India | H8: Bengaluru | I8: Monitors | J8: =IF(K8<50, "Low", IF(K8<200, "Medium", "High")) -> High | K8: 845.97 | L8: 845.97 | M8: 0.147 | N8: 4 | O8: =(L34*N8)*(1-M8) -> 8983.8642
A9: 45369 | B9: =TEXT(Data!B9,"MMM-YYYY") -> May-2024 | C9: =TEXT(D9, "MMM-YYYY") -> Mar-2024 | D9: =_xlfn.MINIFS(A9:A9, G9:G9,G9) -> 45369 | E9: ="Q"&ROUNDUP(MONTH(A9)/3,0)&"-"&YEAR(A9) -> Q1-2024 | F9: Africa | G9: Nigeria | H9: Abuja | I9: Printers | J9: =IF(K9<50, "Low", IF(K9<200, "Medium", "High")) -> Low | K9: 47.22 | L9: 47.22 | M9: 0.194 | N9: 18 | O9: =(L35*N9)*(1-M9) -> 19177.4
A10: 45370 | B10: =TEXT(Data!B10,"MMM-YYYY") -> May-2025 | C10: =TEXT(D10, "MMM-YYYY") -> Mar-2024 | D10: =_xlfn.MINIFS(A10:A10, G10:G10,G10) -> 45370 | E10: ="Q"&ROUNDUP(MONTH(A10)/3,0)&"-"&YEAR(A10) -> Q1-2024 | F10: Africa | G10: Nigeria | H10: Abuja | I10: Monitors | J10: =IF(K10<50, "Low", IF(K10<200, "Medium", "High")) -> High | K10: 2530.81 | L10: 2530.81 | M10: 0.031 | N10: 6 | O10: =(L36*N10)*(1-M10) -> 17656.362
A11: 45371 | B11: =TEXT(Data!B11,"MMM-YYYY") -> Jan-2024 | C11: =TEXT(D11, "MMM-YYYY") -> Mar-2024 | D11: =_xlfn.MINIFS(A11:A11, G11:G11,G11) -> 45371 | E11: ="Q"&ROUNDUP(MONTH(A11)/3,0)&"-"&YEAR(A11) -> Q1-2024 | F11: Americas | G11: Brazil | H11: São Paulo | I11: Components | J11: =IF(K11<50, "Low", IF(K11<200, "Medium", "High")) -> High | K11: 2309.56 | L11: 2309.56 | M11: 0.149 | N11: 31 | O11: =(L37*N11)*(1-M11) -> 5259.58
A12: 45372 | B12: =TEXT(Data!B12,"MMM-YYYY") -> Jan-2025 | C12: =TEXT(D12, "MMM-YYYY") -> Mar-2024 | D12: =_xlfn.MINIFS(A12:A12, G12:G12,G12) -> 45372 | E12: ="Q"&ROUNDUP(MONTH(A12)/3,0)&"-"&YEAR(A12) -> Q1-2024 | F12: Europe | G12: Germany | H12: Berlin | I12: Accessories | J12: =IF(K12<50, "Low", IF(K12<200, "Medium", "High")) -> High | K12: 700.12 | L12: 700.12 | M12: 0.006 | N12: 23 | O12: =(L38*N12)*(1-M12) -> 21204.734
A13: 45373 | B13: =TEXT(Data!B13,"MMM-YYYY") -> Mar-2025 | C13: =TEXT(D13, "MMM-YYYY") -> Mar-2024 | D13: =_xlfn.MINIFS(A13:A13, G13:G13,G13) -> 45373 | E13: ="Q"&ROUNDUP(MONTH(A13)/3,0)&"-"&YEAR(A13) -> Q1-2024 | F13: Asia | G13: Japan | H13: Osaka | I13: Phones | J13: =IF(K13<50, "Low", IF(K13<200, "Medium", "High")) -> High | K13: 691.37 | L13: 691.37 | M13: 0.25 | N13: 20 | O13: =(L39*N13)*(1-M13) -> 26031.15
... A633: 45993 | B633: =TEXT(Data!B633,"MMM-YYYY") -> Feb-2025 | C633: =TEXT(D633, "MMM-YYYY") -> Dec-2025 | D633: =_xlfn.MINIFS(A633:A633, G633:G633,G633) -> 45993 | E633: ="Q"&ROUNDUP(MONTH(A633)/3,0)&"-"&YEAR(A633) -> Q4-2025 | F633: Asia | G633: Japan | H633: Osaka | I633: Laptops | J633: =IF(K633<50, "Low", IF(K633<200, "Medium", "High")) -> Low | K633: 45.98 | L633: 45.98 | M633: 0.173 | N633: 7 | O633: =(L659*N633)*(1-M633) -> 0

Sheet Pivot Cohort Analysis
A1: Country | B1: (All)
A3: Sum of Gross Revenue | B3: Column Labels
A4: Row Labels | B4: Apr-2023 | C4: Apr-2024 | D4: Apr-2025 | E4: Aug-2023 | F4: Aug-2024 | G4: Aug-2025 | H4: Dec-2023 | I4: Dec-2024 | J4: Feb-2023 | K4: Feb-2024 | L4: Feb-2025 | M4: Jan-2023 | N4: Jan-2024 | O4: Jan-2025 | P4: Jul-2023 | Q4: Jul-2024 | R4: Jul-2025 | S4: Jun-2023 | T4: Jun-2024 | U4: Jun-2025 | V4: Mar-2023 | W4: Mar-2024 | X4: Mar-2025 | Y4: May-2023 | Z4: May-2024 | AA4: May-2025 | AB4: Nov-2023 | AC4: Nov-2024 | AD4: Oct-2023 | AE4: Oct-2024 | AF4: Sept-2023 | AG4: Sept-2024 | AH4: Sept-2025 | AI4: Grand Total
A5: Apr-2024 | B5: 14824.899 | C5: 22477.306 | D5: 11781.339 | F5: 49294.844 | I5: 43367.692 | J5: 41567.724 | N5: 7368.06 | P5: 21312.892 | Q5: 1243.5675 | R5: -19.30928 | S5: 27907.737 | T5: 353.7664 | U5: 29284.637 | V5: 86276.904 | W5: 25427.751 | Y5: 24160.544 | Z5: 53971.103 | AA5: 17662.129 | AC5: 21665.382 | AE5: 32079.351 | AI5: 532008.32
A6: Apr-2025 | D6: 26377.533 | E6: 6993.862 | F6: 30066.425 | G6: 51745.06 | H6: 10899.6 | I6: 22741.536 | L6: 15273.33 | O6: 11831.256 | Q6: 9079.5053 | T6: 22569.276 | U6: 9830.4128 | V6: 20289.09 | W6: 5499.1688 | X6: 1687.789 | Y6: 11663.267 | Z6: 41010.924 | AA6: 47770.043 | AC6: 5658.8054 | AD6: 31288.406 | AF6: 44766.472 | AG6: 18353.975 | AH6: 14660.4 | AI6: 460056.14
A7: Aug-2024 | B7: 32735.194 | C7: 45741.466 | D7: 26608.919 | F7: 57488.471 | G7: 10180.661 | H7: 2454.4138 | J7: 97289.67 | K7: 15076 | L7: 7100.6852 | P7: 31848.367 | Q7: 18676.975 | T7: 13928.655 | V7: 50207.703 | Z7: 5308.1555 | AA7: 36583.531 | AB7: 42353.883 | AD7: 1815.2109 | AE7: 14878.791 | AF7: 8757.7692 | AG7: 57712.05 | AH7: 49.7802 | AI7: 576796.35
A8: Aug-2025 | B8: 25448.667 | C8: 17160.811 | D8: 11813.082 | E8: 44990.513 | F8: 31548.788 | G8: 30771.51 | L8: 36886.576 | M8: 7653.6 | N8: 30255.496 | O8: 9162.3608 | P8: 32372.731 | Q8: 33964.937 | S8: 11222.702 | T8: 53128.408 | U8: 9059.1936 | W8: 28098.684 | X8: 8687.4149 | Y8: 62896.528 | Z8: 6873.6311 | AA8: 5994.1018 | AC8: 6953.9874 | AE8: 40152.023 | AF8: 50294.071 | AI8: 595389.82
A9: Dec-2024 | D9: 30054.984 | E9: 28032.604 | G9: 7371.4889 | H9: 15054.2 | L9: 6753.7725 | N9: 79337.233 | P9: 17447.837 | S9: 16255.516 | T9: 8039.3544 | U9: 9349.0342 | W9: 99322.511 | X9: 13554.149 | Y9: 3736.312 | AA9: 8208.8609 | AD9: 3444.5591 | AE9: 32644.137 | AG9: 11640.573 | AH9: 1617.8812 | AI9: 391865.01
A10: Dec-2025 | L10: 0 | AB10: 0 | AI10: 0
A11: Feb-2025 | B11: 36385.454 | C11: 2362.551 | D11: 7038.4882 | E11: 2377.9312 | F11: 31286.996 | H11: 79516.988 | J11: 19625.658 | K11: 34122.605 | O11: 27369.283 | P11: 79487.856 | Q11: 106718.6 | S11: 5667.8292 | U11: 6418.5449 | Y11: 3760.95 | AA11: 841.5672 | AB11: 6720.9426 | AC11: 4722.4032 | AD11: 11668.448 | AE11: 33921.8 | AH11: 21779.835 | AI11: 521794.73
A12: Jan-2025 | D12: 9947.2987 | I12: 13444.762 | J12: 24902.263 | K12: 24630.102 | M12: 35096.967 | N12: 8113.3334 | O12: 47441.619 | P12: 18252.955 | S12: 6452.9218 | T12: 13585.841 | U12: 26888.394 | V12: 125232.05 | W12: 68306.553 | X12: 52560.144 | Y12: 45984.888 | Z12: 39089.558 | AA12: 18720.941 | AB12: 27971.861 | AC12: 35911.89 | AD12: 10311.924 | AG12: 4829.1858 | AI12: 657675.45
A13: Jul-2024 | B13: 14342.188 | E13: 20235.176 | G13: 40507.245 | H13: 7009.2643 | I13: 62986.847 | K13: 35027.455 | L13: 10997.906 | M13: 33178.341 | O13: 17422.405 | P13: 27251.1 | R13: 4225.1933 | S13: 9278.4804 | T13: 44519.542 | U13: 38245.205 | V13: 9902.9228 | X13: 15583.459 | Y13: 15179.749 | Z13: 9877.511 | AB13: 21486.142 | AC13: 47159.894 | AI13: 484416.03
A14: Jul-2025 | B14: 31378.532 | C14: 21447.614 | D14: 20815.888 | E14: 9504.8997 | F14: 20669.092 | G14: 5660.0544 | I14: 6964.3963 | J14: 10393.181 | N14: 24019.121 | P14: 20043.768 | R14: 16395.612 | S14: 10084.108 | V14: 22462.452 | W14: 2603.4792 | X14: 23976.759 | Y14: 2493.1507 | Z14: 97889.28 | AA14: 3415.8504 | AC14: 14894.108 | AD14: 29896.224 | AE14: 7506.8196 | AG14: 160976.27 | AH14: 8401.894 | AI14: 571892.55
A15: Jun-2024 | B15: 47694.762 | C15: 36.9702 | D15: 4544.8392 | F15: 5654.2295 | G15: 9137.6141 | H15: 18364.589 | I15: 24706.764 | J15: 8854.2763 | N15: 3521.1077 | O15: 31422.63 | R15: 3615.6742 | S15: 30168.894 | T15: 54227.522 | U15: 74251.58 | X15: 14467.482 | Y15: 22483.549 | Z15: 29865.732 | AA15: 2281.3896 | AE15: 7561.2927 | AG15: 4270.2181 | AH15: 9873.8136 | AI15: 407004.93
A16: Jun-2025 | D16: 31644.291 | E16: 19353.546 | G16: 13790.976 | H16: 116731.22 | I16: 674.07536 | K16: 8549.7652 | M16: 3365.5756 | P16: 6140.8031 | R16: 13652.986 | T16: 46314.986 | U16: 19287.106 | W16: 733.0112 | X16: 40309.208 | Y16: 129059.84 | Z16: 39751.9 | AB16: 35310.319 | AC16: 21031.9 | AI16: 545701.51
A17: Mar-2024 | B17: 14666.09 | H17: 8510.0766 | I17: 88929.73 | J17: 4534.0944 | M17: 31735.89 | N17: 28021.034 | O17: 26031.15 | Q17: 3565.5894 | R17: 15979.622 | W17: 1403.9546 | X17: 46661.229 | Z17: 17656.362 | AA17: 30794.86 | AE17: 17934.414 | AH17: 33813.981 | AI17: 370238.08
A18: Mar-2025 | B18: 59066.056 | C18: 28646.703 | D18: 26958.519 | G18: 42205.544 | H18: 17698.503 | J18: 15891.92 | L18: 35734.359 | N18: 28945.64 | O18: 41965.13 | P18: 45086.595 | Q18: 14867.19 | R18: 13660.278 | S18: 98011.346 | T18: 26511.737 | U18: 54798.866 | V18: 11379.122 | W18: 35913.938 | X18: 23605.161 | Y18: 20697.169 | Z18: 11597.651 | AC18: 4499.15 | AF18: 12985.618 | AI18: 670726.2
A19: May-2024 | B19: 11803.702 | C19: 5807.6003 | D19: 78030.317 | E19: 57129.954 | F19: 21984.96 | H19: 9671.5258 | I19: 34632.216 | J19: 45029.794 | L19: 4119.0446 | O19: 21238.118 | S19: 44117.408 | T19: 3822.367 | U19: 93667.868 | V19: 28786.488 | W19: 29809.479 | Y19: 10198.972 | Z19: 11273.617 | AA19: 4086.5862 | AC19: 6580.1227 | AE19: 11819.917 | AF19: 2073.2046 | AH19: 7255.458 | AI19: 542938.72
A20: May-2025 | B20: 989.3947 | F20: 39489.654 | G20: 33475.68 | H20: 22309.837 | I20: 59221.441 | J20: 15339.646 | K20: 105981.7 | L20: 1853.3248 | N20: 5749.1559 | R20: 78253.279 | S20: 7167.5669 | U20: 1948.1462 | W20: 48582.216 | X20: 4846.6447 | Y20: 5497.3325 | AA20: 41071.932 | AC20: 45872.984 | AD20: 17009.912 | AF20: 20287.469 | AG20: 21303.28 | AH20: 20866.56 | AI20: 597117.16
A21: Nov-2024 | B21: 7944.7971 | C21: 39508.724 | D21: 51929.129 | E21: 12481.437 | G21: 9431.7696 | I21: 5532.6686 | K21: 6352.3799 | N21: 31218.691 | Q21: 29033.704 | R21: 5002.3123 | U21: 15357.7 | V21: 17084.938 | W21: 74491.455 | Y21: 17985.918 | AA21: 17830.455 | AB21: 15275.596 | AC21: 2237.6024 | AD21: 10855.106 | AE21: 18599.828 | AF21: 18307.712 | AG21: 48863.066 | AH21: 11792.958 | AI21: 467117.95
A22: Nov-2025 | B22: 10511.386 | D22: 0 | E22: 0 | F22: 3208.8336 | G22: 2667.2333 | H22: 0 | I22: 0 | K22: 0 | N22: 0 | P22: 0 | Q22: 0 | R22: 0 | S22: 0 | T22: 0 | U22: 0 | W22: 18416.457 | X22: 0 | AA22: 34640.985 | AB22: 0 | AC22: 0 | AD22: 0 | AE22: 0 | AF22: 486.56036 | AI22: 69931.455
A23: Oct-2024 | B23: 24416.279 | D23: 4648.9351 | E23: 9151.63 | G23: 31629.555 | H23: 18916.432 | K23: 64128.859 | L23: 554.9796 | M23: 789.46368 | O23: 6823.2037 | P23: 20805.371 | R23: 87186.76 | V23: 32095.464 | Y23: 34932.682 | AB23: 6137.9842 | AD23: 6770.0719 | AE23: 25491.118 | AF23: 158.1652 | AG23: 36310.302 | AI23: 410947.25
A24: Oct-2025 | B24: 19117.733 | D24: 51926.012 | E24: 109937.12 | F24: 62066.492 | G24: 7543.8006 | H24: 28925.557 | J24: 24128.643 | K24: 21446.4 | L24: 17843.722 | M24: 8582.88 | N24: 6980.1763 | Q24: 4083.43 | R24: 20722.293 | S24: 19816.344 | T24: 66005.5 | U24: 4921.3008 | W24: 46878.839 | X24: 31581.442 | Y24: 3085.38 | AC24: 8728.9427 | AG24: 2183.9423 | AI24: 566505.95
A25: Sept-2024 | B25: 85336.721 | D25: 17694.882 | E25: 61980.597 | F25: 13882.919 | G25: 26302.967 | K25: 74200.581 | L25: 7256.5422 | M25: 132103 | N25: 11002.005 | O25: 6319.9847 | P25: 9587.7281 | S25: 1541.592 | Y25: 14139.906 | Z25: 9097.8674 | AD25: 5219.7773 | AE25: 101008.89 | AG25: 3645.6089 | AH25: 593.5216 | AI25: 580915.09
A26: Sept-2025 | B26: 11393.723 | F26: 23507.575 | G26: 9301.946 | H26: 35256.783 | I26: 10814.319 | J26: 39068.86 | K26: 26490.276 | L26: 20641.897 | M26: 14063.654 | N26: 5968.5956 | P26: 18398.439 | Q26: 1119.492 | T26: 25485.5 | U26: 29597.64 | V26: 10310.463 | W26: 8118.5574 | Y26: 1551.6 | Z26: 8897.573 | AA26: 58944.55 | AC26: 64527.264 | AE26: 22209.694 | AF26: 4778.8646 | AI26: 450447.26
A27: Grand Total | B27: 448055.58 | C27: 183189.75 | D27: 411814.46 | E27: 382169.27 | F27: 390149.28 | G27: 331723.1 | H27: 391318.99 | I27: 374016.45 | J27: 346625.73 | K27: 416006.13 | L27: 165016.14 | M27: 266569.37 | N27: 270499.65 | O27: 247027.14 | P27: 348036.44 | Q27: 222352.99 | R27: 258674.7 | S27: 287692.45 | T27: 378492.45 | U27: 422905.63 | V27: 414027.6 | W27: 493606.05 | X27: 277520.88 | Y27: 429507.73 | Z27: 382160.86 | AA27: 328847.78 | AB27: 155256.73 | AC27: 290444.44 | AD27: 128279.64 | AE27: 365808.07 | AF27: 162895.91 | AG27: 370088.47 | AH27: 130706.08 | AI27: 10471486

Sheet ABC Data
A1: ORD-2024-275203 | B1: 45362 | C1: 45388 | D1: =DATEDIF(B1,C1, "MD") -> 26 | E1: =TEXT(Data!B1,"MMM-YYYY") -> Mar-2024 | F1: ="Q"&ROUNDUP(MONTH(B1)/3,0)&"-"&YEAR(B1) -> Q1-2024 | G1: Africa | H1: Kenya | I1: Kisumu | J1: Corporate | K1: Retail | L1: C. Otieno | M1: Components | N1: CMP-8270 | O1: 279.24 | P1: =IF(Q1<50, "Low", IF(Q1<200, "Medium", "High")) -> High | Q1: 608.9 | R1: 0.112 | S1: 9 | T1: =(Q27*S1)*(1-R1) -> 1403.9546 | U1: =(O1*S1) -> 2513.16 | V1: =(T1-U1) -> -1109.2054 | W1: =IF(T1=0, 0, V1/T1) -> -0.79005783
A2: ORD-2024-358795 | B2: 45588 | C2: 45587 | D2: =DATEDIF(C2, B2, "MD") -> 1 | E2: =TEXT(Data!B2,"MMM-YYYY") -> Oct-2024 | F2: ="Q"&ROUNDUP(MONTH(B2)/3,0)&"-"&YEAR(B2) -> Q4-2024 | G2: Africa | H2: Nigeria | I2: Port Harcourt | J2: Education | K2: Online | L2: J. Njeri | M2: Printers | N2: PRN-9322 | O2: 1084.39 | P2: =IF(Q2<50, "Low", IF(Q2<200, "Medium", "High")) -> High | Q2: 759.33 | R2: 0.237 | S2: 31 | T2: =(Q28*S2)*(1-R2) -> 17934.414 | U2: =(O2*S2) -> 33616.09 | V2: =(T2-U2) -> -15681.676 | W2: =IF(T2=0, 0, V2/T2) -> -0.87439019
A3: ORD-2023-373538 | B3: 44985 | C3: 45010 | D3: =DATEDIF(B3,C3, "MD") -> 25 | E3: =TEXT(Data!B3,"MMM-YYYY") -> Feb-2023 | F3: ="Q"&ROUNDUP(MONTH(B3)/3,0)&"-"&YEAR(B3) -> Q1-2023 | G3: Africa | H3: Kenya | I3: Nairobi | J3: Corporate | K3: Retail | L3: I. Johnson | M3: Networking | N3: NET-9666 | O3: 1460.76 | P3: =IF(Q3<50, "Low", IF(Q3<200, "Medium", "High")) -> Low | Q3: -30.66 | R3: 0.131 | S3: 12 | T3: =(Q29*S3)*(1-R3) -> 4534.0944 | U3: =(O3*S3) -> 17529.12 | V3: =(T3-U3) -> -12995.026 | W3: =IF(T3=0, 0, V3/T3) -> -2.8660686
A4: ORD-2025-168148 | B4: 45745 | C4: 45749 | D4: =DATEDIF(B4,C4, "MD") -> 4 | E4: =TEXT(Data!B4,"MMM-YYYY") -> Mar-2025 | F4: ="Q"&ROUNDUP(MONTH(B4)/3,0)&"-"&YEAR(B4) -> Q1-2025 | G4: Africa | H4: Nigeria | I4: Lagos | J4: Non-Profit | K4: Marketplace | L4: G. Dubois | M4: Phones | N4: PHN-4556 | O4: 259.93 | P4: =IF(Q4<50, "Low", IF(Q4<200, "Medium", "High")) -> High | Q4: 255.94 | R4: 0.072 | S4: 22 | T4: =(Q30*S4)*(1-R4) -> 34016.731 | U4: =(O4*S4) -> 5718.46 | V4: =(T4-U4) -> 28298.271 | W4: =IF(T4=0, 0, V4/T4) -> 0.83189272
A5: ORD-2023-824839 | B5: 45266 | C5: 45291 | D5: =DATEDIF(B5,C5, "MD") -> 25 | E5: =TEXT(Data!B5,"MMM-YYYY") -> Dec-2023 | F5: ="Q"&ROUNDUP(MONTH(B5)/3,0)&"-"&YEAR(B5) -> Q4-2023 | G5: Asia | H5: Japan | I5: Osaka | J5: Consumer | K5: Retail | L5: L. Okafor | M5: Printers | N5: PRN-8041 | O5: 663.03 | P5: =IF(Q5<50, "Low", IF(Q5<200, "Medium", "High")) -> High | Q5: 813.51 | R5: 0.102 | S5: 15 | T5: =(Q31*S5)*(1-R5) -> 8510.0766 | U5: =(O5*S5) -> 9945.45 | V5: =(T5-U5) -> -1435.3734 | W5: =IF(T5=0, 0, V5/T5) -> -0.16866751
A6: ORD-2023-723587 | B6: 44928 | C6: 44931 | D6: =DATEDIF(B6,C6, "MD") -> 3 | E6: =TEXT(Data!B6,"MMM-YYYY") -> Jan-2023 | F6: ="Q"&ROUNDUP(MONTH(B6)/3,0)&"-"&YEAR(B6) -> Q1-2023 | G6: Americas | H6: Canada | I6: Toronto | J6: Corporate | K6: Distributor | L6: B. Chen | M6: Laptops | N6: LAP-8555 | O6: 315.87 | P6: =IF(Q6<50, "Low", IF(Q6<200, "Medium", "High")) -> High | Q6: 591.68 | R6: 0 | S6: 7 | T6: =(Q32*S6)*(1-R6) -> 12558.49 | U6: =(O6*S6) -> 2211.09 | V6: =(T6-U6) -> 10347.4 | W6: =IF(T6=0, 0, V6/T6) -> 0.82393664
A7: ORD-2024-336584 | B7: 45653 | C7: 45671 | D7: =DATEDIF(B7,C7, "MD") -> 18 | E7: =TEXT(Data!B7,"MMM-YYYY") -> Dec-2024 | F7: ="Q"&ROUNDUP(MONTH(B7)/3,0)&"-"&YEAR(B7) -> Q4-2024 | G7: Asia | H7: India | I7: Bengaluru | J7: Small Business | K7: Marketplace | L7: E. Garcia | M7: Monitors | N7: MON-8629 | O7: 586.07 | P7: =IF(Q7<50, "Low", IF(Q7<200, "Medium", "High")) -> High | Q7: 845.97 | R7: 0.147 | S7: 4 | T7: =(Q33*S7)*(1-R7) -> 8983.8642 | U7: =(O7*S7) -> 2344.28 | V7: =(T7-U7) -> 6639.5842 | W7: =IF(T7=0, 0, V7/T7) -> 0.73905661
A8: ORD-2023-112666 | B8: 44941 | C8: 44939 | D8: =DATEDIF(C8,B8, "MD") -> 2 | E8: =TEXT(Data!B8,"MMM-YYYY") -> Jan-2023 | F8: ="Q"&ROUNDUP(MONTH(B8)/3,0)&"-"&YEAR(B8) -> Q1-2023 | G8: Africa | H8: Nigeria | I8: Abuja | J8: Education | K8: Online | L8: O. Wang | M8: Printers | N8: PRN-6276 | O8: 28.38 | P8: =IF(Q8<50, "Low", IF(Q8<200, "Medium", "High")) -> Low | Q8: 47.22 | R8: 0.194 | S8: 18 | T8: =(Q34*S8)*(1-R8) -> 19177.4 | U8: =(O8*S8) -> 510.84 | V8: =(T8-U8) -> 18666.56 | W8: =IF(T8=0, 0, V8/T8) -> 0.9733624
A9: ORD-2024-589570 | B9: 45416 | C9: 45441 | D9: =DATEDIF(B9,C9, "MD") -> 25 | E9: =TEXT(Data!B9,"MMM-YYYY") -> May-2024 | F9: ="Q"&ROUNDUP(MONTH(B9)/3,0)&"-"&YEAR(B9) -> Q2-2024 | G9: Africa | H9: Nigeria | I9: Abuja | J9: Non-Profit | K9: Marketplace | L9: O. Wang | M9: Monitors | N9: MON-6892 | O9: 1295.34 | P9: =IF(Q9<50, "Low", IF(Q9<200, "Medium", "High")) -> High | Q9: 2530.81 | R9: 0.031 | S9: 6 | T9: =(Q35*S9)*(1-R9) -> 17656.362 | U9: =(O9*S9) -> 7772.04 | V9: =(T9-U9) -> 9884.3222 | W9: =IF(T9=0, 0, V9/T9) -> 0.55981646
A10: ORD-2025-997421 | B10: 45798 | C10: 45817 | D10: =DATEDIF(B10,C10, "MD") -> 19 | E10: =TEXT(Data!B10,"MMM-YYYY") -> May-2025 | F10: ="Q"&ROUNDUP(MONTH(B10)/3,0)&"-"&YEAR(B10) -> Q2-2025 | G10: Americas | H10: Brazil | I10: São Paulo | J10: Non-Profit | K10: Online | L10: A. Patel | M10: Components | N10: CMP-3731 | O10: 1331.38 | P10: =IF(Q10<50, "Low", IF(Q10<200, "Medium", "High")) -> High | Q10: 2309.56 | R10: 0.149 | S10: 31 | T10: =(Q36*S10)*(1-R10) -> 5259.58 | U10: =(O10*S10) -> 41272.78 | V10: =(T10-U10) -> -36013.2 | W10: =IF(T10=0, 0, V10/T10) -> -6.8471627
A11: ORD-2024-210687 | B11: 45319 | C11: 45331 | D11: =DATEDIF(B11,C11, "MD") -> 12 | E11: =TEXT(Data!B11,"MMM-YYYY") -> Jan-2024 | F11: ="Q"&ROUNDUP(MONTH(B11)/3,0)&"-"&YEAR(B11) -> Q1-2024 | G11: Europe | H11: Germany | I11: Berlin | J11: Corporate | K11: Online | L11: G. Dubois | M11: Accessories | N11: ACC-7938 | O11: 644.17 | P11: =IF(Q11<50, "Low", IF(Q11<200, "Medium", "High")) -> High | Q11: 700.12 | R11: 0.006 | S11: 23 | T11: =(Q37*S11)*(1-R11) -> 21204.734 | U11: =(O11*S11) -> 14815.91 | V11: =(T11-U11) -> 6388.8236 | W11: =IF(T11=0, 0, V11/T11) -> 0.30129233
A12: ORD-2025-515515 | B12: 45660 | C12: 45680 | D12: =DATEDIF(B12,C12, "MD") -> 20 | E12: =TEXT(Data!B12,"MMM-YYYY") -> Jan-2025 | F12: ="Q"&ROUNDUP(MONTH(B12)/3,0)&"-"&YEAR(B12) -> Q1-2025 | G12: Asia | H12: Japan | I12: Osaka | J12: Corporate | K12: Distributor | L12: F. Müller | M12: Phones | N12: PHN-7019 | O12: 908.6 | P12: =IF(Q12<50, "Low", IF(Q12<200, "Medium", "High")) -> High | Q12: 691.37 | R12: 0.25 | S12: 20 | T12: =(Q38*S12)*(1-R12) -> 26031.15 | U12: =(O12*S12) -> 18172 | V12: =(T12-U12) -> 7859.15 | W12: =IF(T12=0, 0, V12/T12) -> 0.30191328
A13: ORD-2025-487261 | B13: 45722 | C13: 45747 | D13: =DATEDIF(B13,C13, "MD") -> 25 | E13: =TEXT(Data!B13,"MMM-YYYY") -> Mar-2025 | F13: ="Q"&ROUNDUP(MONTH(B13)/3,0)&"-"&YEAR(B13) -> Q1-2025 | G13: Americas | H13: Brazil | I13: Brasília | J13: Non-Profit | K13: Online | L13: J. Njeri | M13: Components | N13: CMP-3693 | O13: 331.57 | P13: =IF(Q13<50, "Low", IF(Q13<200, "Medium", "High")) -> High | Q13: 548.4 | R13: 0.094 | S13: 10 | T13: =(Q39*S13)*(1-R13) -> 12644.498 | U13: =(O13*S13) -> 3315.7 | V13: =(T13-U13) -> 9328.7984 | W13: =IF(T13=0, 0, V13/T13) -> 0.73777528
A14: ORD-2024-890180 | B14: 45311 | C14: 45335 | D14: =DATEDIF(B14,C14, "MD") -> 24 | E14: =TEXT(Data!B14,"MMM-YYYY") -> Jan-2024 | F14: ="Q"&ROUNDUP(MONTH(B14)/3,0)&"-"&YEAR(B14) -> Q1-2024 | G14: Europe | H14: France | I14: Marseille | J14: Corporate | K14: Retail | L14: H. Kim | M14: Printers | N14: PRN-8392 | O14: 643.53 | P14: =IF(Q14<50, "Low", IF(Q14<200, "Medium", "High")) -> High | Q14: 1439.01 | R14: 0 | S14: 15 | T14: =(Q40*S14)*(1-R14) -> 6816.3 | U14: =(O14*S14) -> 9652.95 | V14: =(T14-U14) -> -2836.65 | W14: =IF(T14=0, 0, V14/T14) -> -0.41615686
A15: ORD-2025-840976 | B15: 45901 | C15: 45930 | D15: =DATEDIF(B15,C15, "MD") -> 29 | E15: =TEXT(Data!B15,"MMM-YYYY") -> Sep-2025 | F15: ="Q"&ROUNDUP(MONTH(B15)/3,0)&"-"&YEAR(B15) -> Q3-2025 | G15: Americas | H15: Brazil | I15: Brasília | J15: Education | K15: Retail | L15: K. Singh | M15: Accessories | N15: ACC-1663 | O15: 780.59 | P15: =IF(Q15<50, "Low", IF(Q15<200, "Medium", "High")) -> High | Q15: 631.57 | R15: 0 | S15: 12 | T15: =(Q41*S15)*(1-R15) -> 18971.64 | U15: =(O15*S15) -> 9367.08 | V15: =(T15-U15) -> 9604.56 | W15: =IF(T15=0, 0, V15/T15) -> 0.50625882
A16: ORD-2023-937291 | B16: 45039 | C16: 45038 | D16: =DATEDIF(C16, B16, "MD") -> 1 | E16: =TEXT(Data!B16,"MMM-YYYY") -> Apr-2023 | F16: ="Q"&ROUNDUP(MONTH(B16)/3,0)&"-"&YEAR(B16) -> Q2-2023 | G16: Africa | H16: Kenya | I16: Nairobi | J16: Small Business | K16: Direct | L16: E. Garcia | M16: Laptops | N16: LAP-1698 | O16: 756.51 | P16: =IF(Q16<50, "Low", IF(Q16<200, "Medium", "High")) -> High | Q16: 850.8 | R16: 0.074 | S16: 9 | T16: =(Q42*S16)*(1-R16) -> 14666.09 | U16: =(O16*S16) -> 6808.59 | V16: =(T16-U16) -> 7857.4999 | W16: =IF(T16=0, 0, V16/T16) -> 0.5357597
A17: ORD-2024-206081 | B17: 45636 | C17: 45665 | D17: =DATEDIF(B17,C17, "MD") -> 29 | E17: =TEXT(Data!B17,"MMM-YYYY") -> Dec-2024 | F17: ="Q"&ROUNDUP(MONTH(B17)/3,0)&"-"&YEAR(B17) -> Q4-2024 | G17: Europe | H17: France | I17: Marseille | J17: Small Business | K17: Retail | L17: K. Singh | M17: Printers | N17: PRN-6791 | O17: 891.08 | P17: =IF(Q17<50, "Low", IF(Q17<200, "Medium", "High")) -> High | Q17: 1040.1 | R17: 0.109 | S17: 28 | T17: =(Q43*S17)*(1-R17) -> 79945.866 | U17: =(O17*S17) -> 24950.24 | V17: =(T17-U17) -> 54995.626 | W17: =IF(T17=0, 0, V17/T17) -> 0.68791082
A18: ORD-2025-233883 | B18: 45908 | C18: 45916 | D18: =DATEDIF(B18,C18, "MD") -> 8 | E18: =TEXT(Data!B18,"MMM-YYYY") -> Sep-2025 | F18: ="Q"&ROUNDUP(MONTH(B18)/3,0)&"-"&YEAR(B18) -> Q3-2025 | G18: Asia | H18: Japan | I18: Osaka | J18: Corporate | K18: Distributor | L18: C. Otieno | M18: Phones | N18: PHN-1197 | O18: 1225.57 | P18: =IF(Q18<50, "Low", IF(Q18<200, "Medium", "High")) -> High | Q18: 2705.57 | R18: 0.183 | S18: 16 | T18: =(Q44*S18)*(1-R18) -> 14842.341 | U18: =(O18*S18) -> 19609.12 | V18: =(T18-U18) -> -4766.779 | W18: =IF(T18=0, 0, V18/T18) -> -0.32116086
A19: ORD-2025-843974 | B19: 45858 | C19: 45874 | D19: =DATEDIF(B19,C19, "MD") -> 16 | E19: =TEXT(Data!B19,"MMM-YYYY") -> Jul-2025 | F19: ="Q"&ROUNDUP(MONTH(B19)/3,0)&"-"&YEAR(B19) -> Q3-2025 | G19: Americas | H19: Brazil | I19: Brasília | J19: Enterprise | K19: Marketplace | L19: G. Dubois | M19: Accessories | N19: ACC-8098 | O19: 1068.17 | P19: =IF(Q19<50, "Low", IF(Q19<200, "Medium", "High")) -> High | Q19: 2375.37 | R19: 0.109 | S19: 18 | T19: =(Q45*S19)*(1-R19) -> 15979.622 | U19: =(O19*S19) -> 19227.06 | V19: =(T19-U19) -> -3247.4383 | W19: =IF(T19=0, 0, V19/T19) -> -0.20322373
A20: ORD-2025-745263 | B20: 45798 | C20: 45796 | D20: =DATEDIF(C20,B20, "MD") -> 2 | E20: =TEXT(Data!B20,"MMM-YYYY") -> May-2025 | F20: ="Q"&ROUNDUP(MONTH(B20)/3,0)&"-"&YEAR(B20) -> Q2-2025 | G20: Europe | H20: United Kingdom | I20: Birmingham | J20: Enterprise | K20: Online | L20: M. Rossi | M20: Laptops | N20: LAP-3385 | O20: 1015.16 | P20: =IF(Q20<50, "Low", IF(Q20<200, "Medium", "High")) -> High | Q20: 2148.14 | R20: 0.038 | S20: 19 | T20: =(Q46*S20)*(1-R20) -> 25535.28 | U20: =(O20*S20) -> 19288.04 | V20: =(T20-U20) -> 6247.2399 | W20: =IF(T20=0, 0, V20/T20) -> 0.24465132
A21: ORD-2024-798002 | B21: 45498 | C21: 45497 | D21: =DATEDIF(C21,B21, "MD") -> 1 | E21: =TEXT(Data!B21,"MMM-YYYY") -> Jul-2024 | F21: ="Q"&ROUNDUP(MONTH(B21)/3,0)&"-"&YEAR(B21) -> Q3-2024 | G21: Africa | H21: Kenya | I21: Mombasa | J21: Non-Profit | K21: Direct | L21: J. Njeri | M21: Laptops | N21: LAP-9815 | O21: 1494.4 | P21: =IF(Q21<50, "Low", IF(Q21<200, "Medium", "High")) -> High | Q21: 3661.07 | R21: 0.072 | S21: 7 | T21: =(Q47*S21)*(1-R21) -> 3565.5894 | U21: =(O21*S21) -> 10460.8 | V21: =(T21-U21) -> -6895.2106 | W21: =IF(T21=0, 0, V21/T21) -> -1.9338207
A22: ORD-2023-867836 | B22: 45057 | C22: 45074 | D22: =DATEDIF(B22,C22, "MD") -> 17 | E22: =TEXT(Data!B22,"MMM-YYYY") -> May-2023 | F22: ="Q"&ROUNDUP(MONTH(B22)/3,0)&"-"&YEAR(B22) -> Q2-2023 | G22: Asia | H22: China | I22: Shenzhen | J22: Enterprise | K22: Marketplace | L22: E. Garcia | M22: Networking | N22: NET-3255 | O22: 1331.19 | P22: =IF(Q22<50, "Low", IF(Q22<200, "Medium", "High")) -> High | Q22: 2903.09 | R22: 0.143 | S22: 8 | T22: =(Q48*S22)*(1-R22) -> 24160.544 | U22: =(O22*S22) -> 10649.52 | V22: =(T22-U22) -> 13511.024 | W22: =IF(T22=0, 0, V22/T22) -> 0.55921853
A23: ORD-2025-580047 | B23: 45822 | C23: 45837 | D23: =DATEDIF(B23,C23, "MD") -> 15 | E23: =TEXT(Data!B23,"MMM-YYYY") -> Jun-2025 | F23: ="Q"&ROUNDUP(MONTH(B23)/3,0)&"-"&YEAR(B23) -> Q2-2025 | G23: Africa | H23: Nigeria | I23: Port Harcourt | J23: Consumer | K23: Marketplace | L23: M. Rossi | M23: Accessories | N23: ACC-3961 | O23: 730.99 | P23: =IF(Q23<50, "Low", IF(Q23<200, "Medium", "High")) -> High | Q23: 1242.84 | R23: 0.12 | S23: 10 | T23: =(Q49*S23)*(1-R23) -> 16065.368 | U23: =(O23*S23) -> 7309.9 | V23: =(T23-U23) -> 8755.468 | W23: =IF(T23=0, 0, V23/T23) -> 0.54499019
A24: ORD-2024-500109 | B24: 45430 | C24: 45435 | D24: =DATEDIF(B24,C24, "MD") -> 5 | E24: =TEXT(Data!B24,"MMM-YYYY") -> May-2024 | F24: ="Q"&ROUNDUP(MONTH(B24)/3,0)&"-"&YEAR(B24) -> Q2-2024 | G24: Americas | H24: USA | I24: Chicago | J24: Enterprise | K24: Retail | L24: H. Kim | M24: Laptops | N24: LAP-4987 | O24: 1274.59 | P24: =IF(Q24<50, "Low", IF(Q24<200, "Medium", "High")) -> High | Q24: 2553.69 | R24: 0.01 | S24: 8 | T24: =(Q50*S24)*(1-R24) -> 14187.65 | U24: =(O24*S24) -> 10196.72 | V24: =(T24-U24) -> 3990.9304 | W24: =IF(T24=0, 0, V24/T24) -> 0.28129608
A25: ORD-2023-271836 | B25: 44964 | C25: 44969 | D25: =DATEDIF(B25,C25, "MD") -> 5 | E25: =TEXT(Data!B25,"MMM-YYYY") -> Feb-2023 | F25: ="Q"&ROUNDUP(MONTH(B25)/3,0)&"-"&YEAR(B25) -> Q1-2023 | G25: Americas | H25: Brazil | I25: São Paulo | J25: Education | K25: Online | L25: N. Brown | M25: Components | N25: CMP-2693 | O25: 948.55 | P25: =IF(Q25<50, "Low", IF(Q25<200, "Medium", "High")) -> High | Q25: 2089.16 | R25: 0.007 | S25: 12 | T25: =(Q51*S25)*(1-R25) -> 31336.101 | U25: =(O25*S25) -> 11382.6 | V25: =(T25-U25) -> 19953.501 | W25: =IF(T25=0, 0, V25/T25) -> 0.63675762
A26: ORD-2024-215294 | B26: 45473 | C26: 45487 | D26: =DATEDIF(B26,C26, "MD") -> 14 | E26: =TEXT(Data!B26,"MMM-YYYY") -> Jun-2024 | F26: ="Q"&ROUNDUP(MONTH(B26)/3,0)&"-"&YEAR(B26) -> Q2-2024 | G26: Americas | H26: Brazil | I26: Brasília | J26: Education | K26: Retail | L26: C. Otieno | M26: Accessories | N26: ACC-8683 | O26: 1491.85 | P26: =IF(Q26<50, "Low", IF(Q26<200, "Medium", "High")) -> High | Q26: 2583.02 | R26: 0.168 | S26: 4 | T26: =(Q52*S26)*(1-R26) -> 353.7664 | U26: =(O26*S26) -> 5967.4 | V26: =(T26-U26) -> -5613.6336 | W26: =IF(T26=0, 0, V26/T26) -> -15.868193
A27: ORD-2024-788105 | B27: 45626 | C27: 45656 | D27: =DATEDIF(B27,C27, "MD") -> 0 | E27: =TEXT(Data!B27,"MMM-YYYY") -> Nov-2024 | F27: ="Q"&ROUNDUP(MONTH(B27)/3,0)&"-"&YEAR(B27) -> Q4-2024 | G27: Europe | H27: France | I27: Marseille | J27: Consumer | K27: Marketplace | L27: F. Müller | M27: Printers | N27: PRN-4170 | O27: 117.64 | P27: =IF(Q27<50, "Low", IF(Q27<200, "Medium", "High")) -> Medium | Q27: 175.67 | R27: 0 | S27: 10 | T27: =(Q53*S27)*(1-R27) -> 3857.2 | U27: =(O27*S27) -> 1176.4 | V27: =(T27-U27) -> 2680.8 | W27: =IF(T27=0, 0, V27/T27) -> 0.69501193
A28: ORD-2024-855073 | B28: 45492 | C28: 45492 | D28: =DATEDIF(B28,C28, "MD") -> 0 | E28: =TEXT(Data!B28,"MMM-YYYY") -> Jul-2024 | F28: ="Q"&ROUNDUP(MONTH(B28)/3,0)&"-"&YEAR(B28) -> Q3-2024 | G28: Africa | H28: Kenya | I28: Kisumu | J28: Small Business | K28: Retail | L28: A. Patel | M28: Phones | N28: PHN-6854 | O28: 857.24 | P28: =IF(Q28<50, "Low", IF(Q28<200, "Medium", "High")) -> High | Q28: 758.23 | R28: 0.125 | S28: 6 | T28: =(Q54*S28)*(1-R28) -> 1243.5675 | U28: =(O28*S28) -> 5143.44 | V28: =(T28-U28) -> -3899.8725 | W28: =IF(T28=0, 0, V28/T28) -> -3.136036
A29: ORD-2023-897079 | B29: 45030 | C29: 45060 | D29: =DATEDIF(B29,C29, "MD") -> 0 | E29: =TEXT(Data!B29,"MMM-YYYY") -> Apr-2023 | F29: ="Q"&ROUNDUP(MONTH(B29)/3,0)&"-"&YEAR(B29) -> Q2-2023 | G29: Africa | H29: Kenya | I29: Nakuru | J29: Consumer | K29: Marketplace | L29: M. Rossi | M29: Phones | N29: PHN-1784 | O29: 209.25 | P29: =IF(Q29<50, "Low", IF(Q29<200, "Medium", "High")) -> High | Q29: 434.8 | R29: 0 | S29: 9 | T29: =(Q55*S29)*(1-R29) -> 377.1 | U29: =(O29*S29) -> 1883.25 | V29: =(T29-U29) -> -1506.15 | W29: =IF(T29=0, 0, V29/T29) -> -3.9940334
A30: ORD-2025-548982 | B30: 45754 | C30: 45758 | D30: =DATEDIF(B30,C30, "MD") -> 4 | E30: =TEXT(Data!B30,"MMM-YYYY") -> Apr-2025 | F30: ="Q"&ROUNDUP(MONTH(B30)/3,0)&"-"&YEAR(B30) -> Q2-2025 | G30: Europe | H30: France | I30: Lyon | J30: Education | K30: Retail | L30: E. Garcia | M30: Networking | N30: NET-9716 | O30: 754.77 | P30: =IF(Q30<50, "Low", IF(Q30<200, "Medium", "High")) -> High | Q30: 1666.18 | R30: 0.139 | S30: 14 | T30: =(Q56*S30)*(1-R30) -> 11781.339 | U30: =(O30*S30) -> 10566.78 | V30: =(T30-U30) -> 1214.5585 | W30: =IF(T30=0, 0, V30/T30) -> 0.10309173
A31: ORD-2024-170313 | B31: 45653 | C31: 45672 | D31: =DATEDIF(B31,C31, "MD") -> 19 | E31: =TEXT(Data!B31,"MMM-YYYY") -> Dec-2024 | F31: ="Q"&ROUNDUP(MONTH(B31)/3,0)&"-"&YEAR(B31) -> Q4-2024 | G31: Asia | H31: India | I31: Delhi | J31: Non-Profit | K31: Distributor | L31: G. Dubois | M31: Components | N31: CMP-6919 | O31: 495.59 | P31: =IF(Q31<50, "Low", IF(Q31<200, "Medium", "High")) -> High | Q31: 631.78 | R31: 0.087 | S31: 17 | T31: =(Q57*S31)*(1-R31) -> 43367.692 | U31: =(O31*S31) -> 8425.03 | V31: =(T31-U31) -> 34942.662 | W31: =IF(T31=0, 0, V31/T31) -> 0.80573026
A32: ORD-2023-562894 | B32: 44980 | C32: 45010 | D32: =DATEDIF(B32,C32, "MD") -> 2 | E32: =TEXT(Data!B32,"MMM-YYYY") -> Feb-2023 | F32: ="Q"&ROUNDUP(MONTH(B32)/3,0)&"-"&YEAR(B32) -> Q1-2023 | G32: Americas | H32: Canada | I32: Montreal | J32: Enterprise | K32: Online | L32: D. Smith | M32: Phones | N32: PHN-4854 | O32: 1242.66 | P32: =IF(Q32<50, "Low", IF(Q32<200, "Medium", "High")) -> High | Q32: 1794.07 | R32: 0.089 | S32: 16 | T32: =(Q58*S32)*(1-R32) -> 10231.623 | U32: =(O32*S32) -> 19882.56 | V32: =(T32-U32) -> -9650.9368 | W32: =IF(T32=0, 0, V32/T32) -> -0.94324592
A33: ORD-2025-474710 | B33: 45862 | C33: 45875 | D33: =DATEDIF(B33,C33, "MD") -> 13 | E33: =TEXT(Data!B33,"MMM-YYYY") -> Jul-2025 | F33: ="Q"&ROUNDUP(MONTH(B33)/3,0)&"-"&YEAR(B33) -> Q3-2025 | G33: Africa | H33: South Africa | I33: Johannesburg | J33: Education | K33: Marketplace | L33: D. Smith | M33: Networking | N33: NET-7966 | O33: 1463.9 | P33: =IF(Q33<50, "Low", IF(Q33<200, "Medium", "High")) -> High | Q33: 2633.02 | R33: 0.084 | S33: 4 | T33: =(Q59*S33)*(1-R33) -> -19.30928 | U33: =(O33*S33) -> 5855.6 | V33: =(T33-U33) -> -5874.9093 | W33: =IF(T33=0, 0, V33/T33) -> 304.25315
A34: ORD-2024-629525 | B34: 45400 | C34: 45420 | D34: =DATEDIF(B34,C34, "MD") -> 20 | E34: =TEXT(Data!B34,"MMM-YYYY") -> Apr-2024 | F34: ="Q"&ROUNDUP(MONTH(B34)/3,0)&"-"&YEAR(B34) -> Q2-2024 | G34: Europe | H34: United Kingdom | I34: London | J34: Non-Profit | K34: Not Provided | L34: D. Smith | M34: Laptops | N34: LAP-9932 | O34: 645.33 | P34: =IF(Q34<50, "Low", IF(Q34<200, "Medium", "High")) -> High | Q34: 1321.85 | R34: 0 | S34: 10 | T34: =(Q60*S34)*(1-R34) -> 14370.6 | U34: =(O34*S34) -> 6453.3 | V34: =(T34-U34) -> 7917.3 | W34: =IF(T34=0, 0, V34/T34) -> 0.55093733
A35: ORD-2024-167215 | B35: 45527 | C35: 45525 | D35: =DATEDIF(C35,B35, "MD") -> 2 | E35: =TEXT(Data!B35,"MMM-YYYY") -> Aug-2024 | F35: ="Q"&ROUNDUP(MONTH(B35)/3,0)&"-"&YEAR(B35) -> Q3-2024 | G35: Africa | H35: South Africa | I35: Johannesburg | J35: Education | K35: Retail | L35: E. Garcia | M35: Components | N35: CMP-1559 | O35: 1432.52 | P35: =IF(Q35<50, "Low", IF(Q35<200, "Medium", "High")) -> High | Q35: 3036.87 | R35: 0 | S35: 9 | T35: =(Q61*S35)*(1-R35) -> 17207.01 | U35: =(O35*S35) -> 12892.68 | V35: =(T35-U35) -> 4314.33 | W35: =IF(T35=0, 0, V35/T35) -> 0.25073095
A36: ORD-2023-864121 | B36: 45012 | C36: 45038 | D36: =DATEDIF(B36,C36, "MD") -> 26 | E36: =TEXT(Data!B36,"MMM-YYYY") -> Mar-2023 | F36: ="Q"&ROUNDUP(MONTH(B36)/3,0)&"-"&YEAR(B36) -> Q1-2023 | G36: Asia | H36: India | I36: Delhi | J36: Non-Profit | K36: Marketplace | L36: J. Njeri | M36: Printers | N36: PRN-4506 | O36: 178.53 | P36: =IF(Q36<50, "Low", IF(Q36<200, "Medium", "High")) -> Medium | Q36: 199.37 | R36: 0.101 | S36: 37 | T36: =(Q62*S36)*(1-R36) -> 86276.904 | U36: =(O36*S36) -> 6605.61 | V36: =(T36-U36) -> 79671.294 | W36: =IF(T36=0, 0, V36/T36) -> 0.9234371
A37: ORD-2024-692673 | B37: 45358 | C37: 45376 | D37: =DATEDIF(B37,C37, "MD") -> 18 | E37: =TEXT(Data!B37,"MMM-YYYY") -> Mar-2024 | F37: ="Q"&ROUNDUP(MONTH(B37)/3,0)&"-"&YEAR(B37) -> Q1-2024 | G37: Europe | H37: Germany | I37: Munich | J37: Corporate | K37: Online | L37: B. Chen | M37: Components | N37: CMP-7617 | O37: 712.84 | P37: =IF(Q37<50, "Low", IF(Q37<200, "Medium", "High")) -> High | Q37: 927.51 | R37: 0.243 | S37: 27 | T37: =(Q63*S37)*(1-R37) -> 25427.751 | U37: =(O37*S37) -> 19246.68 | V37: =(T37-U37) -> 6181.0711 | W37: =IF(T37=0, 0, V37/T37) -> 0.24308367
A38: ORD-2025-718992 | B38: 45832 | C38: 45848 | D38: =DATEDIF(B38,C38, "MD") -> 16 | E38: =TEXT(Data!B38,"MMM-YYYY") -> Jun-2025 | F38: ="Q"&ROUNDUP(MONTH(B38)/3,0)&"-"&YEAR(B38) -> Q2-2025 | G38: Asia | H38: China | I38: Shanghai | J38: Enterprise | K38: Direct | L38: N. Brown | M38: Components | N38: CMP-8390 | O38: 757.19 | P38: =IF(Q38<50, "Low", IF(Q38<200, "Medium", "High")) -> High | Q38: 1735.41 | R38: 0.136 | S38: 8 | T38: =(Q64*S38)*(1-R38) -> 13219.269 | U38: =(O38*S38) -> 6057.52 | V38: =(T38-U38) -> 7161.7491 | W38: =IF(T38=0, 0, V38/T38) -> 0.54176589
A39: ORD-2024-599522 | B39: 45401 | C39: 45418 | D39: =DATEDIF(B39,C39, "MD") -> 17 | E39: =TEXT(Data!B39,"MMM-YYYY") -> Apr-2024 | F39: ="Q"&ROUNDUP(MONTH(B39)/3,0)&"-"&YEAR(B39) -> Q2-2024 | G39: Africa | H39: Nigeria | I39: Port Harcourt | J39: Non-Profit | K39: Online | L39: A. Patel | M39: Printers | N39: PRN-7303 | O39: 865.33 | P39: =IF(Q39<50, "Low", IF(Q39<200, "Medium", "High")) -> High | Q39: 1395.64 | R39: 0.175 | S39: 13 | T39: =(Q65*S39)*(1-R39) -> 8106.7057 | U39: =(O39*S39) -> 11249.29 | V39: =(T39-U39) -> -3142.5843 | W39: =IF(T39=0, 0, V39/T39) -> -0.38765244
A40: ORD-2023-651638 | B40: 45094 | C40: 45101 | D40: =DATEDIF(B40,C40, "MD") -> 7 | E40: =TEXT(Data!B40,"MMM-YYYY") -> Jun-2023 | F40: ="Q"&ROUNDUP(MONTH(B40)/3,0)&"-"&YEAR(B40) -> Q2-2023 | G40: Americas | H40: USA | I40: San Francisco | J40: Corporate | K40: Retail | L40: I. Johnson | M40: Printers | N40: PRN-6536 | O40: 313.99 | P40: =IF(Q40<50, "Low", IF(Q40<200, "Medium", "High")) -> High | Q40: 454.42 | R40: 0.129 | S40: 9 | T40: =(Q66*S40)*(1-R40) -> 8980.9071 | U40: =(O40*S40) -> 2825.91 | V40: =(T40-U40) -> 6154.9971 | W40: =IF(T40=0, 0, V40/T40) -> 0.68534248
A41: ORD-2024-635626 | B41: 45531 | C41: 45554 | D41: =DATEDIF(B41,C41, "MD") -> 23 | E41: =TEXT(Data!B41,"MMM-YYYY") -> Aug-2024 | F41: ="Q"&ROUNDUP(MONTH(B41)/3,0)&"-"&YEAR(B41) -> Q3-2024 | G41: Europe | H41: Germany | I41: Berlin | J41: Small Business | K41: Direct | L41: D. Smith | M41: Monitors | N41: MON-9967 | O41: 1024.01 | P41: =IF(Q41<50, "Low", IF(Q41<200, "Medium", "High")) -> High | Q41: 1580.97 | R41: 0.037 | S41: 27 | T41: =(Q67*S41)*(1-R41) -> 32087.834 | U41: =(O41*S41) -> 27648.27 | V41: =(T41-U41) -> 4439.5641 | W41: =IF(T41=0, 0, V41/T41) -> 0.13835661
A42: ORD-2024-296582 | B42: 45302 | C42: 45324 | D42: =DATEDIF(B42,C42, "MD") -> 22 | E42: =TEXT(Data!B42,"MMM-YYYY") -> Jan-2024 | F42: ="Q"&ROUNDUP(MONTH(B42)/3,0)&"-"&YEAR(B42) -> Q1-2024 | G42: Africa | H42: South Africa | I42: Durban | J42: Consumer | K42: Online | L42: K. Singh | M42: Networking | N42: NET-1412 | O42: 1206.2 | P42: =IF(Q42<50, "Low", IF(Q42<200, "Medium", "High")) -> High | Q42: 1759.79 | R42: 0 | S42: 6 | T42: =(Q68*S42)*(1-R42) -> 7368.06 | U42: =(O42*S42) -> 7237.2 | V42: =(T42-U42) -> 130.86 | W42: =IF(T42=0, 0, V42/T42) -> 0.017760442
A43: ORD-2024-998320 | B43: 45590 | C43: 45610 | D43: =DATEDIF(B43,C43, "MD") -> 20 | E43: =TEXT(Data!B43,"MMM-YYYY") -> Oct-2024 | F43: ="Q"&ROUNDUP(MONTH(B43)/3,0)&"-"&YEAR(B43) -> Q4-2024 | G43: Africa | H43: Kenya | I43: Mombasa | J43: Corporate | K43: Direct | L43: H. Kim | M43: Printers | N43: PRN-3143 | O43: 1396.48 | P43: =IF(Q43<50, "Low", IF(Q43<200, "Medium", "High")) -> High | Q43: 3204.5 | R43: 0.318 | S43: 14 | T43: =(Q69*S43)*(1-R43) -> 5778.736 | U43: =(O43*S43) -> 19550.72 | V43: =(T43-U43) -> -13771.984 | W43: =IF(T43=0, 0, V43/T43) -> -2.3832173
A44: ORD-2025-820255 | B44: 45806 | C44: 45828 | D44: =DATEDIF(B44,C44, "MD") -> 22 | E44: =TEXT(Data!B44,"MMM-YYYY") -> May-2025 | F44: ="Q"&ROUNDUP(MONTH(B44)/3,0)&"-"&YEAR(B44) -> Q2-2025 | G44: Europe | H44: Germany | I44: Berlin | J44: Corporate | K44: Direct | L44: A. Patel | M44: Printers | N44: PRN-9787 | O44: 483.47 | P44: =IF(Q44<50, "Low", IF(Q44<200, "Medium", "High")) -> High | Q44: 1135.43 | R44: 0.146 | S44: 11 | T44: =(Q70*S44)*(1-R44) -> 17662.129 | U44: =(O44*S44) -> 5318.17 | V44: =(T44-U44) -> 12343.959 | W44: =IF(T44=0, 0, V44/T44) -> 0.69889417
A45: ORD-2024-389336 | B45: 45432 | C45: 45445 | D45: =DATEDIF(B45,C45, "MD") -> 13 | E45: =TEXT(Data!B45,"MMM-YYYY") -> May-2024 | F45: ="Q"&ROUNDUP(MONTH(B45)/3,0)&"-"&YEAR(B45) -> Q2-2024 | G45: Americas | H45: Canada | I45: Vancouver | J45: Enterprise | K45: Marketplace | L45: K. Singh | M45: Components | N45: CMP-5946 | O45: 675.43 | P45: =IF(Q45<50, "Low", IF(Q45<200, "Medium", "High")) -> High | Q45: 996.36 | R45: 0.182 | S45: 22 | T45: =(Q71*S45)*(1-R45) -> 22844.122 | U45: =(O45*S45) -> 14859.46 | V45: =(T45-U45) -> 7984.6624 | W45: =IF(T45=0, 0, V45/T45) -> 0.34952809
A46: ORD-2023-308124 | B46: 45035 | C46: 45046 | D46: =DATEDIF(B46,C46, "MD") -> 11 | E46: =TEXT(Data!B46,"MMM-YYYY") -> Apr-2023 | F46: ="Q"&ROUNDUP(MONTH(B46)/3,0)&"-"&YEAR(B46) -> Q2-2023 | G46: Asia | H46: India | I46: Delhi | J46: Small Business | K46: Retail | L46: A. Patel | M46: Networking | N46: NET-2062 | O46: 826.55 | P46: =IF(Q46<50, "Low", IF(Q46<200, "Medium", "High")) -> High | Q46: 1397.05 | R46: 0.169 | S46: 28 | T46: =(Q72*S46)*(1-R46) -> 14447.799 | U46: =(O46*S46) -> 23143.4 | V46: =(T46-U46) -> -8695.6008 | W46: =IF(T46=0, 0, V46/T46) -> -0.60186334
A47: ORD-2023-128295 | B47: 45100 | C47: 45110 | D47: =DATEDIF(B47,C47, "MD") -> 10 | E47: =TEXT(Data!B47,"MMM-YYYY") -> Jun-2023 | F47: ="Q"&ROUNDUP(MONTH(B47)/3,0)&"-"&YEAR(B47) -> Q2-2023 | G47: Africa | H47: Nigeria | I47: Abuja | J47: Consumer | K47: Online | L47: J. Njeri | M47: Printers | N47: PRN-2542 | O47: 337.75 | P47: =IF(Q47<50, "Low", IF(Q47<200, "Medium", "High")) -> High | Q47: 548.89 | R47: 0 | S47: 13 | T47: =(Q73*S47)*(1-R47) -> 18926.83 | U47: =(O47*S47) -> 4390.75 | V47: =(T47-U47) -> 14536.08 | W47: =IF(T47=0, 0, V47/T47) -> 0.76801451
... A74: ORD-2024-800947 | B74: 45641 | C74: 45646 | D74: =DATEDIF(B74,C74, "MD") -> 5 | E74: =TEXT(Data!B74,"MMM-YYYY") -> Dec-2024 | F74: ="Q"&ROUNDUP(MONTH(B74)/3,0)&"-"&YEAR(B74) -> Q4-2024 | G74: Asia | H74: China | I74: Shenzhen | J74: Small Business | K74: Direct | L74: J. Njeri | M74: Networking | N74: NET-1846 | O74: 717.55 | P74: =IF(Q74<50, "Low", IF(Q74<200, "Medium", "High")) -> High | Q74: 546.43 | R74: 0.047 | S74: 18 | T74: =(Q100*S74)*(1-R74) -> 34328.07 | U74: =(O74*S74) -> 12915.9 | V74: =(T74-U74) -> 21412.17 | W74: =IF(T74=0, 0, V74/T74) -> 0.62375106
A75: ORD-2023-382272 | B75: 45066 | C75: 45064 | D75: =DATEDIF(C75,B75, "MD") -> 2 | E75: =TEXT(Data!B75,"MMM-YYYY") -> May-2023 | F75: ="Q"&ROUNDUP(MONTH(B75)/3,0)&"-"&YEAR(B75) -> Q2-2023 | G75: Africa | H75: South Africa | I75: Durban | J75: Corporate | K75: Distributor | L75: A. Patel | M75: Components | N75: CMP-5208 | O75: 917.88 | P75: =IF(Q75<50, "Low", IF(Q75<200, "Medium", "High")) -> High | Q75: 1347.92 | R75: 0.343 | S75: 5 | T75: =(Q101*S75)*(1-R75) -> 10198.972 | U75: =(O75*S75) -> 4589.4 | V75: =(T75-U75) -> 5609.5724 | W75: =IF(T75=0, 0, V75/T75) -> 0.55001349
A76: ORD-2023-722117 | B76: 45187 | C76: 45207 | D76: =DATEDIF(B76,C76, "MD") -> 20 | E76: =TEXT(Data!B76,"MMM-YYYY") -> Sep-2023 | F76: ="Q"&ROUNDUP(MONTH(B76)/3,0)&"-"&YEAR(B76) -> Q3-2023 | G76: Asia | H76: India | I76: Delhi | J76: Small Business | K76: Direct | L76: B. Chen | M76: Components | N76: CMP-1009 | O76: 825.64 | P76: =IF(Q76<50, "Low", IF(Q76<200, "Medium", "High")) -> High | Q76: 1108.43 | R76: 0.114 | S76: 7 | T76: =(Q102*S76)*(1-R76) -> 2073.2046 | U76: =(O76*S76) -> 5779.48 | V76: =(T76-U76) -> -3706.2754 | W76: =IF(T76=0, 0, V76/T76) -> -1.7877037
A77: ORD-2024-446699 | B77: 45532 | C77: 45560 | D77: =DATEDIF(B77,C77, "MD") -> 28 | E77: =TEXT(Data!B77,"MMM-YYYY") -> Aug-2024 | F77: ="Q"&ROUNDUP(MONTH(B77)/3,0)&"-"&YEAR(B77) -> Q3-2024 | G77: Americas | H77: Brazil | I77: Rio de Janeiro | J77: Non-Profit | K77: Online | L77: Not Provided | M77: Accessories | N77: ACC-4490 | O77: 1394.65 | P77: =IF(Q77<50, "Low", IF(Q77<200, "Medium", "High")) -> High | Q77: 3144.1 | R77: 0.134 | S77: 13 | T77: =(Q103*S77)*(1-R77) -> 21984.96 | U77: =(O77*S77) -> 18130.45 | V77: =(T77-U77) -> 3854.5101 | W77: =IF(T77=0, 0, V77/T77) -> 0.17532486
A78: ORD-2024-451005 | B78: 45473 | C78: 45471 | D78: =DATEDIF(C78,B78, "MD") -> 2 | E78: =TEXT(Data!B78,"MMM-YYYY") -> Jun-2024 | F78: ="Q"&ROUNDUP(MONTH(B78)/3,0)&"-"&YEAR(B78) -> Q2-2024 | G78: Americas | H78: Brazil | I78: Rio de Janeiro | J78: Small Business | K78: Direct | L78: L. Okafor | M78: Accessories | N78: ACC-9162 | O78: 1112.98 | P78: =IF(Q78<50, "Low", IF(Q78<200, "Medium", "High")) -> High | Q78: 2095.73 | R78: 0.072 | S78: 17 | T78: =(Q104*S78)*(1-R78) -> 3822.367 | U78: =(O78*S78) -> 18920.66 | V78: =(T78-U78) -> -15098.293 | W78: =IF(T78=0, 0, V78/T78) -> -3.9499851
A79: ORD-2023-290279 | B79: 45091 | C79: 45093 | D79: =DATEDIF(B79,C79, "MD") -> 2 | E79: =TEXT(Data!B79,"MMM-YYYY") -> Jun-2023 | F79: ="Q"&ROUNDUP(MONTH(B79)/3,0)&"-"&YEAR(B79) -> Q2-2023 | G79: Europe | H79: United Kingdom | I79: Manchester | J79: Non-Profit | K79: Direct | L79: K. Singh | M79: Components | N79: CMP-5820 | O79: 357.36 | P79: =IF(Q79<50, "Low", IF(Q79<200, "Medium", "High")) -> High | Q79: 703.62 | R79: 0.257 | S79: 20 | T79: =(Q105*S79)*(1-R79) -> 44117.408 | U79: =(O79*S79) -> 7147.2 | V79: =(T79-U79) -> 36970.208 | W79: =IF(T79=0, 0, V79/T79) -> 0.83799592
A80: ORD-2024-192263 | B80: 45617 | C80: 45647 | D80: =DATEDIF(B80,C80, "MD") -> 0 | E80: =TEXT(Data!B80,"MMM-YYYY") -> Nov-2024 | F80: ="Q"&ROUNDUP(MONTH(B80)/3,0)&"-"&YEAR(B80) -> Q4-2024 | G80: Europe | H80: France | I80: Marseille | J80: Small Business | K80: Direct | L80: I. Johnson | M80: Monitors | N80: MON-7943 | O80: 1122.68 | P80: =IF(Q80<50, "Low", IF(Q80<200, "Medium", "High")) -> High | Q80: 1997.19 | R80: 0.186 | S80: 3 | T80: =(Q106*S80)*(1-R80) -> 3404.8806 | U80: =(O80*S80) -> 3368.04 | V80: =(T80-U80) -> 36.8406 | W80: =IF(T80=0, 0, V80/T80) -> 0.010819939
A81: ORD-2023-159379 | B81: 44965 | C81: 44968 | D81: =DATEDIF(B81,C81, "MD") -> 3 | E81: =TEXT(Data!B81,"MMM-YYYY") -> Feb-2023 | F81: ="Q"&ROUNDUP(MONTH(B81)/3,0)&"-"&YEAR(B81) -> Q1-2023 | G81: Africa | H81: South Africa | I81: Cape Town | J81: Corporate | K81: Direct | L81: M. Rossi | M81: Networking | N81: NET-5018 | O81: 1410.05 | P81: =IF(Q81<50, "Low", IF(Q81<200, "Medium", "High")) -> High | Q81: 2763.95 | R81: 0.161 | S81: 26 | T81: =(Q107*S81)*(1-R81) -> 336.15374 | U81: =(O81*S81) -> 36661.3 | V81: =(T81-U81) -> -36325.146 | W81: =IF(T81=0, 0, V81/T81) -> -108.06111
A82: ORD-2023-343322 | B82: 45157 | C82: 45181 | D82: =DATEDIF(B82,C82, "MD") -> 24 | E82: =TEXT(Data!B82,"MMM-YYYY") -> Aug-2023 | F82: ="Q"&ROUNDUP(MONTH(B82)/3,0)&"-"&YEAR(B82) -> Q3-2023 | G82: Americas | H82: Canada | I82: Vancouver | J82: Enterprise | K82: Retail | L82: I. Johnson | M82: Printers | N82: PRN-9669 | O82: 1183.95 | P82: =IF(Q82<50, "Low", IF(Q82<200, "Medium", "High")) -> High | Q82: 1503.53 | R82: 0.241 | S82: 16 | T82: =(Q108*S82)*(1-R82) -> 27333.837 | U82: =(O82*S82) -> 18943.2 | V82: =(T82-U82) -> 8390.6366 | W82: =IF(T82=0, 0, V82/T82) -> 0.30696886
A83: ORD-2025-114382 | B83: 45791 | C83: 45801 | D83: =DATEDIF(B83,C83, "MD") -> 10 | E83: =TEXT(Data!B83,"MMM-YYYY") -> May-2025 | F83: ="Q"&ROUNDUP(MONTH(B83)/3,0)&"-"&YEAR(B83) -> Q2-2025 | G83: Europe | H83: France | I83: Paris | J83: Small Business | K83: Marketplace | L83: K. Singh | M83: Components | N83: CMP-2865 | O83: 170.39 | P83: =IF(Q83<50, "Low", IF(Q83<200, "Medium", "High")) -> High | Q83: 388.04 | R83: 0.084 | S83: 15 | T83: =(Q109*S83)*(1-R83) -> 2281.3896 | U83: =(O83*S83) -> 2555.85 | V83: =(T83-U83) -> -274.4604 | W83: =IF(T83=0, 0, V83/T83) -> -0.12030405
A84: ORD-2025-488349 | B84: 45770 | C84: 45769 | D84: =DATEDIF(C84,B84, "MD") -> 1 | E84: =TEXT(Data!B84,"MMM-YYYY") -> Apr-2025 | F84: ="Q"&ROUNDUP(MONTH(B84)/3,0)&"-"&YEAR(B84) -> Q2-2025 | G84: Americas | H84: USA | I84: San Francisco | J84: Non-Profit | K84: Distributor | L84: D. Smith | M84: Monitors | N84: MON-3371 | O84: 23.24 | P84: =IF(Q84<50, "Low", IF(Q84<200, "Medium", "High")) -> Low | Q84: 44.57 | R84: 0.215 | S84: 15 | T84: =(Q110*S84)*(1-R84) -> 4198.3763 | U84: =(O84*S84) -> 348.6 | V84: =(T84-U84) -> 3849.7763 | W84: =IF(T84=0, 0, V84/T84) -> 0.9169679
A85: ORD-2025-330203 | B85: 45741 | C85: 45764 | D85: =DATEDIF(B85,C85, "MD") -> 23 | E85: =TEXT(Data!B85,"MMM-YYYY") -> Mar-2025 | F85: ="Q"&ROUNDUP(MONTH(B85)/3,0)&"-"&YEAR(B85) -> Q1-2025 | G85: Europe | H85: United Kingdom | I85: London | J85: Consumer | K85: Retail | L85: H. Kim | M85: Networking | N85: NET-7166 | O85: 1421.19 | P85: =IF(Q85<50, "Low", IF(Q85<200, "Medium", "High")) -> High | Q85: 1808.26 | R85: 0.104 | S85: 13 | T85: =(Q111*S85)*(1-R85) -> 11939.782 | U85: =(O85*S85) -> 18475.47 | V85: =(T85-U85) -> -6535.6876 | W85: =IF(T85=0, 0, V85/T85) -> -0.5473875
A86: ORD-2023-841426 | B86: 45282 | C86: 45283 | D86: =DATEDIF(B86,C86, "MD") -> 1 | E86: =TEXT(Data!B86,"MMM-YYYY") -> Dec-2023 | F86: ="Q"&ROUNDUP(MONTH(B86)/3,0)&"-"&YEAR(B86) -> Q4-2023 | G86: Africa | H86: South Africa | I86: Cape Town | J86: Non-Profit | K86: Marketplace | L86: D. Smith | M86: Components | N86: CMP-4531 | O86: 1186.18 | P86: =IF(Q86<50, "Low", IF(Q86<200, "Medium", "High")) -> High | Q86: 1285.09 | R86: 0.07 | S86: 11 | T86: =(Q112*S86)*(1-R86) -> 18364.589 | U86: =(O86*S86) -> 13047.98 | V86: =(T86-U86) -> 5316.6091 | W86: =IF(T86=0, 0, V86/T86) -> 0.2895033
A87: ORD-2024-594592 | B87: 45388 | C87: 45407 | D87: =DATEDIF(B87,C87, "MD") -> 19 | E87: =TEXT(Data!B87,"MMM-YYYY") -> Apr-2024 | F87: ="Q"&ROUNDUP(MONTH(B87)/3,0)&"-"&YEAR(B87) -> Q2-2024 | G87: Asia | H87: China | I87: Shanghai | J87: Corporate | K87: Retail | L87: K. Singh | M87: Components | N87: CMP-8196 | O87: 1366.48 | P87: =IF(Q87<50, "Low", IF(Q87<200, "Medium", "High")) -> High | Q87: 1678.14 | R87: 0.154 | S87: 10 | T87: =(Q113*S87)*(1-R87) -> 36.9702 | U87: =(O87*S87) -> 13664.8 | V87: =(T87-U87) -> -13627.83 | W87: =IF(T87=0, 0, V87/T87) -> -368.61661
A88: ORD-2025-863978 | B88: 45876 | C88: 45888 | D88: =DATEDIF(B88,C88, "MD") -> 12 | E88: =TEXT(Data!B88,"MMM-YYYY") -> Aug-2025 | F88: ="Q"&ROUNDUP(MONTH(B88)/3,0)&"-"&YEAR(B88) -> Q3-2025 | G88: Africa | H88: Kenya | I88: Nakuru | J88: Corporate | K88: Not Provided | L88: M. Rossi | M88: Components | N88: CMP-2854 | O88: 601.51 | P88: =IF(Q88<50, "Low", IF(Q88<200, "Medium", "High")) -> High | Q88: 679.35 | R88: 0.188 | S88: 3 | T88: =(Q114*S88)*(1-R88) -> 532.266 | U88: =(O88*S88) -> 1804.53 | V88: =(T88-U88) -> -1272.264 | W88: =IF(T88=0, 0, V88/T88) -> -2.3902785
A89: ORD-2024-604471 | B89: 45312 | C89: 45316 | D89: =DATEDIF(B89,C89, "MD") -> 4 | E89: =TEXT(Data!B89,"MMM-YYYY") -> Jan-2024 | F89: ="Q"&ROUNDUP(MONTH(B89)/3,0)&"-"&YEAR(B89) -> Q1-2024 | G89: Asia | H89: India | I89: Delhi | J89: Consumer | K89: Direct | L89: C. Otieno | M89: Monitors | N89: MON-8973 | O89: 523.7 | P89: =IF(Q89<50, "Low", IF(Q89<200, "Medium", "High")) -> High | Q89: 1109.92 | R89: 0.03 | S89: 11 | T89: =(Q115*S89)*(1-R89) -> 2666.1129 | U89: =(O89*S89) -> 5760.7 | V89: =(T89-U89) -> -3094.5871 | W89: =IF(T89=0, 0, V89/T89) -> -1.1607112
A90: ORD-2023-258768 | B90: 45106 | C90: 45109 | D90: =DATEDIF(B90,C90, "MD") -> 3 | E90: =TEXT(Data!B90,"MMM-YYYY") -> Jun-2023 | F90: ="Q"&ROUNDUP(MONTH(B90)/3,0)&"-"&YEAR(B90) -> Q2-2023 | G90: Asia | H90: Japan | I90: Nagoya | J90: Education | K90: Marketplace | L90: F. Müller | M90: Monitors | N90: MON-2990 | O90: 55.65 | P90: =IF(Q90<50, "Low", IF(Q90<200, "Medium", "High")) -> Medium | Q90: 83.57 | R90: 0.066 | S90: 8 | T90: =(Q116*S90)*(1-R90) -> 25677.677 | U90: =(O90*S90) -> 445.2 | V90: =(T90-U90) -> 25232.477 | W90: =IF(T90=0, 0, V90/T90) -> 0.98266198
A91: ORD-2025-626047 | B91: 45775 | C91: 45792 | D91: =DATEDIF(B91,C91, "MD") -> 17 | E91: =TEXT(Data!B91,"MMM-YYYY") -> Apr-2025 | F91: ="Q"&ROUNDUP(MONTH(B91)/3,0)&"-"&YEAR(B91) -> Q2-2025 | G91: Asia | H91: Japan | I91: Nagoya | J91: Education | K91: Direct | L91: N. Brown | M91: Networking | N91: NET-1966 | O91: 691.19 | P91: =IF(Q91<50, "Low", IF(Q91<200, "Medium", "High")) -> High | Q91: 1284.3 | R91: 0.074 | S91: 7 | T91: =(Q117*S91)*(1-R91) -> 346.4629 | U91: =(O91*S91) -> 4838.33 | V91: =(T91-U91) -> -4491.8671 | W91: =IF(T91=0, 0, V91/T91) -> -12.96493
A92: ORD-2025-526752 | B92: 45817 | C92: 45833 | D92: =DATEDIF(B92,C92, "MD") -> 16 | E92: =TEXT(Data!B92,"MMM-YYYY") -> Jun-2025 | F92: ="Q"&ROUNDUP(MONTH(B92)/3,0)&"-"&YEAR(B92) -> Q2-2025 | G92: Asia | H92: India | I92: Hyderabad | J92: Enterprise | K92: Distributor | L92: M. Rossi | M92: Phones | N92: PHN-3482 | O92: 527.33 | P92: =IF(Q92<50, "Low", IF(Q92<200, "Medium", "High")) -> High | Q92: 911.72 | R92: 0.144 | S92: 25 | T92: =(Q118*S92)*(1-R92) -> 74251.58 | U92: =(O92*S92) -> 13183.25 | V92: =(T92-U92) -> 61068.33 | W92: =IF(T92=0, 0, V92/T92) -> 0.82245159
A93: ORD-2023-374486 | B93: 45101 | C93: 45100 | D93: =DATEDIF(C93,B93, "MD") -> 1 | E93: =TEXT(Data!B93,"MMM-YYYY") -> Jun-2023 | F93: ="Q"&ROUNDUP(MONTH(B93)/3,0)&"-"&YEAR(B93) -> Q2-2023 | G93: Americas | H93: Brazil | I93: Rio de Janeiro | J93: Non-Profit | K93: Retail | L93: E. Garcia | M93: Printers | N93: PRN-6490 | O93: 804.01 | P93: =IF(Q93<50, "Low", IF(Q93<200, "Medium", "High")) -> High | Q93: 1405.07 | R93: 0.096 | S93: 8 | T93: =(Q119*S93)*(1-R93) -> 4491.2166 | U93: =(O93*S93) -> 6432.08 | V93: =(T93-U93) -> -1940.8634 | W93: =IF(T93=0, 0, V93/T93) -> -0.43214646
A94: ORD-2024-997336 | B94: 45569 | C94: 45598 | D94: =DATEDIF(B94,C94, "MD") -> 29 | E94: =TEXT(Data!B94,"MMM-YYYY") -> Oct-2024 | F94: ="Q"&ROUNDUP(MONTH(B94)/3,0)&"-"&YEAR(B94) -> Q4-2024 | G94: Africa | H94: Nigeria | I94: Abuja | J94: Corporate | K94: Distributor | L94: F. Müller | M94: Accessories | N94: ACC-9038 | O94: 412.09 | P94: =IF(Q94<50, "Low", IF(Q94<200, "Medium", "High")) -> High | Q94: 968.94 | R94: 0.099 | S94: 23 | T94: =(Q120*S94)*(1-R94) -> 1834.1927 | U94: =(O94*S94) -> 9478.07 | V94: =(T94-U94) -> -7643.8773 | W94: =IF(T94=0, 0, V94/T94) -> -4.1674341
A95: ORD-2025-725646 | B95: 45910 | C95: 45930 | D95: =DATEDIF(B95,C95, "MD") -> 20 | E95: =TEXT(Data!B95,"MMM-YYYY") -> Sep-2025 | F95: ="Q"&ROUNDUP(MONTH(B95)/3,0)&"-"&YEAR(B95) -> Q3-2025 | G95: Africa | H95: Kenya | I95: Mombasa | J95: Corporate | K95: Direct | L95: L. Okafor | M95: Phones | N95: PHN-6954 | O95: 1009.48 | P95: =IF(Q95<50, "Low", IF(Q95<200, "Medium", "High")) -> High | Q95: 1088.81 | R95: 0.16 | S95: 6 | T95: =(Q121*S95)*(1-R95) -> 9873.8136 | U95: =(O95*S95) -> 6056.88 | V95: =(T95-U95) -> 3816.9336 | W95: =IF(T95=0, 0, V95/T95) -> 0.38657136
A96: ORD-2023-868734 | B96: 45022 | C96: 45043 | D96: =DATEDIF(B96,C96, "MD") -> 21 | E96: =TEXT(Data!B96,"MMM-YYYY") -> Apr-2023 | F96: ="Q"&ROUNDUP(MONTH(B96)/3,0)&"-"&YEAR(B96) -> Q2-2023 | G96: Europe | H96: United Kingdom | I96: Manchester | J96: Enterprise | K96: Distributor | L96: I. Johnson | M96: Printers | N96: PRN-8970 | O96: 1084.79 | P96: =IF(Q96<50, "Low", IF(Q96<200, "Medium", "High")) -> High | Q96: 2484.99 | R96: 0.034 | S96: 18 | T96: =(Q122*S96)*(1-R96) -> 47694.762 | U96: =(O96*S96) -> 19526.22 | V96: =(T96-U96) -> 28168.542 | W96: =IF(T96=0, 0, V96/T96) -> 0.59060033
A97: ORD-2025-262491 | B97: 45870 | C97: 45885 | D97: =DATEDIF(B97,C97, "MD") -> 15 | E97: =TEXT(Data!B97,"MMM-YYYY") -> Aug-2025 | F97: ="Q"&ROUNDUP(MONTH(B97)/3,0)&"-"&YEAR(B97) -> Q3-2025 | G97: Asia | H97: India | I97: Not Provided | J97: Enterprise | K97: Direct | L97: O. Wang | M97: Monitors | N97: MON-1822 | O97: 24.44 | P97: =IF(Q97<50, "Low", IF(Q97<200, "Medium", "High")) -> Low | Q97: 28.69 | R97: 0.146 | S97: 6 | T97: =(Q123*S97)*(1-R97) -> 8605.3481 | U97: =(O97*S97) -> 146.64 | V97: =(T97-U97) -> 8458.7081 | W97: =IF(T97=0, 0, V97/T97) -> 0.98295943
A98: ORD-2024-638884 | B98: 45440 | C98: 45438 | D98: =DATEDIF(C98,B98, "MD") -> 2 | E98: =TEXT(Data!B98,"MMM-YYYY") -> May-2024 | F98: ="Q"&ROUNDUP(MONTH(B98)/3,0)&"-"&YEAR(B98) -> Q2-2024 | G98: Africa | H98: Nigeria | I98: Abuja | J98: Enterprise | K98: Online | L98: F. Müller | M98: Accessories | N98: ACC-5177 | O98: 1227.08 | P98: =IF(Q98<50, "Low", IF(Q98<200, "Medium", "High")) -> High | Q98: 1896.62 | R98: 0 | S98: 18 | T98: =(Q124*S98)*(1-R98) -> 25810.2 | U98: =(O98*S98) -> 22087.44 | V98: =(T98-U98) -> 3722.76 | W98: =IF(T98=0, 0, V98/T98) -> 0.144236
A99: ORD-2025-541501 | B99: 45860 | C99: 45887 | D99: =DATEDIF(B99,C99, "MD") -> 27 | E99: =TEXT(Data!B99,"MMM-YYYY") -> Jul-2025 | F99: ="Q"&ROUNDUP(MONTH(B99)/3,0)&"-"&YEAR(B99) -> Q3-2025 | G99: Asia | H99: China | I99: Shenzhen | J99: Non-Profit | K99: Marketplace | L99: M. Rossi | M99: Networking | N99: NET-1804 | O99: 547.32 | P99: =IF(Q99<50, "Low", IF(Q99<200, "Medium", "High")) -> High | Q99: 419.17 | R99: 0.092 | S99: 14 | T99: =(Q125*S99)*(1-R99) -> 3615.6742 | U99: =(O99*S99) -> 7662.48 | V99: =(T99-U99) -> -4046.8058 | W99: =IF(T99=0, 0, V99/T99) -> -1.1192396
A100: ORD-2023-422918 | B100: 44985 | C100: 45005 | D100: =DATEDIF(B100,C100, "MD") -> 20 | E100: =TEXT(Data!B100,"MMM-YYYY") -> Feb-2023 | F100: ="Q"&ROUNDUP(MONTH(B100)/3,0)&"-"&YEAR(B100) -> Q1-2023 | G100: Europe | H100: Germany | I100: Berlin | J100: Small Business | K100: Direct | L100: H. Kim | M100: Laptops | N100: LAP-3679 | O100: 1200.78 | P100: =IF(Q100<50, "Low", IF(Q100<200, "Medium", "High")) -> High | Q100: 2001.17 | R100: 0.292 | S100: 18 | T100: =(Q126*S100)*(1-R100) -> 8854.2763 | U100: =(O100*S100) -> 21614.04 | V100: =(T100-U100) -> -12759.764 | W100: =IF(T100=0, 0, V100/T100) -> -1.4410849
A101: ORD-2025-328504 | B101: 45684 | C101: 45703 | D101: =DATEDIF(B101,C101, "MD") -> 19 | E101: =TEXT(Data!B101,"MMM-YYYY") -> Jan-2025 | F101: ="Q"&ROUNDUP(MONTH(B101)/3,0)&"-"&YEAR(B101) -> Q1-2025 | G101: Asia | H101: China | I101: Shenzhen | J101: Non-Profit | K101: Direct | L101: L. Okafor | M101: Phones | N101: PHN-8368 | O101: 1253.22 | P101: =IF(Q101<50, "Low", IF(Q101<200, "Medium", "High")) -> High | Q101: 3104.71 | R101: 0 | S101: 17 | T101: =(Q127*S101)*(1-R101) -> 31422.63 | U101: =(O101*S101) -> 21304.74 | V101: =(T101-U101) -> 10117.89 | W101: =IF(T101=0, 0, V101/T101) -> 0.32199374
A102: ORD-2024-851883 | B102: 45304 | C102: 45313 | D102: =DATEDIF(B102,C102, "MD") -> 9 | E102: =TEXT(Data!B102,"MMM-YYYY") -> Jan-2024 | F102: ="Q"&ROUNDUP(MONTH(B102)/3,0)&"-"&YEAR(B102) -> Q1-2024 | G102: Asia | H102: India | I102: Mumbai | J102: Enterprise | K102: Marketplace | L102: J. Njeri | M102: Components | N102: CMP-8141 | O102: 313.6 | P102: =IF(Q102<50, "Low", IF(Q102<200, "Medium", "High")) -> High | Q102: 334.28 | R102: 0.14 | S102: 22 | T102: =(Q128*S102)*(1-R102) -> 854.9948 | U102: =(O102*S102) -> 6899.2 | V102: =(T102-U102) -> -6044.2052 | W102: =IF(T102=0, 0, V102/T102) -> -7.0692888
A103: ORD-2025-662997 | B103: 45747 | C103: 45751 | D103: =DATEDIF(B103,C103, "MD") -> 4 | E103: =TEXT(Data!B103,"MMM-YYYY") -> Mar-2025 | F103: ="Q"&ROUNDUP(MONTH(B103)/3,0)&"-"&YEAR(B103) -> Q1-2025 | G103: Africa | H103: Kenya | I103: Nakuru | J103: Corporate | K103: Direct | L103: C. Otieno | M103: Laptops | N103: LAP-7136 | O103: 862.08 | P103: =IF(Q103<50, "Low", IF(Q103<200, "Medium", "High")) -> High | Q103: 1952.83 | R103: 0 | S103: 7 | T103: =(Q129*S103)*(1-R103) -> 2527.7 | U103: =(O103*S103) -> 6034.56 | V103: =(T103-U103) -> -3506.86 | W103: =IF(T103=0, 0, V103/T103) -> -1.3873719
A104: ORD-2024-478165 | B104: 45631 | C104: 45654 | D104: =DATEDIF(B104,C104, "MD") -> 23 | E104: =TEXT(Data!B104,"MMM-YYYY") -> Dec-2024 | F104: ="Q"&ROUNDUP(MONTH(B104)/3,0)&"-"&YEAR(B104) -> Q4-2024 | G104: Americas | H104: Canada | I104: Vancouver | J104: Corporate | K104: Direct | L104: F. Müller | M104: Accessories | N104: ACC-2386 | O104: 107.03 | P104: =IF(Q104<50, "Low", IF(Q104<200, "Medium", "High")) -> High | Q104: 242.29 | R104: 0.18 | S104: 30 | T104: =(Q130*S104)*(1-R104) -> 24706.764 | U104: =(O104*S104) -> 3210.9 | V104: =(T104-U104) -> 21495.864 | W104: =IF(T104=0, 0, V104/T104) -> 0.87003964
A105: ORD-2024-771210 | B105: 45549 | C105: 45570 | D105: =DATEDIF(B105,C105, "MD") -> 21 | E105: =TEXT(Data!B105,"MMM-YYYY") -> Sep-2024 | F105: ="Q"&ROUNDUP(MONTH(B105)/3,0)&"-"&YEAR(B105) -> Q3-2024 | G105: Asia | H105: China | I105: Shanghai | J105: Small Business | K105: Online | L105: H. Kim | M105: Laptops | N105: LAP-5150 | O105: 1405.56 | P105: =IF(Q105<50, "Low", IF(Q105<200, "Medium", "High")) -> High | Q105: 2968.87 | R105: 0.169 | S105: 5 | T105: =(Q131*S105)*(1-R105) -> 4270.2181 | U105: =(O105*S105) -> 7027.8 | V105: =(T105-U105) -> -2757.5818 | W105: =IF(T105=0, 0, V105/T105) -> -0.64577072
A106: ORD-2024-155337 | B106: 45433 | C106: 45439 | D106: =DATEDIF(B106,C106, "MD") -> 6 | E106: =TEXT(Data!B106,"MMM-YYYY") -> May-2024 | F106: ="Q"&ROUNDUP(MONTH(B106)/3,0)&"-"&YEAR(B106) -> Q2-2024 | G106: Africa | H106: South Africa | I106: Johannesburg | J106: Non-Profit | K106: Online | L106: M. Rossi | M106: Components | N106: CMP-8101 | O106: 1157.51 | P106: =IF(Q106<50, "Low", IF(Q106<200, "Medium", "High")) -> High | Q106: 1394.3 | R106: 0.278 | S106: 12 | T106: =(Q132*S106)*(1-R106) -> 4055.5318 | U106: =(O106*S106) -> 13890.12 | V106: =(T106-U106) -> -9834.5882 | W106: =IF(T106=0, 0, V106/T106) -> -2.4249812
A107: ORD-2023-251563 | B107: 45057 | C107: 45084 | D107: =DATEDIF(B107,C107, "MD") -> 27 | E107: =TEXT(Data!B107,"MMM-YYYY") -> May-2023 | F107: ="Q"&ROUNDUP(MONTH(B107)/3,0)&"-"&YEAR(B107) -> Q2-2023 | G107: Africa | H107: Kenya | I107: Mombasa | J107: Corporate | K107: Online | L107: J. Njeri | M107: Phones | N107: PHN-8970 | O107: 12.85 | P107: =IF(Q107<50, "Low", IF(Q107<200, "Medium", "High")) -> Low | Q107: 15.41 | R107: 0.137 | S107: 39 | T107: =(Q133*S107)*(1-R107) -> 22483.549 | U107: =(O107*S107) -> 501.15 | V107: =(T107-U107) -> 21982.399 | W107: =IF(T107=0, 0, V107/T107) -> 0.97771037
A108: ORD-2024-286833 | B108: 45518 | C108: 45539 | D108: =DATEDIF(B108,C108, "MD") -> 21 | E108: =TEXT(Data!B108,"MMM-YYYY") -> Aug-2024 | F108: ="Q"&ROUNDUP(MONTH(B108)/3,0)&"-"&YEAR(B108) -> Q3-2024 | G108: Europe | H108: United Kingdom | I108: Manchester | J108: Non-Profit | K108: Online | L108: J. Njeri | M108: Phones | N108: PHN-2341 | O108: 1138.8 | P108: =IF(Q108<50, "Low", IF(Q108<200, "Medium", "High")) -> High | Q108: 2250.81 | R108: 0.123 | S108: 12 | T108: =(Q134*S108)*(1-R108) -> 5654.2295 | U108: =(O108*S108) -> 13665.6 | V108: =(T108-U108) -> -8011.3705 | W108: =IF(T108=0, 0, V108/T108) -> -1.416881
A109: ORD-2024-792558 | B109: 45581 | C109: 45604 | D109: =DATEDIF(B109,C109, "MD") -> 23 | E109: =TEXT(Data!B109,"MMM-YYYY") -> Oct-2024 | F109: ="Q"&ROUNDUP(MONTH(B109)/3,0)&"-"&YEAR(B109) -> Q4-2024 | G109: Asia | H109: Japan | I109: Osaka | J109: Small Business | K109: Retail | L109: J. Njeri | M109: Networking | N109: NET-6387 | O109: 82.14 | P109: =IF(Q109<50, "Low", IF(Q109<200, "Medium", "High")) -> Medium | Q109: 166.04 | R109: 0 | S109: 10 | T109: =(Q135*S109)*(1-R109) -> 5727.1 | U109: =(O109*S109) -> 821.4 | V109: =(T109-U109) -> 4905.7 | W109: =IF(T109=0, 0, V109/T109) -> 0.85657663
A110: ORD-2024-166150 | B110: 45445 | C110: 45451 | D110: =DATEDIF(B110,C110, "MD") -> 6 | E110: =TEXT(Data!B110,"MMM-YYYY") -> Jun-2024 | F110: ="Q"&ROUNDUP(MONTH(B110)/3,0)&"-"&YEAR(B110) -> Q2-2024 | G110: Africa | H110: Kenya | I110: Kisumu | J110: Consumer | K110: Marketplace | L110: A. Patel | M110: Accessories | N110: ACC-9820 | O110: 292.94 | P110: =IF(Q110<50, "Low", IF(Q110<200, "Medium", "High")) -> High | Q110: 356.55 | R110: 0.229 | S110: 2 | T110: =(Q136*S110)*(1-R110) -> 3583.4075 | U110: =(O110*S110) -> 585.88 | V110: =(T110-U110) -> 2997.5275 | W110: =IF(T110=0, 0, V110/T110) -> 0.83650199
... A145: ORD-2023-309373 | B145: 45112 | C145: 45121 | D145: =DATEDIF(B145,C145, "MD") -> 9 | E145: =TEXT(Data!B145,"MMM-YYYY") -> Jul-2023 | F145: ="Q"&ROUNDUP(MONTH(B145)/3,0)&"-"&YEAR(B145) -> Q3-2023 | G145: Americas | H145: Brazil | I145: Brasília | J145: Enterprise | K145: Direct | L145: B. Chen | M145: Networking | N145: NET-2394 | O145: 578.85 | P145: =IF(Q145<50, "Low", IF(Q145<200, "Medium", "High")) -> High | Q145: 998.76 | R145: 0.082 | S145: 28 | T145: =(Q171*S145)*(1-R145) -> 31331.12 | U145: =(O145*S145) -> 16207.8 | V145: =(T145-U145) -> 15123.32 | W145: =IF(T145=0, 0, V145/T145) -> 0.48269324
A146: ORD-2023-825495 | B146: 45260 | C146: 45259 | D146: =DATEDIF(C146,B146, "MD") -> 1 | E146: =TEXT(Data!B146,"MMM-YYYY") -> Nov-2023 | F146: ="Q"&ROUNDUP(MONTH(B146)/3,0)&"-"&YEAR(B146) -> Q4-2023 | G146: Africa | H146: South Africa | I146: Durban | J146: Small Business | K146: Marketplace | L146: E. Garcia | M146: Laptops | N146: LAP-1525 | O146: 275.56 | P146: =IF(Q146<50, "Low", IF(Q146<200, "Medium", "High")) -> High | Q146: 630.72 | R146: 0.107 | S146: 23 | T146: =(Q172*S146)*(1-R146) -> 42353.883 | U146: =(O146*S146) -> 6337.88 | V146: =(T146-U146) -> 36016.003 | W146: =IF(T146=0, 0, V146/T146) -> 0.85035894
A147: ORD-2025-244832 | B147: 45911 | C147: 45928 | D147: =DATEDIF(B147,C147, "MD") -> 17 | E147: =TEXT(Data!B147,"MMM-YYYY") -> Sep-2025 | F147: ="Q"&ROUNDUP(MONTH(B147)/3,0)&"-"&YEAR(B147) -> Q3-2025 | G147: Africa | H147: Kenya | I147: Nairobi | J147: Non-Profit | K147: Distributor | L147: J. Njeri | M147: Laptops | N147: LAP-3278 | O147: 891.46 | P147: =IF(Q147<50, "Low", IF(Q147<200, "Medium", "High")) -> High | Q147: 728.61 | R147: 0.185 | S147: 6 | T147: =(Q173*S147)*(1-R147) -> 49.7802 | U147: =(O147*S147) -> 5348.76 | V147: =(T147-U147) -> -5298.9798 | W147: =IF(T147=0, 0, V147/T147) -> -106.44754
A148: ORD-2024-211453 | B148: 45386 | C148: 45406 | D148: =DATEDIF(B148,C148, "MD") -> 20 | E148: =TEXT(Data!B148,"MMM-YYYY") -> Apr-2024 | F148: ="Q"&ROUNDUP(MONTH(B148)/3,0)&"-"&YEAR(B148) -> Q2-2024 | G148: Europe | H148: Germany | I148: Frankfurt | J148: Non-Profit | K148: Direct | L148: O. Wang | M148: Accessories | N148: ACC-6543 | O148: 683.42 | P148: =IF(Q148<50, "Low", IF(Q148<200, "Medium", "High")) -> High | Q148: 951.51 | R148: 0 | S148: 14 | T148: =(Q174*S148)*(1-R148) -> 31944.08 | U148: =(O148*S148) -> 9567.88 | V148: =(T148-U148) -> 22376.2 | W148: =IF(T148=0, 0, V148/T148) -> 0.70048034
A149: ORD-2023-192324 | B149: 45183 | C149: 45185 | D149: =DATEDIF(B149,C149, "MD") -> 2 | E149: =TEXT(Data!B149,"MMM-YYYY") -> Sep-2023 | F149: ="Q"&ROUNDUP(MONTH(B149)/3,0)&"-"&YEAR(B149) -> Q3-2023 | G149: Europe | H149: France | I149: Lyon | J149: Non-Profit | K149: Direct | L149: B. Chen | M149: Printers | N149: PRN-4432 | O149: 376.83 | P149: =IF(Q149<50, "Low", IF(Q149<200, "Medium", "High")) -> High | Q149: 732.88 | R149: 0.188 | S149: 25 | T149: =(Q175*S149)*(1-R149) -> 5066.271 | U149: =(O149*S149) -> 9420.75 | V149: =(T149-U149) -> -4354.479 | W149: =IF(T149=0, 0, V149/T149) -> -0.85950377
A150: ORD-2024-438404 | B150: 45558 | C150: 45583 | D150: =DATEDIF(B150,C150, "MD") -> 25 | E150: =TEXT(Data!B150,"MMM-YYYY") -> Sep-2024 | F150: ="Q"&ROUNDUP(MONTH(B150)/3,0)&"-"&YEAR(B150) -> Q3-2024 | G150: Americas | H150: Canada | I150: Vancouver | J150: Small Business | K150: Online | L150: N. Brown | M150: Phones | N150: PHN-4568 | O150: 1297 | P150: =IF(Q150<50, "Low", IF(Q150<200, "Medium", "High")) -> High | Q150: 2411.52 | R150: 0.021 | S150: 18 | T150: =(Q176*S150)*(1-R150) -> 57712.05 | U150: =(O150*S150) -> 23346 | V150: =(T150-U150) -> 34366.05 | W150: =IF(T150=0, 0, V150/T150) -> 0.59547443
A151: ORD-2025-246470 | B151: 45763 | C151: 45793 | D151: =DATEDIF(B151,C151, "MD") -> 0 | E151: =TEXT(Data!B151,"MMM-YYYY") -> Apr-2025 | F151: ="Q"&ROUNDUP(MONTH(B151)/3,0)&"-"&YEAR(B151) -> Q2-2025 | G151: Americas | H151: Canada | I151: Montreal | J151: Enterprise | K151: Distributor | L151: K. Singh | M151: Printers | N151: PRN-6178 | O151: 763.32 | P151: =IF(Q151<50, "Low", IF(Q151<200, "Medium", "High")) -> High | Q151: 568.29 | R151: 0.131 | S151: 16 | T151: =(Q177*S151)*(1-R151) -> 26608.919 | U151: =(O151*S151) -> 12213.12 | V151: =(T151-U151) -> 14395.799 | W151: =IF(T151=0, 0, V151/T151) -> 0.54101405
A152: ORD-2023-497686 | B152: 45110 | C152: 45130 | D152: =DATEDIF(B152,C152, "MD") -> 20 | E152: =TEXT(Data!B152,"MMM-YYYY") -> Jul-2023 | F152: ="Q"&ROUNDUP(MONTH(B152)/3,0)&"-"&YEAR(B152) -> Q3-2023 | G152: Africa | H152: South Africa | I152: Johannesburg | J152: Small Business | K152: Distributor | L152: F. Müller | M152: Laptops | N152: LAP-6342 | O152: 1001.96 | P152: =IF(Q152<50, "Low", IF(Q152<200, "Medium", "High")) -> High | Q152: 1254.95 | R152: 0.045 | S152: 18 | T152: =(Q178*S152)*(1-R152) -> 517.2471 | U152: =(O152*S152) -> 18035.28 | V152: =(T152-U152) -> -17518.033 | W152: =IF(T152=0, 0, V152/T152) -> -33.867822
A153: ORD-2023-596758 | B153: 45267 | C153: 45265 | D153: =DATEDIF(C153,B153, "MD") -> 2 | E153: =TEXT(Data!B153,"MMM-YYYY") -> Dec-2023 | F153: ="Q"&ROUNDUP(MONTH(B153)/3,0)&"-"&YEAR(B153) -> Q4-2023 | G153: Asia | H153: Japan | I153: Tokyo | J153: Non-Profit | K153: Marketplace | L153: H. Kim | M153: Printers | N153: PRN-8175 | O153: 1097.59 | P153: =IF(Q153<50, "Low", IF(Q153<200, "Medium", "High")) -> High | Q153: 845.55 | R153: 0.184 | S153: 6 | T153: =(Q179*S153)*(1-R153) -> 2454.4138 | U153: =(O153*S153) -> 6585.54 | V153: =(T153-U153) -> -4131.1262 | W153: =IF(T153=0, 0, V153/T153) -> -1.6831417
A154: ORD-2024-201376 | B154: 45340 | C154: 45355 | D154: =DATEDIF(B154,C154, "MD") -> 15 | E154: =TEXT(Data!B154,"MMM-YYYY") -> Feb-2024 | F154: ="Q"&ROUNDUP(MONTH(B154)/3,0)&"-"&YEAR(B154) -> Q1-2024 | G154: Africa | H154: Kenya | I154: Kisumu | J154: Education | K154: Direct | L154: K. Singh | M154: Printers | N154: PRN-7089 | O154: 928.68 | P154: =IF(Q154<50, "Low", IF(Q154<200, "Medium", "High")) -> High | Q154: 2145.17 | R154: 0.136 | S154: 16 | T154: =(Q180*S154)*(1-R154) -> 5684.1523 | U154: =(O154*S154) -> 14858.88 | V154: =(T154-U154) -> -9174.7277 | W154: =IF(T154=0, 0, V154/T154) -> -1.614089
A155: ORD-2023-842488 | B155: 45230 | C155: 45232 | D155: =DATEDIF(B155,C155, "MD") -> 2 | E155: =TEXT(Data!B155,"MMM-YYYY") -> Oct-2023 | F155: ="Q"&ROUNDUP(MONTH(B155)/3,0)&"-"&YEAR(B155) -> Q4-2023 | G155: Africa | H155: Kenya | I155: Kisumu | J155: Education | K155: Retail | L155: O. Wang | M155: Accessories | N155: ACC-4124 | O155: 867.89 | P155: =IF(Q155<50, "Low", IF(Q155<200, "Medium", "High")) -> High | Q155: 1349.94 | R155: 0.184 | S155: 10 | T155: =(Q181*S155)*(1-R155) -> 48.3072 | U155: =(O155*S155) -> 8678.9 | V155: =(T155-U155) -> -8630.5928 | W155: =IF(T155=0, 0, V155/T155) -> -178.66059
A156: ORD-2024-136321 | B156: 45511 | C156: 45521 | D156: =DATEDIF(B156,C156, "MD") -> 10 | E156: =TEXT(Data!B156,"MMM-YYYY") -> Aug-2024 | F156: ="Q"&ROUNDUP(MONTH(B156)/3,0)&"-"&YEAR(B156) -> Q3-2024 | G156: Asia | H156: Japan | I156: Osaka | J156: Consumer | K156: Online | L156: K. Singh | M156: Networking | N156: NET-7924 | O156: 436.58 | P156: =IF(Q156<50, "Low", IF(Q156<200, "Medium", "High")) -> High | Q156: 527.48 | R156: 0.111 | S156: 19 | T156: =(Q182*S156)*(1-R156) -> 37272.187 | U156: =(O156*S156) -> 8295.02 | V156: =(T156-U156) -> 28977.167 | W156: =IF(T156=0, 0, V156/T156) -> 0.77744746
A157: ORD-2024-764468 | B157: 45323 | C157: 45343 | D157: =DATEDIF(B157,C157, "MD") -> 20 | E157: =TEXT(Data!B157,"MMM-YYYY") -> Feb-2024 | F157: ="Q"&ROUNDUP(MONTH(B157)/3,0)&"-"&YEAR(B157) -> Q1-2024 | G157: Europe | H157: France | I157: Paris | J157: Small Business | K157: Marketplace | L157: A. Patel | M157: Networking | N157: NET-8761 | O157: 656.2 | P157: =IF(Q157<50, "Low", IF(Q157<200, "Medium", "High")) -> High | Q157: 1467.17 | R157: 0.018 | S157: 5 | T157: =(Q183*S157)*(1-R157) -> 9391.848 | U157: =(O157*S157) -> 3281 | V157: =(T157-U157) -> 6110.848 | W157: =IF(T157=0, 0, V157/T157) -> 0.65065448
A158: ORD-2024-553449 | B158: 45531 | C158: 45553 | D158: =DATEDIF(B158,C158, "MD") -> 22 | E158: =TEXT(Data!B158,"MMM-YYYY") -> Aug-2024 | F158: ="Q"&ROUNDUP(MONTH(B158)/3,0)&"-"&YEAR(B158) -> Q3-2024 | G158: Asia | H158: India | I158: Delhi | J158: Consumer | K158: Direct | L158: B. Chen | M158: Components | N158: CMP-3875 | O158: 896.75 | P158: =IF(Q158<50, "Low", IF(Q158<200, "Medium", "High")) -> High | Q158: 1651.14 | R158: 0.025 | S158: 15 | T158: =(Q184*S158)*(1-R158) -> 20216.284 | U158: =(O158*S158) -> 13451.25 | V158: =(T158-U158) -> 6765.0337 | W158: =IF(T158=0, 0, V158/T158) -> 0.3346329
A159: ORD-2025-766923 | B159: 45703 | C159: 45703 | D159: =DATEDIF(B159,C159, "MD") -> 0 | E159: =TEXT(Data!B159,"MMM-YYYY") -> Feb-2025 | F159: ="Q"&ROUNDUP(MONTH(B159)/3,0)&"-"&YEAR(B159) -> Q1-2025 | G159: Europe | H159: Germany | I159: Frankfurt | J159: Small Business | K159: Marketplace | L159: L. Okafor | M159: Accessories | N159: ACC-3989 | O159: 815.83 | P159: =IF(Q159<50, "Low", IF(Q159<200, "Medium", "High")) -> High | Q159: 1982.18 | R159: 0.127 | S159: 6 | T159: =(Q185*S159)*(1-R159) -> 7100.6852 | U159: =(O159*S159) -> 4894.98 | V159: =(T159-U159) -> 2205.7052 | W159: =IF(T159=0, 0, V159/T159) -> 0.31063272
A160: ORD-2025-418232 | B160: 45870 | C160: 45890 | D160: =DATEDIF(B160,C160, "MD") -> 20 | E160: =TEXT(Data!B160,"MMM-YYYY") -> Aug-2025 | F160: ="Q"&ROUNDUP(MONTH(B160)/3,0)&"-"&YEAR(B160) -> Q3-2025 | G160: Asia | H160: China | I160: Shanghai | J160: Corporate | K160: Direct | L160: I. Johnson | M160: Phones | N160: PHN-9234 | O160: 1220.41 | P160: =IF(Q160<50, "Low", IF(Q160<200, "Medium", "High")) -> High | Q160: 2552.22 | R160: 0.181 | S160: 14 | T160: =(Q186*S160)*(1-R160) -> 10180.661 | U160: =(O160*S160) -> 17085.74 | V160: =(T160-U160) -> -6905.0786 | W160: =IF(T160=0, 0, V160/T160) -> -0.67825442
...

Sheet Pivot ABC Data
A3: Row Labels | B3: Sum of Gross Revenue | D3: Product Category | E3: Gross Revenue | F3: Revenue Contribution % | G3: Frequency | H3: Cummulative % | I3: Class
A4: Printers | B4: 1926575.4 | D4: Printers | E4: 1926575.4 | F4: =(GETPIVOTDATA("Gross Revenue",$A$3,"ProductCategory","Printers")/GETPIVOTDATA("Gross Revenue",$A$3)) -> 0.183983 | G4: =SUM(GETPIVOTDATA("Gross Revenue",$A$3:$A$3,"ProductCategory","Printers")) -> 1926575.4 | H4: =(G4/GETPIVOTDATA("Gross Revenue",$A$3)) -> 0.183983 | I4: =IF(H4<=0.8, "A", IF(H4<=0.95, "B", "C")) -> A
A5: Phones | B5: 1573214 | D5: Phones | E5: 1573214 | F5: =(GETPIVOTDATA("Gross Revenue",$A$3,"ProductCategory","Phones")/GETPIVOTDATA("Gross Revenue",$A$3)) -> 0.1502379 | G5: =SUM(G4+GETPIVOTDATA("Gross Revenue",$A$3,"ProductCategory","Phones")) -> 3499789.5 | H5: =(G5/GETPIVOTDATA("Gross Revenue",$A$3)) -> 0.3342209 | I5: =IF(H5<=0.8, "A", IF(H5<=0.95, "B", "C")) -> A
A6: Monitors | B6: 1493059.8 | D6: Monitors | E6: 1493059.8 | F6: =(GETPIVOTDATA("Gross Revenue",$A$3,"ProductCategory","Monitors")/GETPIVOTDATA("Gross Revenue",$A$3)) -> 0.14258337 | G6: =SUM(G5+GETPIVOTDATA("Gross Revenue",$A$3,"ProductCategory","Monitors")) -> 4992849.3 | H6: =(G6/GETPIVOTDATA("Gross Revenue",$A$3)) -> 0.47680428 | I6: =IF(H6<=0.8, "A", IF(H6<=0.95, "B", "C")) -> A
A7: Networking | B7: 1471202.5 | D7: Networking | E7: 1471202.5 | F7: =(GETPIVOTDATA("Gross Revenue",$A$3,"ProductCategory","Networking")/GETPIVOTDATA("Gross Revenue",$A$3)) -> 0.14049606 | G7: =SUM(G6+GETPIVOTDATA("Gross Revenue",$A$3,"ProductCategory","Networking")) -> 6464051.7 | H7: =(G7/GETPIVOTDATA("Gross Revenue",$A$3)) -> 0.61730033 | I7: =IF(H7<=0.8, "A", IF(H7<=0.95, "B", "C")) -> A
A8: Laptops | B8: 1405895.7 | D8: Laptops | E8: 1405895.7 | F8: =(GETPIVOTDATA("Gross Revenue",$A$3,"ProductCategory","Laptops")/GETPIVOTDATA("Gross Revenue",$A$3)) -> 0.13425943 | G8: =SUM(G7+GETPIVOTDATA("Gross Revenue",$A$3,"ProductCategory","Laptops")) -> 7869947.5 | H8: =(G8/GETPIVOTDATA("Gross Revenue",$A$3)) -> 0.75155976 | I8: =IF(H8<=0.8, "A", IF(H8<=0.95, "B", "C")) -> A
A9: Accessories | B9: 1352771.8 | D9: Accessories | E9: 1352771.8 | F9: =(GETPIVOTDATA("Gross Revenue",$A$3,"ProductCategory","Accessories")/GETPIVOTDATA("Gross Revenue",$A$3)) -> 0.12918623 | G9: =SUM(G8+GETPIVOTDATA("Gross Revenue",$A$3,"ProductCategory","Accessories")) -> 9222719.3 | H9: =(G9/GETPIVOTDATA("Gross Revenue",$A$3)) -> 0.88074599 | I9: =IF(H9<=0.8, "A", IF(H9<=0.95, "B", "C")) -> B
A10: Components | B10: 1248766.7 | D10: Components | E10: 1248766.7 | F10: =(GETPIVOTDATA("Gross Revenue",$A$3,"ProductCategory","Components")/GETPIVOTDATA("Gross Revenue",$A$3)) -> 0.11925401 | G10: =SUM(G9+GETPIVOTDATA("Gross Revenue",$A$3,"ProductCategory","Components")) -> 10471486 | H10: =(G10/GETPIVOTDATA("Gross Revenue",$A$3)) -> 1 | I10: =IF(H10<=0.8, "A", IF(H10<=0.95, "B", "C")) -> C
A11: (blank) | E11: =SUM(E4:E10) -> 10471486 | F11: =SUM(F4:F10) -> 1 | G11: =SUM(G4:G10) -> 44447419
A12: (blank)
A13: Grand Total | B13: 10471486
D16: Row Labels | E16: Sum of Gross Revenue
D17: Accessories | E17: 1352771.8
D18: B | E18: 1352771.8
D19: Components | E19: 1248766.7
D20: C | E20: 1248766.7
D21: Laptops | E21: 1405895.7
D22: A | E22: 1405895.7
D23: Monitors | E23: 1493059.8
D24: A | E24: 1493059.8
D25: Networking | E25: 1471202.5
D26: A | E26: 1471202.5
D27: Phones | E27: 1573214
D28: A | E28: 1573214
... D31: Grand Total | E31: 10471486

Sheet Salesperson Productivity
A1: OrderID | B1: OrderDate | C1: RequiredDate | D1: Leadtime days | E1: Month | F1: CustomerSegment | G1: Channel | H1: Salesperson | I1: ProductCategory | J1: UnitCost | K1: Price Band | L1: UnitPrice | M1: DiscountPct | N1: Quantity | O1: Gross Revenue | P1: Cost of Goods | Q1: Gross Profit | R1: Margin%
A2: ORD-2024-275203 | B2: 45362 | C2: 45388 | D2: =DATEDIF(B2,C2, "MD") -> 26 | E2: =TEXT(Data!B2,"MMM-YYYY") -> Oct-2024 | F2: Corporate | G2: Retail | H2: C. Otieno | I2: Components | J2: 279.24 | K2: =IF(L2<50, "Low", IF(L2<200, "Medium", "High")) -> High | L2: 608.9 | M2: 0.112 | N2: 9 | O2: =(L28*N2)*(1-M2) -> 1403.9546 | P2: =(J2*N2) -> 2513.16 | Q2: =(O2-P2) -> -1109.2054 | R2: =(Q2/O2) -> -0.79005783
A3: ORD-2024-358795 | B3: 45588 | C3: 45587 | D3: =DATEDIF(C3, B3, "MD") -> 1 | E3: =TEXT(Data!B3,"MMM-YYYY") -> Feb-2023 | F3: Education | G3: Online | H3: J. Njeri | I3: Printers | J3: 1084.39 | K3: =IF(L3<50, "Low", IF(L3<200, "Medium", "High")) -> High | L3: 759.33 | M3: 0.237 | N3: 31 | O3: =(L29*N3)*(1-M3) -> 17934.414 | P3: =(J3*N3) -> 33616.09 | Q3: =(O3-P3) -> -15681.676 | R3: =(Q3/O3) -> -0.87439019
A4: ORD-2023-373538 | B4: 44985 | C4: 45010 | D4: =DATEDIF(B4,C4, "MD") -> 25 | E4: =TEXT(Data!B4,"MMM-YYYY") -> Mar-2025 | F4: Corporate | G4: Retail | H4: I. Johnson | I4: Networking | J4: 1460.76 | K4: =IF(L4<50, "Low", IF(L4<200, "Medium", "High")) -> Low | L4: -30.66 | M4: 0.131 | N4: 12 | O4: =(L30*N4)*(1-M4) -> 4534.0944 | P4: =(J4*N4) -> 17529.12 | Q4: =(O4-P4) -> -12995.026 | R4: =(Q4/O4) -> -2.8660686
A5: ORD-2025-168148 | B5: 45745 | C5: 45749 | D5: =DATEDIF(B5,C5, "MD") -> 4 | E5: =TEXT(Data!B5,"MMM-YYYY") -> Dec-2023 | F5: Non-Profit | G5: Marketplace | H5: G. Dubois | I5: Phones | J5: 259.93 | K5: =IF(L5<50, "Low", IF(L5<200, "Medium", "High")) -> High | L5: 255.94 | M5: 0.072 | N5: 22 | O5: =(L31*N5)*(1-M5) -> 34016.731 | P5: =(J5*N5) -> 5718.46 | Q5: =(O5-P5) -> 28298.271 | R5: =(Q5/O5) -> 0.83189272
A6: ORD-2023-824839 | B6: 45266 | C6: 45291 | D6: =DATEDIF(B6,C6, "MD") -> 25 | E6: =TEXT(Data!B6,"MMM-YYYY") -> Jan-2023 | F6: Consumer | G6: Retail | H6: L. Okafor | I6: Printers | J6: 663.03 | K6: =IF(L6<50, "Low", IF(L6<200, "Medium", "High")) -> High | L6: 813.51 | M6: 0.102 | N6: 15 | O6: =(L32*N6)*(1-M6) -> 8510.0766 | P6: =(J6*N6) -> 9945.45 | Q6: =(O6-P6) -> -1435.3734 | R6: =(Q6/O6) -> -0.16866751
A7: ORD-2023-723587 | B7: 44928 | C7: 44931 | D7: =DATEDIF(B7,C7, "MD") -> 3 | E7: =TEXT(Data!B7,"MMM-YYYY") -> Dec-2024 | F7: Corporate | G7: Distributor | H7: B. Chen | I7: Laptops | J7: 315.87 | K7: =IF(L7<50, "Low", IF(L7<200, "Medium", "High")) -> High | L7: 591.68 | M7: 0 | N7: 7 | O7: =(L33*N7)*(1-M7) -> 12558.49 | P7: =(J7*N7) -> 2211.09 | Q7: =(O7-P7) -> 10347.4 | R7: =(Q7/O7) -> 0.82393664
A8: ORD-2024-336584 | B8: 45653 | C8: 45671 | D8: =DATEDIF(B8,C8, "MD") -> 18 | E8: =TEXT(Data!B8,"MMM-YYYY") -> Jan-2023 | F8: Small Business | G8: Marketplace | H8: E. Garcia | I8: Monitors | J8: 586.07 | K8: =IF(L8<50, "Low", IF(L8<200, "Medium", "High")) -> High | L8: 845.97 | M8: 0.147 | N8: 4 | O8: =(L34*N8)*(1-M8) -> 8983.8642 | P8: =(J8*N8) -> 2344.28 | Q8: =(O8-P8) -> 6639.5842 | R8: =(Q8/O8) -> 0.73905661
A9: ORD-2023-112666 | B9: 44941 | C9: 44939 | D9: =DATEDIF(C9,B9, "MD") -> 2 | E9: =TEXT(Data!B9,"MMM-YYYY") -> May-2024 | F9: Education | G9: Online | H9: O. Wang | I9: Printers | J9: 28.38 | K9: =IF(L9<50, "Low", IF(L9<200, "Medium", "High")) -> Low | L9: 47.22 | M9: 0.194 | N9: 18 | O9: =(L35*N9)*(1-M9) -> 19177.4 | P9: =(J9*N9) -> 510.84 | Q9: =(O9-P9) -> 18666.56 | R9: =(Q9/O9) -> 0.9733624
A10: ORD-2024-589570 | B10: 45416 | C10: 45441 | D10: =DATEDIF(B10,C10, "MD") -> 25 | E10: =TEXT(Data!B10,"MMM-YYYY") -> May-2025 | F10: Non-Profit | G10: Marketplace | H10: O. Wang | I10: Monitors | J10: 1295.34 | K10: =IF(L10<50, "Low", IF(L10<200, "Medium", "High")) -> High | L10: 2530.81 | M10: 0.031 | N10: 6 | O10: =(L36*N10)*(1-M10) -> 17656.362 | P10: =(J10*N10) -> 7772.04 | Q10: =(O10-P10) -> 9884.3222 | R10: =(Q10/O10) -> 0.55981646
A11: ORD-2025-997421 | B11: 45798 | C11: 45817 | D11: =DATEDIF(B11,C11, "MD") -> 19 | E11: =TEXT(Data!B11,"MMM-YYYY") -> Jan-2024 | F11: Non-Profit | G11: Online | H11: A. Patel | I11: Components | J11: 1331.38 | K11: =IF(L11<50, "Low", IF(L11<200, "Medium", "High")) -> High | L11: 2309.56 | M11: 0.149 | N11: 31 | O11: =(L37*N11)*(1-M11) -> 5259.58 | P11: =(J11*N11) -> 41272.78 | Q11: =(O11-P11) -> -36013.2 | R11: =(Q11/O11) -> -6.8471627
A12: ORD-2024-210687 | B12: 45319 | C12: 45331 | D12: =DATEDIF(B12,C12, "MD") -> 12 | E12: =TEXT(Data!B12,"MMM-YYYY") -> Jan-2025 | F12: Corporate | G12: Online | H12: G. Dubois | I12: Accessories | J12: 644.17 | K12: =IF(L12<50, "Low", IF(L12<200, "Medium", "High")) -> High | L12: 700.12 | M12: 0.006 | N12: 23 | O12: =(L38*N12)*(1-M12) -> 21204.734 | P12: =(J12*N12) -> 14815.91 | Q12: =(O12-P12) -> 6388.8236 | R12: =(Q12/O12) -> 0.30129233
A13: ORD-2025-515515 | B13: 45660 | C13: 45680 | D13: =DATEDIF(B13,C13, "MD") -> 20 | E13: =TEXT(Data!B13,"MMM-YYYY") -> Mar-2025 | F13: Corporate | G13: Distributor | H13: F. Müller | I13: Phones | J13: 908.6 | K13: =IF(L13<50, "Low", IF(L13<200, "Medium", "High")) -> High | L13: 691.37 | M13: 0.25 | N13: 20 | O13: =(L39*N13)*(1-M13) -> 26031.15 | P13: =(J13*N13) -> 18172 | Q13: =(O13-P13) -> 7859.15 | R13: =(Q13/O13) -> 0.30191328
A14: ORD-2025-487261 | B14: 45722 | C14: 45747 | D14: =DATEDIF(B14,C14, "MD") -> 25 | E14: =TEXT(Data!B14,"MMM-YYYY") -> Jan-2024 | F14: Non-Profit | G14: Online | H14: J. Njeri | I14: Components | J14: 331.57 | K14: =IF(L14<50, "Low", IF(L14<200, "Medium", "High")) -> High | L14: 548.4 | M14: 0.094 | N14: 10 | O14: =(L40*N14)*(1-M14) -> 12644.498 | P14: =(J14*N14) -> 3315.7 | Q14: =(O14-P14) -> 9328.7984 | R14: =(Q14/O14) -> 0.73777528
A15: ORD-2024-890180 | B15: 45311 | C15: 45335 | D15: =DATEDIF(B15,C15, "MD") -> 24 | E15: =TEXT(Data!B15,"MMM-YYYY") -> Sep-2025 | F15: Corporate | G15: Retail | H15: H. Kim | I15: Printers | J15: 643.53 | K15: =IF(L15<50, "Low", IF(L15<200, "Medium", "High")) -> High | L15: 1439.01 | M15: 0 | N15: 15 | O15: =(L41*N15)*(1-M15) -> 6816.3 | P15: =(J15*N15) -> 9652.95 | Q15: =(O15-P15) -> -2836.65 | R15: =(Q15/O15) -> -0.41615686
A16: ORD-2025-840976 | B16: 45901 | C16: 45930 | D16: =DATEDIF(B16,C16, "MD") -> 29 | E16: =TEXT(Data!B16,"MMM-YYYY") -> Apr-2023 | F16: Education | G16: Retail | H16: K. Singh | I16: Accessories | J16: 780.59 | K16: =IF(L16<50, "Low", IF(L16<200, "Medium", "High")) -> High | L16: 631.57 | M16: 0 | N16: 12 | O16: =(L42*N16)*(1-M16) -> 18971.64 | P16: =(J16*N16) -> 9367.08 | Q16: =(O16-P16) -> 9604.56 | R16: =(Q16/O16) -> 0.50625882
A17: ORD-2023-937291 | B17: 45039 | C17: 45038 | D17: =DATEDIF(C17, B17, "MD") -> 1 | E17: =TEXT(Data!B17,"MMM-YYYY") -> Dec-2024 | F17: Small Business | G17: Direct | H17: E. Garcia | I17: Laptops | J17: 756.51 | K17: =IF(L17<50, "Low", IF(L17<200, "Medium", "High")) -> High | L17: 850.8 | M17: 0.074 | N17: 9 | O17: =(L43*N17)*(1-M17) -> 14666.09 | P17: =(J17*N17) -> 6808.59 | Q17: =(O17-P17) -> 7857.4999 | R17: =(Q17/O17) -> 0.5357597
A18: ORD-2024-206081 | B18: 45636 | C18: 45665 | D18: =DATEDIF(B18,C18, "MD") -> 29 | E18: =TEXT(Data!B18,"MMM-YYYY") -> Sep-2025 | F18: Small Business | G18: Retail | H18: K. Singh | I18: Printers | J18: 891.08 | K18: =IF(L18<50, "Low", IF(L18<200, "Medium", "High")) -> High | L18: 1040.1 | M18: 0.109 | N18: 28 | O18: =(L44*N18)*(1-M18) -> 79945.866 | P18: =(J18*N18) -> 24950.24 | Q18: =(O18-P18) -> 54995.626 | R18: =(Q18/O18) -> 0.68791082
A19: ORD-2025-233883 | B19: 45908 | C19: 45916 | D19: =DATEDIF(B19,C19, "MD") -> 8 | E19: =TEXT(Data!B19,"MMM-YYYY") -> Jul-2025 | F19: Corporate | G19: Distributor | H19: C. Otieno | I19: Phones | J19: 1225.57 | K19: =IF(L19<50, "Low", IF(L19<200, "Medium", "High")) -> High | L19: 2705.57 | M19: 0.183 | N19: 16 | O19: =(L45*N19)*(1-M19) -> 14842.341 | P19: =(J19*N19) -> 19609.12 | Q19: =(O19-P19) -> -4766.779 | R19: =(Q19/O19) -> -0.32116086
A20: ORD-2025-843974 | B20: 45858 | C20: 45874 | D20: =DATEDIF(B20,C20, "MD") -> 16 | E20: =TEXT(Data!B20,"MMM-YYYY") -> May-2025 | F20: Enterprise | G20: Marketplace | H20: G. Dubois | I20: Accessories | J20: 1068.17 | K20: =IF(L20<50, "Low", IF(L20<200, "Medium", "High")) -> High | L20: 2375.37 | M20: 0.109 | N20: 18 | O20: =(L46*N20)*(1-M20) -> 15979.622 | P20: =(J20*N20) -> 19227.06 | Q20: =(O20-P20) -> -3247.4383 | R20: =(Q20/O20) -> -0.20322373
A21: ORD-2025-745263 | B21: 45798 | C21: 45796 | D21: =DATEDIF(C21,B21, "MD") -> 2 | E21: =TEXT(Data!B21,"MMM-YYYY") -> Jul-2024 | F21: Enterprise | G21: Online | H21: M. Rossi | I21: Laptops | J21: 1015.16 | K21: =IF(L21<50, "Low", IF(L21<200, "Medium", "High")) -> High | L21: 2148.14 | M21: 0.038 | N21: 19 | O21: =(L47*N21)*(1-M21) -> 25535.28 | P21: =(J21*N21) -> 19288.04 | Q21: =(O21-P21) -> 6247.2399 | R21: =(Q21/O21) -> 0.24465132
A22: ORD-2024-798002 | B22: 45498 | C22: 45497 | D22: =DATEDIF(C22,B22, "MD") -> 1 | E22: =TEXT(Data!B22,"MMM-YYYY") -> May-2023 | F22: Non-Profit | G22: Direct | H22: J. Njeri | I22: Laptops | J22: 1494.4 | K22: =IF(L22<50, "Low", IF(L22<200, "Medium", "High")) -> High | L22: 3661.07 | M22: 0.072 | N22: 7 | O22: =(L48*N22)*(1-M22) -> 3565.5894 | P22: =(J22*N22) -> 10460.8 | Q22: =(O22-P22) -> -6895.2106 | R22: =(Q22/O22) -> -1.9338207
A23: ORD-2023-867836 | B23: 45057 | C23: 45074 | D23: =DATEDIF(B23,C23, "MD") -> 17 | E23: =TEXT(Data!B23,"MMM-YYYY") -> Jun-2025 | F23: Enterprise | G23: Marketplace | H23: E. Garcia | I23: Networking | J23: 1331.19 | K23: =IF(L23<50, "Low", IF(L23<200, "Medium", "High")) -> High | L23: 2903.09 | M23: 0.143 | N23: 8 | O23: =(L49*N23)*(1-M23) -> 24160.544 | P23: =(J23*N23) -> 10649.52 | Q23: =(O23-P23) -> 13511.024 | R23: =(Q23/O23) -> 0.55921853
A24: ORD-2025-580047 | B24: 45822 | C24: 45837 | D24: =DATEDIF(B24,C24, "MD") -> 15 | E24: =TEXT(Data!B24,"MMM-YYYY") -> May-2024 | F24: Consumer | G24: Marketplace | H24: M. Rossi | I24: Accessories | J24: 730.99 | K24: =IF(L24<50, "Low", IF(L24<200, "Medium", "High")) -> High | L24: 1242.84 | M24: 0.12 | N24: 10 | O24: =(L50*N24)*(1-M24) -> 16065.368 | P24: =(J24*N24) -> 7309.9 | Q24: =(O24-P24) -> 8755.468 | R24: =(Q24/O24) -> 0.54499019
A25: ORD-2024-500109 | B25: 45430 | C25: 45435 | D25: =DATEDIF(B25,C25, "MD") -> 5 | E25: =TEXT(Data!B25,"MMM-YYYY") -> Feb-2023 | F25: Enterprise | G25: Retail | H25: H. Kim | I25: Laptops | J25: 1274.59 | K25: =IF(L25<50, "Low", IF(L25<200, "Medium", "High")) -> High | L25: 2553.69 | M25: 0.01 | N25: 8 | O25: =(L51*N25)*(1-M25) -> 14187.65 | P25: =(J25*N25) -> 10196.72 | Q25: =(O25-P25) -> 3990.9304 | R25: =(Q25/O25) -> 0.28129608
A26: ORD-2023-271836 | B26: 44964 | C26: 44969 | D26: =DATEDIF(B26,C26, "MD") -> 5 | E26: =TEXT(Data!B26,"MMM-YYYY") -> Jun-2024 | F26: Education | G26: Online | H26: N. Brown | I26: Components | J26: 948.55 | K26: =IF(L26<50, "Low", IF(L26<200, "Medium", "High")) -> High | L26: 2089.16 | M26: 0.007 | N26: 12 | O26: =(L52*N26)*(1-M26) -> 31336.101 | P26: =(J26*N26) -> 11382.6 | Q26: =(O26-P26) -> 19953.501 | R26: =(Q26/O26) -> 0.63675762
A27: ORD-2024-215294 | B27: 45473 | C27: 45487 | D27: =DATEDIF(B27,C27, "MD") -> 14 | E27: =TEXT(Data!B27,"MMM-YYYY") -> Nov-2024 | F27: Education | G27: Retail | H27: C. Otieno | I27: Accessories | J27: 1491.85 | K27: =IF(L27<50, "Low", IF(L27<200, "Medium", "High")) -> High | L27: 2583.02 | M27: 0.168 | N27: 4 | O27: =(L53*N27)*(1-M27) -> 353.7664 | P27: =(J27*N27) -> 5967.4 | Q27: =(O27-P27) -> -5613.6336 | R27: =(Q27/O27) -> -15.868193
A28: ORD-2024-788105 | B28: 45626 | C28: 45656 | D28: =DATEDIF(B28,C28, "MD") -> 0 | E28: =TEXT(Data!B28,"MMM-YYYY") -> Jul-2024 | F28: Consumer | G28: Marketplace | H28: F. Müller | I28: Printers | J28: 117.64 | K28: =IF(L28<50, "Low", IF(L28<200, "Medium", "High")) -> Medium | L28: 175.67 | M28: 0 | N28: 10 | O28: =(L54*N28)*(1-M28) -> 3857.2 | P28: =(J28*N28) -> 1176.4 | Q28: =(O28-P28) -> 2680.8 | R28: =(Q28/O28) -> 0.69501193
A29: ORD-2024-855073 | B29: 45492 | C29: 45492 | D29: =DATEDIF(B29,C29, "MD") -> 0 | E29: =TEXT(Data!B29,"MMM-YYYY") -> Apr-2023 | F29: Small Business | G29: Retail | H29: A. Patel | I29: Phones | J29: 857.24 | K29: =IF(L29<50, "Low", IF(L29<200, "Medium", "High")) -> High | L29: 758.23 | M29: 0.125 | N29: 6 | O29: =(L55*N29)*(1-M29) -> 1243.5675 | P29: =(J29*N29) -> 5143.44 | Q29: =(O29-P29) -> -3899.8725 | R29: =(Q29/O29) -> -3.136036
A30: ORD-2023-897079 | B30: 45030 | C30: 45060 | D30: =DATEDIF(B30,C30, "MD") -> 0 | E30: =TEXT(Data!B30,"MMM-YYYY") -> Apr-2025 | F30: Consumer | G30: Marketplace | H30: M. Rossi | I30: Phones | J30: 209.25 | K30: =IF(L30<50, "Low", IF(L30<200, "Medium", "High")) -> High | L30: 434.8 | M30: 0 | N30: 9 | O30: =(L56*N30)*(1-M30) -> 377.1 | P30: =(J30*N30) -> 1883.25 | Q30: =(O30-P30) -> -1506.15 | R30: =(Q30/O30) -> -3.9940334
A31: ORD-2025-548982 | B31: 45754 | C31: 45758 | D31: =DATEDIF(B31,C31, "MD") -> 4 | E31: =TEXT(Data!B31,"MMM-YYYY") -> Dec-2024 | F31: Education | G31: Retail | H31: E. Garcia | I31: Networking | J31: 754.77 | K31: =IF(L31<50, "Low", IF(L31<200, "Medium", "High")) -> High | L31: 1666.18 | M31: 0.139 | N31: 14 | O31: =(L57*N31)*(1-M31) -> 11781.339 | P31: =(J31*N31) -> 10566.78 | Q31: =(O31-P31) -> 1214.5585 | R31: =(Q31/O31) -> 0.10309173
A32: ORD-2024-170313 | B32: 45653 | C32: 45672 | D32: =DATEDIF(B32,C32, "MD") -> 19 | E32: =TEXT(Data!B32,"MMM-YYYY") -> Feb-2023 | F32: Non-Profit | G32: Distributor | H32: G. Dubois | I32: Components | J32: 495.59 | K32: =IF(L32<50, "Low", IF(L32<200, "Medium", "High")) -> High | L32: 631.78 | M32: 0.087 | N32: 17 | O32: =(L58*N32)*(1-M32) -> 43367.692 | P32: =(J32*N32) -> 8425.03 | Q32: =(O32-P32) -> 34942.662 | R32: =(Q32/O32) -> 0.80573026
A33: ORD-2023-562894 | B33: 44980 | C33: 45010 | D33: =DATEDIF(B33,C33, "MD") -> 2 | E33: =TEXT(Data!B33,"MMM-YYYY") -> Jul-2025 | F33: Enterprise | G33: Online | H33: D. Smith | I33: Phones | J33: 1242.66 | K33: =IF(L33<50, "Low", IF(L33<200, "Medium", "High")) -> High | L33: 1794.07 | M33: 0.089 | N33: 16 | O33: =(L59*N33)*(1-M33) -> 10231.623 | P33: =(J33*N33) -> 19882.56 | Q33: =(O33-P33) -> -9650.9368 | R33: =(Q33/O33) -> -0.94324592
A34: ORD-2025-474710 | B34: 45862 | C34: 45875 | D34: =DATEDIF(B34,C34, "MD") -> 13 | E34: =TEXT(Data!B34,"MMM-YYYY") -> Apr-2024 | F34: Education | G34: Marketplace | H34: D. Smith | I34: Networking | J34: 1463.9 | K34: =IF(L34<50, "Low", IF(L34<200, "Medium", "High")) -> High | L34: 2633.02 | M34: 0.084 | N34: 4 | O34: =(L60*N34)*(1-M34) -> -19.30928 | P34: =(J34*N34) -> 5855.6 | Q34: =(O34-P34) -> -5874.9093 | R34: =(Q34/O34) -> 304.25315
A35: ORD-2024-629525 | B35: 45400 | C35: 45420 | D35: =DATEDIF(B35,C35, "MD") -> 20 | E35: =TEXT(Data!B35,"MMM-YYYY") -> Aug-2024 | F35: Non-Profit | G35: Not Provided | H35: D. Smith | I35: Laptops | J35: 645.33 | K35: =IF(L35<50, "Low", IF(L35<200, "Medium", "High")) -> High | L35: 1321.85 | M35: 0 | N35: 10 | O35: =(L61*N35)*(1-M35) -> 14370.6 | P35: =(J35*N35) -> 6453.3 | Q35: =(O35-P35) -> 7917.3 | R35: =(Q35/O35) -> 0.55093733
A36: ORD-2024-167215 | B36: 45527 | C36: 45525 | D36: =DATEDIF(C36,B36, "MD") -> 2 | E36: =TEXT(Data!B36,"MMM-YYYY") -> Mar-2023 | F36: Education | G36: Retail | H36: E. Garcia | I36: Components | J36: 1432.52 | K36: =IF(L36<50, "Low", IF(L36<200, "Medium", "High")) -> High | L36: 3036.87 | M36: 0 | N36: 9 | O36: =(L62*N36)*(1-M36) -> 17207.01 | P36: =(J36*N36) -> 12892.68 | Q36: =(O36-P36) -> 4314.33 | R36: =(Q36/O36) -> 0.25073095
A37: ORD-2023-864121 | B37: 45012 | C37: 45038 | D37: =DATEDIF(B37,C37, "MD") -> 26 | E37: =TEXT(Data!B37,"MMM-YYYY") -> Mar-2024 | F37: Non-Profit | G37: Marketplace | H37: J. Njeri | I37: Printers | J37: 178.53 | K37: =IF(L37<50, "Low", IF(L37<200, "Medium", "High")) -> Medium | L37: 199.37 | M37: 0.101 | N37: 37 | O37: =(L63*N37)*(1-M37) -> 86276.904 | P37: =(J37*N37) -> 6605.61 | Q37: =(O37-P37) -> 79671.294 | R37: =(Q37/O37) -> 0.9234371
A38: ORD-2024-692673 | B38: 45358 | C38: 45376 | D38: =DATEDIF(B38,C38, "MD") -> 18 | E38: =TEXT(Data!B38,"MMM-YYYY") -> Jun-2025 | F38: Corporate | G38: Online | H38: B. Chen | I38: Components | J38: 712.84 | K38: =IF(L38<50, "Low", IF(L38<200, "Medium", "High")) -> High | L38: 927.51 | M38: 0.243 | N38: 27 | O38: =(L64*N38)*(1-M38) -> 25427.751 | P38: =(J38*N38) -> 19246.68 | Q38: =(O38-P38) -> 6181.0711 | R38: =(Q38/O38) -> 0.24308367
A39: ORD-2025-718992 | B39: 45832 | C39: 45848 | D39: =DATEDIF(B39,C39, "MD") -> 16 | E39: =TEXT(Data!B39,"MMM-YYYY") -> Apr-2024 | F39: Enterprise | G39: Direct | H39: N. Brown | I39: Components | J39: 757.19 | K39: =IF(L39<50, "Low", IF(L39<200, "Medium", "High")) -> High | L39: 1735.41 | M39: 0.136 | N39: 8 | O39: =(L65*N39)*(1-M39) -> 13219.269 | P39: =(J39*N39) -> 6057.52 | Q39: =(O39-P39) -> 7161.7491 | R39: =(Q39/O39) -> 0.54176589
A40: ORD-2024-599522 | B40: 45401 | C40: 45418 | D40: =DATEDIF(B40,C40, "MD") -> 17 | E40: =TEXT(Data!B40,"MMM-YYYY") -> Jun-2023 | F40: Non-Profit | G40: Online | H40: A. Patel | I40: Printers | J40: 865.33 | K40: =IF(L40<50, "Low", IF(L40<200, "Medium", "High")) -> High | L40: 1395.64 | M40: 0.175 | N40: 13 | O40: =(L66*N40)*(1-M40) -> 8106.7057 | P40: =(J40*N40) -> 11249.29 | Q40: =(O40-P40) -> -3142.5843 | R40: =(Q40/O40) -> -0.38765244
A41: ORD-2023-651638 | B41: 45094 | C41: 45101 | D41: =DATEDIF(B41,C41, "MD") -> 7 | E41: =TEXT(Data!B41,"MMM-YYYY") -> Aug-2024 | F41: Corporate | G41: Retail | H41: I. Johnson | I41: Printers | J41: 313.99 | K41: =IF(L41<50, "Low", IF(L41<200, "Medium", "High")) -> High | L41: 454.42 | M41: 0.129 | N41: 9 | O41: =(L67*N41)*(1-M41) -> 8980.9071 | P41: =(J41*N41) -> 2825.91 | Q41: =(O41-P41) -> 6154.9971 | R41: =(Q41/O41) -> 0.68534248
A42: ORD-2024-635626 | B42: 45531 | C42: 45554 | D42: =DATEDIF(B42,C42, "MD") -> 23 | E42: =TEXT(Data!B42,"MMM-YYYY") -> Jan-2024 | F42: Small Business | G42: Direct | H42: D. Smith | I42: Monitors | J42: 1024.01 | K42: =IF(L42<50, "Low", IF(L42<200, "Medium", "High")) -> High | L42: 1580.97 | M42: 0.037 | N42: 27 | O42: =(L68*N42)*(1-M42) -> 32087.834 | P42: =(J42*N42) -> 27648.27 | Q42: =(O42-P42) -> 4439.5641 | R42: =(Q42/O42) -> 0.13835661
A43: ORD-2024-296582 | B43: 45302 | C43: 45324 | D43: =DATEDIF(B43,C43, "MD") -> 22 | E43: =TEXT(Data!B43,"MMM-YYYY") -> Oct-2024 | F43: Consumer | G43: Online | H43: K. Singh | I43: Networking | J43: 1206.2 | K43: =IF(L43<50, "Low", IF(L43<200, "Medium", "High")) -> High | L43: 1759.79 | M43: 0 | N43: 6 | O43: =(L69*N43)*(1-M43) -> 7368.06 | P43: =(J43*N43) -> 7237.2 | Q43: =(O43-P43) -> 130.86 | R43: =(Q43/O43) -> 0.017760442
A44: ORD-2024-998320 | B44: 45590 | C44: 45610 | D44: =DATEDIF(B44,C44, "MD") -> 20 | E44: =TEXT(Data!B44,"MMM-YYYY") -> May-2025 | F44: Corporate | G44: Direct | H44: H. Kim | I44: Printers | J44: 1396.48 | K44: =IF(L44<50, "Low", IF(L44<200, "Medium", "High")) -> High | L44: 3204.5 | M44: 0.318 | N44: 14 | O44: =(L70*N44)*(1-M44) -> 5778.736 | P44: =(J44*N44) -> 19550.72 | Q44: =(O44-P44) -> -13771.984 | R44: =(Q44/O44) -> -2.3832173
A45: ORD-2025-820255 | B45: 45806 | C45: 45828 | D45: =DATEDIF(B45,C45, "MD") -> 22 | E45: =TEXT(Data!B45,"MMM-YYYY") -> May-2024 | F45: Corporate | G45: Direct | H45: A. Patel | I45: Printers | J45: 483.47 | K45: =IF(L45<50, "Low", IF(L45<200, "Medium", "High")) -> High | L45: 1135.43 | M45: 0.146 | N45: 11 | O45: =(L71*N45)*(1-M45) -> 17662.129 | P45: =(J45*N45) -> 5318.17 | Q45: =(O45-P45) -> 12343.959 | R45: =(Q45/O45) -> 0.69889417
A46: ORD-2024-389336 | B46: 45432 | C46: 45445 | D46: =DATEDIF(B46,C46, "MD") -> 13 | E46: =TEXT(Data!B46,"MMM-YYYY") -> Apr-2023 | F46: Enterprise | G46: Marketplace | H46: K. Singh | I46: Components | J46: 675.43 | K46: =IF(L46<50, "Low", IF(L46<200, "Medium", "High")) -> High | L46: 996.36 | M46: 0.182 | N46: 22 | O46: =(L72*N46)*(1-M46) -> 22844.122 | P46: =(J46*N46) -> 14859.46 | Q46: =(O46-P46) -> 7984.6624 | R46: =(Q46/O46) -> 0.34952809
A47: ORD-2023-308124 | B47: 45035 | C47: 45046 | D47: =DATEDIF(B47,C47, "MD") -> 11 | E47: =TEXT(Data!B47,"MMM-YYYY") -> Jun-2023 | F47: Small Business | G47: Retail | H47: A. Patel | I47: Networking | J47: 826.55 | K47: =IF(L47<50, "Low", IF(L47<200, "Medium", "High")) -> High | L47: 1397.05 | M47: 0.169 | N47: 28 | O47: =(L73*N47)*(1-M47) -> 14447.799 | P47: =(J47*N47) -> 23143.4 | Q47: =(O47-P47) -> -8695.6008 | R47: =(Q47/O47) -> -0.60186334
A48: ORD-2023-128295 | B48: 45100 | C48: 45110 | D48: =DATEDIF(B48,C48, "MD") -> 10 | E48: =TEXT(Data!B48,"MMM-YYYY") -> May-2024 | F48: Consumer | G48: Online | H48: J. Njeri | I48: Printers | J48: 337.75 | K48: =IF(L48<50, "Low", IF(L48<200, "Medium", "High")) -> High | L48: 548.89 | M48: 0 | N48: 13 | O48: =(L74*N48)*(1-M48) -> 18926.83 | P48: =(J48*N48) -> 4390.75 | Q48: =(O48-P48) -> 14536.08 | R48: =(Q48/O48) -> 0.76801451
... A75: ORD-2024-800947 | B75: 45641 | C75: 45646 | D75: =DATEDIF(B75,C75, "MD") -> 5 | E75: =TEXT(Data!B75,"MMM-YYYY") -> May-2023 | F75: Small Business | G75: Direct | H75: J. Njeri | I75: Networking | J75: 717.55 | K75: =IF(L75<50, "Low", IF(L75<200, "Medium", "High")) -> High | L75: 546.43 | M75: 0.047 | N75: 18 | O75: =(L101*N75)*(1-M75) -> 34328.07 | P75: =(J75*N75) -> 12915.9 | Q75: =(O75-P75) -> 21412.17 | R75: =(Q75/O75) -> 0.62375106
A76: ORD-2023-382272 | B76: 45066 | C76: 45064 | D76: =DATEDIF(C76,B76, "MD") -> 2 | E76: =TEXT(Data!B76,"MMM-YYYY") -> Sep-2023 | F76: Corporate | G76: Distributor | H76: A. Patel | I76: Components | J76: 917.88 | K76: =IF(L76<50, "Low", IF(L76<200, "Medium", "High")) -> High | L76: 1347.92 | M76: 0.343 | N76: 5 | O76: =(L102*N76)*(1-M76) -> 10198.972 | P76: =(J76*N76) -> 4589.4 | Q76: =(O76-P76) -> 5609.5724 | R76: =(Q76/O76) -> 0.55001349
A77: ORD-2023-722117 | B77: 45187 | C77: 45207 | D77: =DATEDIF(B77,C77, "MD") -> 20 | E77: =TEXT(Data!B77,"MMM-YYYY") -> Aug-2024 | F77: Small Business | G77: Direct | H77: B. Chen | I77: Components | J77: 825.64 | K77: =IF(L77<50, "Low", IF(L77<200, "Medium", "High")) -> High | L77: 1108.43 | M77: 0.114 | N77: 7 | O77: =(L103*N77)*(1-M77) -> 2073.2046 | P77: =(J77*N77) -> 5779.48 | Q77: =(O77-P77) -> -3706.2754 | R77: =(Q77/O77) -> -1.7877037
A78: ORD-2024-446699 | B78: 45532 | C78: 45560 | D78: =DATEDIF(B78,C78, "MD") -> 28 | E78: =TEXT(Data!B78,"MMM-YYYY") -> Jun-2024 | F78: Non-Profit | G78: Online | H78: Not Provided | I78: Accessories | J78: 1394.65 | K78: =IF(L78<50, "Low", IF(L78<200, "Medium", "High")) -> High | L78: 3144.1 | M78: 0.134 | N78: 13 | O78: =(L104*N78)*(1-M78) -> 21984.96 | P78: =(J78*N78) -> 18130.45 | Q78: =(O78-P78) -> 3854.5101 | R78: =(Q78/O78) -> 0.17532486
A79: ORD-2024-451005 | B79: 45473 | C79: 45471 | D79: =DATEDIF(C79,B79, "MD") -> 2 | E79: =TEXT(Data!B79,"MMM-YYYY") -> Jun-2023 | F79: Small Business | G79: Direct | H79: L. Okafor | I79: Accessories | J79: 1112.98 | K79: =IF(L79<50, "Low", IF(L79<200, "Medium", "High")) -> High | L79: 2095.73 | M79: 0.072 | N79: 17 | O79: =(L105*N79)*(1-M79) -> 3822.367 | P79: =(J79*N79) -> 18920.66 | Q79: =(O79-P79) -> -15098.293 | R79: =(Q79/O79) -> -3.9499851
A80: ORD-2023-290279 | B80: 45091 | C80: 45093 | D80: =DATEDIF(B80,C80, "MD") -> 2 | E80: =TEXT(Data!B80,"MMM-YYYY") -> Nov-2024 | F80: Non-Profit | G80: Direct | H80: K. Singh | I80: Components | J80: 357.36 | K80: =IF(L80<50, "Low", IF(L80<200, "Medium", "High")) -> High | L80: 703.62 | M80: 0.257 | N80: 20 | O80: =(L106*N80)*(1-M80) -> 44117.408 | P80: =(J80*N80) -> 7147.2 | Q80: =(O80-P80) -> 36970.208 | R80: =(Q80/O80) -> 0.83799592
A81: ORD-2024-192263 | B81: 45617 | C81: 45647 | D81: =DATEDIF(B81,C81, "MD") -> 0 | E81: =TEXT(Data!B81,"MMM-YYYY") -> Feb-2023 | F81: Small Business | G81: Direct | H81: I. Johnson | I81: Monitors | J81: 1122.68 | K81: =IF(L81<50, "Low", IF(L81<200, "Medium", "High")) -> High | L81: 1997.19 | M81: 0.186 | N81: 3 | O81: =(L107*N81)*(1-M81) -> 3404.8806 | P81: =(J81*N81) -> 3368.04 | Q81: =(O81-P81) -> 36.8406 | R81: =(Q81/O81) -> 0.010819939
A82: ORD-2023-159379 | B82: 44965 | C82: 44968 | D82: =DATEDIF(B82,C82, "MD") -> 3 | E82: =TEXT(Data!B82,"MMM-YYYY") -> Aug-2023 | F82: Corporate | G82: Direct | H82: M. Rossi | I82: Networking | J82: 1410.05 | K82: =IF(L82<50, "Low", IF(L82<200, "Medium", "High")) -> High | L82: 2763.95 | M82: 0.161 | N82: 26 | O82: =(L108*N82)*(1-M82) -> 336.15374 | P82: =(J82*N82) -> 36661.3 | Q82: =(O82-P82) -> -36325.146 | R82: =(Q82/O82) -> -108.06111
A83: ORD-2023-343322 | B83: 45157 | C83: 45181 | D83: =DATEDIF(B83,C83, "MD") -> 24 | E83: =TEXT(Data!B83,"MMM-YYYY") -> May-2025 | F83: Enterprise | G83: Retail | H83: I. Johnson | I83: Printers | J83: 1183.95 | K83: =IF(L83<50, "Low", IF(L83<200, "Medium", "High")) -> High | L83: 1503.53 | M83: 0.241 | N83: 16 | O83: =(L109*N83)*(1-M83) -> 27333.837 | P83: =(J83*N83) -> 18943.2 | Q83: =(O83-P83) -> 8390.6366 | R83: =(Q83/O83) -> 0.30696886
A84: ORD-2025-114382 | B84: 45791 | C84: 45801 | D84: =DATEDIF(B84,C84, "MD") -> 10 | E84: =TEXT(Data!B84,"MMM-YYYY") -> Apr-2025 | F84: Small Business | G84: Marketplace | H84: K. Singh | I84: Components | J84: 170.39 | K84: =IF(L84<50, "Low", IF(L84<200, "Medium", "High")) -> High | L84: 388.04 | M84: 0.084 | N84: 15 | O84: =(L110*N84)*(1-M84) -> 2281.3896 | P84: =(J84*N84) -> 2555.85 | Q84: =(O84-P84) -> -274.4604 | R84: =(Q84/O84) -> -0.12030405
A85: ORD-2025-488349 | B85: 45770 | C85: 45769 | D85: =DATEDIF(C85,B85, "MD") -> 1 | E85: =TEXT(Data!B85,"MMM-YYYY") -> Mar-2025 | F85: Non-Profit | G85: Distributor | H85: D. Smith | I85: Monitors | J85: 23.24 | K85: =IF(L85<50, "Low", IF(L85<200, "Medium", "High")) -> Low | L85: 44.57 | M85: 0.215 | N85: 15 | O85: =(L111*N85)*(1-M85) -> 4198.3763 | P85: =(J85*N85) -> 348.6 | Q85: =(O85-P85) -> 3849.7763 | R85: =(Q85/O85) -> 0.9169679
A86: ORD-2025-330203 | B86: 45741 | C86: 45764 | D86: =DATEDIF(B86,C86, "MD") -> 23 | E86: =TEXT(Data!B86,"MMM-YYYY") -> Dec-2023 | F86: Consumer | G86: Retail | H86: H. Kim | I86: Networking | J86: 1421.19 | K86: =IF(L86<50, "Low", IF(L86<200, "Medium", "High")) -> High | L86: 1808.26 | M86: 0.104 | N86: 13 | O86: =(L112*N86)*(1-M86) -> 11939.782 | P86: =(J86*N86) -> 18475.47 | Q86: =(O86-P86) -> -6535.6876 | R86: =(Q86/O86) -> -0.5473875
A87: ORD-2023-841426 | B87: 45282 | C87: 45283 | D87: =DATEDIF(B87,C87, "MD") -> 1 | E87: =TEXT(Data!B87,"MMM-YYYY") -> Apr-2024 | F87: Non-Profit | G87: Marketplace | H87: D. Smith | I87: Components | J87: 1186.18 | K87: =IF(L87<50, "Low", IF(L87<200, "Medium", "High")) -> High | L87: 1285.09 | M87: 0.07 | N87: 11 | O87: =(L113*N87)*(1-M87) -> 18364.589 | P87: =(J87*N87) -> 13047.98 | Q87: =(O87-P87) -> 5316.6091 | R87: =(Q87/O87) -> 0.2895033
A88: ORD-2024-594592 | B88: 45388 | C88: 45407 | D88: =DATEDIF(B88,C88, "MD") -> 19 | E88: =TEXT(Data!B88,"MMM-YYYY") -> Aug-2025 | F88: Corporate | G88: Retail | H88: K. Singh | I88: Components | J88: 1366.48 | K88: =IF(L88<50, "Low", IF(L88<200, "Medium", "High")) -> High | L88: 1678.14 | M88: 0.154 | N88: 10 | O88: =(L114*N88)*(1-M88) -> 36.9702 | P88: =(J88*N88) -> 13664.8 | Q88: =(O88-P88) -> -13627.83 | R88: =(Q88/O88) -> -368.61661
A89: ORD-2025-863978 | B89: 45876 | C89: 45888 | D89: =DATEDIF(B89,C89, "MD") -> 12 | E89: =TEXT(Data!B89,"MMM-YYYY") -> Jan-2024 | F89: Corporate | G89: Not Provided | H89: M. Rossi | I89: Components | J89: 601.51 | K89: =IF(L89<50, "Low", IF(L89<200, "Medium", "High")) -> High | L89: 679.35 | M89: 0.188 | N89: 3 | O89: =(L115*N89)*(1-M89) -> 532.266 | P89: =(J89*N89) -> 1804.53 | Q89: =(O89-P89) -> -1272.264 | R89: =(Q89/O89) -> -2.3902785
A90: ORD-2024-604471 | B90: 45312 | C90: 45316 | D90: =DATEDIF(B90,C90, "MD") -> 4 | E90: =TEXT(Data!B90,"MMM-YYYY") -> Jun-2023 | F90: Consumer | G90: Direct | H90: C. Otieno | I90: Monitors | J90: 523.7 | K90: =IF(L90<50, "Low", IF(L90<200, "Medium", "High")) -> High | L90: 1109.92 | M90: 0.03 | N90: 11 | O90: =(L116*N90)*(1-M90) -> 2666.1129 | P90: =(J90*N90) -> 5760.7 | Q90: =(O90-P90) -> -3094.5871 | R90: =(Q90/O90) -> -1.1607112
A91: ORD-2023-258768 | B91: 45106 | C91: 45109 | D91: =DATEDIF(B91,C91, "MD") -> 3 | E91: =TEXT(Data!B91,"MMM-YYYY") -> Apr-2025 | F91: Education | G91: Marketplace | H91: F. Müller | I91: Monitors | J91: 55.65 | K91: =IF(L91<50, "Low", IF(L91<200, "Medium", "High")) -> Medium | L91: 83.57 | M91: 0.066 | N91: 8 | O91: =(L117*N91)*(1-M91) -> 25677.677 | P91: =(J91*N91) -> 445.2 | Q91: =(O91-P91) -> 25232.477 | R91: =(Q91/O91) -> 0.98266198
A92: ORD-2025-626047 | B92: 45775 | C92: 45792 | D92: =DATEDIF(B92,C92, "MD") -> 17 | E92: =TEXT(Data!B92,"MMM-YYYY") -> Jun-2025 | F92: Education | G92: Direct | H92: N. Brown | I92: Networking | J92: 691.19 | K92: =IF(L92<50, "Low", IF(L92<200, "Medium", "High")) -> High | L92: 1284.3 | M92: 0.074 | N92: 7 | O92: =(L118*N92)*(1-M92) -> 346.4629 | P92: =(J92*N92) -> 4838.33 | Q92: =(O92-P92) -> -4491.8671 | R92: =(Q92/O92) -> -12.96493
A93: ORD-2025-526752 | B93: 45817 | C93: 45833 | D93: =DATEDIF(B93,C93, "MD") -> 16 | E93: =TEXT(Data!B93,"MMM-YYYY") -> Jun-2023 | F93: Enterprise | G93: Distributor | H93: M. Rossi | I93: Phones | J93: 527.33 | K93: =IF(L93<50, "Low", IF(L93<200, "Medium", "High")) -> High | L93: 911.72 | M93: 0.144 | N93: 25 | O93: =(L119*N93)*(1-M93) -> 74251.58 | P93: =(J93*N93) -> 13183.25 | Q93: =(O93-P93) -> 61068.33 | R93: =(Q93/O93) -> 0.82245159
A94: ORD-2023-374486 | B94: 45101 | C94: 45100 | D94: =DATEDIF(C94,B94, "MD") -> 1 | E94: =TEXT(Data!B94,"MMM-YYYY") -> Oct-2024 | F94: Non-Profit | G94: Retail | H94: E. Garcia | I94: Printers | J94: 804.01 | K94: =IF(L94<50, "Low", IF(L94<200, "Medium", "High")) -> High | L94: 1405.07 | M94: 0.096 | N94: 8 | O94: =(L120*N94)*(1-M94) -> 4491.2166 | P94: =(J94*N94) -> 6432.08 | Q94: =(O94-P94) -> -1940.8634 | R94: =(Q94/O94) -> -0.43214646
A95: ORD-2024-997336 | B95: 45569 | C95: 45598 | D95: =DATEDIF(B95,C95, "MD") -> 29 | E95: =TEXT(Data!B95,"MMM-YYYY") -> Sep-2025 | F95: Corporate | G95: Distributor | H95: F. Müller | I95: Accessories | J95: 412.09 | K95: =IF(L95<50, "Low", IF(L95<200, "Medium", "High")) -> High | L95: 968.94 | M95: 0.099 | N95: 23 | O95: =(L121*N95)*(1-M95) -> 1834.1927 | P95: =(J95*N95) -> 9478.07 | Q95: =(O95-P95) -> -7643.8773 | R95: =(Q95/O95) -> -4.1674341
A96: ORD-2025-725646 | B96: 45910 | C96: 45930 | D96: =DATEDIF(B96,C96, "MD") -> 20 | E96: =TEXT(Data!B96,"MMM-YYYY") -> Apr-2023 | F96: Corporate | G96: Direct | H96: L. Okafor | I96: Phones | J96: 1009.48 | K96: =IF(L96<50, "Low", IF(L96<200, "Medium", "High")) -> High | L96: 1088.81 | M96: 0.16 | N96: 6 | O96: =(L122*N96)*(1-M96) -> 9873.8136 | P96: =(J96*N96) -> 6056.88 | Q96: =(O96-P96) -> 3816.9336 | R96: =(Q96/O96) -> 0.38657136
A97: ORD-2023-868734 | B97: 45022 | C97: 45043 | D97: =DATEDIF(B97,C97, "MD") -> 21 | E97: =TEXT(Data!B97,"MMM-YYYY") -> Aug-2025 | F97: Enterprise | G97: Distributor | H97: I. Johnson | I97: Printers | J97: 1084.79 | K97: =IF(L97<50, "Low", IF(L97<200, "Medium", "High")) -> High | L97: 2484.99 | M97: 0.034 | N97: 18 | O97: =(L123*N97)*(1-M97) -> 47694.762 | P97: =(J97*N97) -> 19526.22 | Q97: =(O97-P97) -> 28168.542 | R97: =(Q97/O97) -> 0.59060033
A98: ORD-2025-262491 | B98: 45870 | C98: 45885 | D98: =DATEDIF(B98,C98, "MD") -> 15 | E98: =TEXT(Data!B98,"MMM-YYYY") -> May-2024 | F98: Enterprise | G98: Direct | H98: O. Wang | I98: Monitors | J98: 24.44 | K98: =IF(L98<50, "Low", IF(L98<200, "Medium", "High")) -> Low | L98: 28.69 | M98: 0.146 | N98: 6 | O98: =(L124*N98)*(1-M98) -> 8605.3481 | P98: =(J98*N98) -> 146.64 | Q98: =(O98-P98) -> 8458.7081 | R98: =(Q98/O98) -> 0.98295943
A99: ORD-2024-638884 | B99: 45440 | C99: 45438 | D99: =DATEDIF(C99,B99, "MD") -> 2 | E99: =TEXT(Data!B99,"MMM-YYYY") -> Jul-2025 | F99: Enterprise | G99: Online | H99: F. Müller | I99: Accessories | J99: 1227.08 | K99: =IF(L99<50, "Low", IF(L99<200, "Medium", "High")) -> High | L99: 1896.62 | M99: 0 | N99: 18 | O99: =(L125*N99)*(1-M99) -> 25810.2 | P99: =(J99*N99) -> 22087.44 | Q99: =(O99-P99) -> 3722.76 | R99: =(Q99/O99) -> 0.144236
A100: ORD-2025-541501 | B100: 45860 | C100: 45887 | D100: =DATEDIF(B100,C100, "MD") -> 27 | E100: =TEXT(Data!B100,"MMM-YYYY") -> Feb-2023 | F100: Non-Profit | G100: Marketplace | H100: M. Rossi | I100: Networking | J100: 547.32 | K100: =IF(L100<50, "Low", IF(L100<200, "Medium", "High")) -> High | L100: 419.17 | M100: 0.092 | N100: 14 | O100: =(L126*N100)*(1-M100) -> 3615.6742 | P100: =(J100*N100) -> 7662.48 | Q100: =(O100-P100) -> -4046.8058 | R100: =(Q100/O100) -> -1.1192396
A101: ORD-2023-422918 | B101: 44985 | C101: 45005 | D101: =DATEDIF(B101,C101, "MD") -> 20 | E101: =TEXT(Data!B101,"MMM-YYYY") -> Jan-2025 | F101: Small Business | G101: Direct | H101: H. Kim | I101: Laptops | J101: 1200.78 | K101: =IF(L101<50, "Low", IF(L101<200, "Medium", "High")) -> High | L101: 2001.17 | M101: 0.292 | N101: 18 | O101: =(L127*N101)*(1-M101) -> 8854.2763 | P101: =(J101*N101) -> 21614.04 | Q101: =(O101-P101) -> -12759.764 | R101: =(Q101/O101) -> -1.4410849
A102: ORD-2025-328504 | B102: 45684 | C102: 45703 | D102: =DATEDIF(B102,C102, "MD") -> 19 | E102: =TEXT(Data!B102,"MMM-YYYY") -> Jan-2024 | F102: Non-Profit | G102: Direct | H102: L. Okafor | I102: Phones | J102: 1253.22 | K102: =IF(L102<50, "Low", IF(L102<200, "Medium", "High")) -> High | L102: 3104.71 | M102: 0 | N102: 17 | O102: =(L128*N102)*(1-M102) -> 31422.63 | P102: =(J102*N102) -> 21304.74 | Q102: =(O102-P102) -> 10117.89 | R102: =(Q102/O102) -> 0.32199374
A103: ORD-2024-851883 | B103: 45304 | C103: 45313 | D103: =DATEDIF(B103,C103, "MD") -> 9 | E103: =TEXT(Data!B103,"MMM-YYYY") -> Mar-2025 | F103: Enterprise | G103: Marketplace | H103: J. Njeri | I103: Components | J103: 313.6 | K103: =IF(L103<50, "Low", IF(L103<200, "Medium", "High")) -> High | L103: 334.28 | M103: 0.14 | N103: 22 | O103: =(L129*N103)*(1-M103) -> 854.9948 | P103: =(J103*N103) -> 6899.2 | Q103: =(O103-P103) -> -6044.2052 | R103: =(Q103/O103) -> -7.0692888
A104: ORD-2025-662997 | B104: 45747 | C104: 45751 | D104: =DATEDIF(B104,C104, "MD") -> 4 | E104: =TEXT(Data!B104,"MMM-YYYY") -> Dec-2024 | F104: Corporate | G104: Direct | H104: C. Otieno | I104: Laptops | J104: 862.08 | K104: =IF(L104<50, "Low", IF(L104<200, "Medium", "High")) -> High | L104: 1952.83 | M104: 0 | N104: 7 | O104: =(L130*N104)*(1-M104) -> 2527.7 | P104: =(J104*N104) -> 6034.56 | Q104: =(O104-P104) -> -3506.86 | R104: =(Q104/O104) -> -1.3873719
A105: ORD-2024-478165 | B105: 45631 | C105: 45654 | D105: =DATEDIF(B105,C105, "MD") -> 23 | E105: =TEXT(Data!B105,"MMM-YYYY") -> Sep-2024 | F105: Corporate | G105: Direct | H105: F. Müller | I105: Accessories | J105: 107.03 | K105: =IF(L105<50, "Low", IF(L105<200, "Medium", "High")) -> High | L105: 242.29 | M105: 0.18 | N105: 30 | O105: =(L131*N105)*(1-M105) -> 24706.764 | P105: =(J105*N105) -> 3210.9 | Q105: =(O105-P105) -> 21495.864 | R105: =(Q105/O105) -> 0.87003964
A106: ORD-2024-771210 | B106: 45549 | C106: 45570 | D106: =DATEDIF(B106,C106, "MD") -> 21 | E106: =TEXT(Data!B106,"MMM-YYYY") -> May-2024 | F106: Small Business | G106: Online | H106: H. Kim | I106: Laptops | J106: 1405.56 | K106: =IF(L106<50, "Low", IF(L106<200, "Medium", "High")) -> High | L106: 2968.87 | M106: 0.169 | N106: 5 | O106: =(L132*N106)*(1-M106) -> 4270.2181 | P106: =(J106*N106) -> 7027.8 | Q106: =(O106-P106) -> -2757.5818 | R106: =(Q106/O106) -> -0.64577072
A107: ORD-2024-155337 | B107: 45433 | C107: 45439 | D107: =DATEDIF(B107,C107, "MD") -> 6 | E107: =TEXT(Data!B107,"MMM-YYYY") -> May-2023 | F107: Non-Profit | G107: Online | H107: M. Rossi | I107: Components | J107: 1157.51 | K107: =IF(L107<50, "Low", IF(L107<200, "Medium", "High")) -> High | L107: 1394.3 | M107: 0.278 | N107: 12 | O107: =(L133*N107)*(1-M107) -> 4055.5318 | P107: =(J107*N107) -> 13890.12 | Q107: =(O107-P107) -> -9834.5882 | R107: =(Q107/O107) -> -2.4249812
A108: ORD-2023-251563 | B108: 45057 | C108: 45084 | D108: =DATEDIF(B108,C108, "MD") -> 27 | E108: =TEXT(Data!B108,"MMM-YYYY") -> Aug-2024 | F108: Corporate | G108: Online | H108: J. Njeri | I108: Phones | J108: 12.85 | K108: =IF(L108<50, "Low", IF(L108<200, "Medium", "High")) -> Low | L108: 15.41 | M108: 0.137 | N108: 39 | O108: =(L134*N108)*(1-M108) -> 22483.549 | P108: =(J108*N108) -> 501.15 | Q108: =(O108-P108) -> 21982.399 | R108: =(Q108/O108) -> 0.97771037
A109: ORD-2024-286833 | B109: 45518 | C109: 45539 | D109: =DATEDIF(B109,C109, "MD") -> 21 | E109: =TEXT(Data!B109,"MMM-YYYY") -> Oct-2024 | F109: Non-Profit | G109: Online | H109: J. Njeri | I109: Phones | J109: 1138.8 | K109: =IF(L109<50, "Low", IF(L109<200, "Medium", "High")) -> High | L109: 2250.81 | M109: 0.123 | N109: 12 | O109: =(L135*N109)*(1-M109) -> 5654.2295 | P109: =(J109*N109) -> 13665.6 | Q109: =(O109-P109) -> -8011.3705 | R109: =(Q109/O109) -> -1.416881
A110: ORD-2024-792558 | B110: 45581 | C110: 45604 | D110: =DATEDIF(B110,C110, "MD") -> 23 | E110: =TEXT(Data!B110,"MMM-YYYY") -> Jun-2024 | F110: Small Business | G110: Retail | H110: J. Njeri | I110: Networking | J110: 82.14 | K110: =IF(L110<50, "Low", IF(L110<200, "Medium", "High")) -> Medium | L110: 166.04 | M110: 0 | N110: 10 | O110: =(L136*N110)*(1-M110) -> 5727.1 | P110: =(J110*N110) -> 821.4 | Q110: =(O110-P110) -> 4905.7 | R110: =(Q110/O110) -> 0.85657663
A111: ORD-2024-166150 | B111: 45445 | C111: 45451 | D111: =DATEDIF(B111,C111, "MD") -> 6 | E111: =TEXT(Data!B111,"MMM-YYYY") -> Jun-2024 | F111: Consumer | G111: Marketplace | H111: A. Patel | I111: Accessories | J111: 292.94 | K111: =IF(L111<50, "Low", IF(L111<200, "Medium", "High")) -> High | L111: 356.55 | M111: 0.229 | N111: 2 | O111: =(L137*N111)*(1-M111) -> 3583.4075 | P111: =(J111*N111) -> 585.88 | Q111: =(O111-P111) -> 2997.5275 | R111: =(Q111/O111) -> 0.83650199
... A146: ORD-2023-309373 | B146: 45112 | C146: 45121 | D146: =DATEDIF(B146,C146, "MD") -> 9 | E146: =TEXT(Data!B146,"MMM-YYYY") -> Nov-2023 | F146: Enterprise | G146: Direct | H146: B. Chen | I146: Networking | J146: 578.85 | K146: =IF(L146<50, "Low", IF(L146<200, "Medium", "High")) -> High | L146: 998.76 | M146: 0.082 | N146: 28 | O146: =(L172*N146)*(1-M146) -> 31331.12 | P146: =(J146*N146) -> 16207.8 | Q146: =(O146-P146) -> 15123.32 | R146: =(Q146/O146) -> 0.48269324
A147: ORD-2023-825495 | B147: 45260 | C147: 45259 | D147: =DATEDIF(C147,B147, "MD") -> 1 | E147: =TEXT(Data!B147,"MMM-YYYY") -> Sep-2025 | F147: Small Business | G147: Marketplace | H147: E. Garcia | I147: Laptops | J147: 275.56 | K147: =IF(L147<50, "Low", IF(L147<200, "Medium", "High")) -> High | L147: 630.72 | M147: 0.107 | N147: 23 | O147: =(L173*N147)*(1-M147) -> 42353.883 | P147: =(J147*N147) -> 6337.88 | Q147: =(O147-P147) -> 36016.003 | R147: =(Q147/O147) -> 0.85035894
A148: ORD-2025-244832 | B148: 45911 | C148: 45928 | D148: =DATEDIF(B148,C148, "MD") -> 17 | E148: =TEXT(Data!B148,"MMM-YYYY") -> Apr-2024 | F148: Non-Profit | G148: Distributor | H148: J. Njeri | I148: Laptops | J148: 891.46 | K148: =IF(L148<50, "Low", IF(L148<200, "Medium", "High")) -> High | L148: 728.61 | M148: 0.185 | N148: 6 | O148: =(L174*N148)*(1-M148) -> 49.7802 | P148: =(J148*N148) -> 5348.76 | Q148: =(O148-P148) -> -5298.9798 | R148: =(Q148/O148) -> -106.44754
A149: ORD-2024-211453 | B149: 45386 | C149: 45406 | D149: =DATEDIF(B149,C149, "MD") -> 20 | E149: =TEXT(Data!B149,"MMM-YYYY") -> Sep-2023 | F149: Non-Profit | G149: Direct | H149: O. Wang | I149: Accessories | J149: 683.42 | K149: =IF(L149<50, "Low", IF(L149<200, "Medium", "High")) -> High | L149: 951.51 | M149: 0 | N149: 14 | O149: =(L175*N149)*(1-M149) -> 31944.08 | P149: =(J149*N149) -> 9567.88 | Q149: =(O149-P149) -> 22376.2 | R149: =(Q149/O149) -> 0.70048034
A150: ORD-2023-192324 | B150: 45183 | C150: 45185 | D150: =DATEDIF(B150,C150, "MD") -> 2 | E150: =TEXT(Data!B150,"MMM-YYYY") -> Sep-2024 | F150: Non-Profit | G150: Direct | H150: B. Chen | I150: Printers | J150: 376.83 | K150: =IF(L150<50, "Low", IF(L150<200, "Medium", "High")) -> High | L150: 732.88 | M150: 0.188 | N150: 25 | O150: =(L176*N150)*(1-M150) -> 5066.271 | P150: =(J150*N150) -> 9420.75 | Q150: =(O150-P150) -> -4354.479 | R150: =(Q150/O150) -> -0.85950377
A151: ORD-2024-438404 | B151: 45558 | C151: 45583 | D151: =DATEDIF(B151,C151, "MD") -> 25 | E151: =TEXT(Data!B151,"MMM-YYYY") -> Apr-2025 | F151: Small Business | G151: Online | H151: N. Brown | I151: Phones | J151: 1297 | K151: =IF(L151<50, "Low", IF(L151<200, "Medium", "High")) -> High | L151: 2411.52 | M151: 0.021 | N151: 18 | O151: =(L177*N151)*(1-M151) -> 57712.05 | P151: =(J151*N151) -> 23346 | Q151: =(O151-P151) -> 34366.05 | R151: =(Q151/O151) -> 0.59547443
A152: ORD-2025-246470 | B152: 45763 | C152: 45793 | D152: =DATEDIF(B152,C152, "MD") -> 0 | E152: =TEXT(Data!B152,"MMM-YYYY") -> Jul-2023 | F152: Enterprise | G152: Distributor | H152: K. Singh | I152: Printers | J152: 763.32 | K152: =IF(L152<50, "Low", IF(L152<200, "Medium", "High")) -> High | L152: 568.29 | M152: 0.131 | N152: 16 | O152: =(L178*N152)*(1-M152) -> 26608.919 | P152: =(J152*N152) -> 12213.12 | Q152: =(O152-P152) -> 14395.799 | R152: =(Q152/O152) -> 0.54101405
A153: ORD-2023-497686 | B153: 45110 | C153: 45130 | D153: =DATEDIF(B153,C153, "MD") -> 20 | E153: =TEXT(Data!B153,"MMM-YYYY") -> Dec-2023 | F153: Small Business | G153: Distributor | H153: F. Müller | I153: Laptops | J153: 1001.96 | K153: =IF(L153<50, "Low", IF(L153<200, "Medium", "High")) -> High | L153: 1254.95 | M153: 0.045 | N153: 18 | O153: =(L179*N153)*(1-M153) -> 517.2471 | P153: =(J153*N153) -> 18035.28 | Q153: =(O153-P153) -> -17518.033 | R153: =(Q153/O153) -> -33.867822
A154: ORD-2023-596758 | B154: 45267 | C154: 45265 | D154: =DATEDIF(C154,B154, "MD") -> 2 | E154: =TEXT(Data!B154,"MMM-YYYY") -> Feb-2024 | F154: Non-Profit | G154: Marketplace | H154: H. Kim | I154: Printers | J154: 1097.59 | K154: =IF(L154<50, "Low", IF(L154<200, "Medium", "High")) -> High | L154: 845.55 | M154: 0.184 | N154: 6 | O154: =(L180*N154)*(1-M154) -> 2454.4138 | P154: =(J154*N154) -> 6585.54 | Q154: =(O154-P154) -> -4131.1262 | R154: =(Q154/O154) -> -1.6831417
A155: ORD-2024-201376 | B155: 45340 | C155: 45355 | D155: =DATEDIF(B155,C155, "MD") -> 15 | E155: =TEXT(Data!B155,"MMM-YYYY") -> Oct-2023 | F155: Education | G155: Direct | H155: K. Singh | I155: Printers | J155: 928.68 | K155: =IF(L155<50, "Low", IF(L155<200, "Medium", "High")) -> High | L155: 2145.17 | M155: 0.136 | N155: 16 | O155: =(L181*N155)*(1-M155) -> 5684.1523 | P155: =(J155*N155) -> 14858.88 | Q155: =(O155-P155) -> -9174.7277 | R155: =(Q155/O155) -> -1.614089
A156: ORD-2023-842488 | B156: 45230 | C156: 45232 | D156: =DATEDIF(B156,C156, "MD") -> 2 | E156: =TEXT(Data!B156,"MMM-YYYY") -> Aug-2024 | F156: Education | G156: Retail | H156: O. Wang | I156: Accessories | J156: 867.89 | K156: =IF(L156<50, "Low", IF(L156<200, "Medium", "High")) -> High | L156: 1349.94 | M156: 0.184 | N156: 10 | O156: =(L182*N156)*(1-M156) -> 48.3072 | P156: =(J156*N156) -> 8678.9 | Q156: =(O156-P156) -> -8630.5928 | R156: =(Q156/O156) -> -178.66059
A157: ORD-2024-136321 | B157: 45511 | C157: 45521 | D157: =DATEDIF(B157,C157, "MD") -> 10 | E157: =TEXT(Data!B157,"MMM-YYYY") -> Feb-2024 | F157: Consumer | G157: Online | H157: K. Singh | I157: Networking | J157: 436.58 | K157: =IF(L157<50, "Low", IF(L157<200, "Medium", "High")) -> High | L157: 527.48 | M157: 0.111 | N157: 19 | O157: =(L183*N157)*(1-M157) -> 37272.187 | P157: =(J157*N157) -> 8295.02 | Q157: =(O157-P157) -> 28977.167 | R157: =(Q157/O157) -> 0.77744746
A158: ORD-2024-764468 | B158: 45323 | C158: 45343 | D158: =DATEDIF(B158,C158, "MD") -> 20 | E158: =TEXT(Data!B158,"MMM-YYYY") -> Aug-2024 | F158: Small Business | G158: Marketplace | H158: A. Patel | I158: Networking | J158: 656.2 | K158: =IF(L158<50, "Low", IF(L158<200, "Medium", "High")) -> High | L158: 1467.17 | M158: 0.018 | N158: 5 | O158: =(L184*N158)*(1-M158) -> 9391.848 | P158: =(J158*N158) -> 3281 | Q158: =(O158-P158) -> 6110.848 | R158: =(Q158/O158) -> 0.65065448
A159: ORD-2024-553449 | B159: 45531 | C159: 45553 | D159: =DATEDIF(B159,C159, "MD") -> 22 | E159: =TEXT(Data!B159,"MMM-YYYY") -> Feb-2025 | F159: Consumer | G159: Direct | H159: B. Chen | I159: Components | J159: 896.75 | K159: =IF(L159<50, "Low", IF(L159<200, "Medium", "High")) -> High | L159: 1651.14 | M159: 0.025 | N159: 15 | O159: =(L185*N159)*(1-M159) -> 20216.284 | P159: =(J159*N159) -> 13451.25 | Q159: =(O159-P159) -> 6765.0337 | R159: =(Q159/O159) -> 0.3346329
A160: ORD-2025-766923 | B160: 45703 | C160: 45703 | D160: =DATEDIF(B160,C160, "MD") -> 0 | E160: =TEXT(Data!B160,"MMM-YYYY") -> Aug-2025 | F160: Small Business | G160: Marketplace | H160: L. Okafor | I160: Accessories | J160: 815.83 | K160: =IF(L160<50, "Low", IF(L160<200, "Medium", "High")) -> High | L160: 1982.18 | M160: 0.127 | N160: 6 | O160: =(L186*N160)*(1-M160) -> 7100.6852 | P160: =(J160*N160) -> 4894.98 | Q160: =(O160-P160) -> 2205.7052 | R160: =(Q160/O160) -> 0.31063272
...

Sheet Sales person Pivot
A1: Month | B1: (All)
A3: Row Labels | B3: Sum of Gross Revenue | C3: Count of OrderID | D3: Sum of Gross Profit | E3: Sales Person | F3: Revenue Per Order | G3: Average Orders Per Month | H3: GP/Order | I3: Highest Rank | J3: Lowest Rank
A4: A. Patel | B4: 599376.02 | C4: 46 | D4: 4160.97 | E4: O. Wang | F4: =GETPIVOTDATA("Sum of Gross Revenue",$A$3,"Salesperson","O. Wang")/GETPIVOTDATA("Count of OrderID",$A$3,"Salesperson","O. Wang") -> 17388.644 | G4: =GETPIVOTDATA("Count of OrderID",$A$3,"Salesperson","A. Patel")/12 -> 3.8333333 | H4: =GETPIVOTDATA("Sum of Gross Profit",$A$3,"Salesperson","A. Patel")/G4 -> 1085.4704 | I4: =_xlfn.RANK.EQ(GETPIVOTDATA("Sum of Gross Revenue",$A$3,"Salesperson","A. Patel"),B4:B19,0) -> 10 | J4: =_xlfn.RANK.EQ(GETPIVOTDATA("Sum of Gross Revenue",$A$3,"Salesperson","A. Patel"),B4:B19,1) -> 7 | K4: =IF(_xlfn.RANK.EQ(G4,G4:G19,0)>=3,"Top 3 ","") -> Top 3
A5: B. Chen | B5: 779292.78 | C5: 48 | D5: 201527.09 | E5: Not Provided | F5: =GETPIVOTDATA("Sum of Gross Revenue",$A$3,"Salesperson","Not Provided")/GETPIVOTDATA("Count of OrderID",$A$3,"Salesperson","Not Provided") -> 24051.575 | G5: =GETPIVOTDATA("Count of OrderID",$A$3,"Salesperson","B. Chen")/12 -> 4 | H5: =GETPIVOTDATA("Sum of Gross Profit",$A$3,"Salesperson","B. Chen")/G5 -> 50381.773
A6: C. Otieno | B6: 536935.05 | C6: 37 | D6: 77518.211 | E6: N. Brown | F6: =GETPIVOTDATA("Sum of Gross Revenue",$A$3,"Salesperson","N. Brown")/GETPIVOTDATA("Count of OrderID",$A$3,"Salesperson","N. Brown") -> 16290.51 | G6: =GETPIVOTDATA("Count of OrderID",$A$3,"Salesperson","C. Otieno")/12 -> 3.0833333 | H6: =GETPIVOTDATA("Sum of Gross Profit",$A$3,"Salesperson","C. Otieno")/G6 -> 25141.041
A7: D. Smith | B7: 562621.6 | C7: 38 | D7: 136878.34 | E7: M. Rossi | F7: =GETPIVOTDATA("Sum of Gross Revenue",$A$3,"Salesperson","M. Rossi")/GETPIVOTDATA("Count of OrderID",$A$3,"Salesperson","M. Rossi") -> 15999.65 | G7: =GETPIVOTDATA("Count of OrderID",$A$3,"Salesperson","D. Smith")/12 -> 3.1666667 | H7: =GETPIVOTDATA("Sum of Gross Profit",$A$3,"Salesperson","D. Smith")/G7 -> 43224.738
A8: E. Garcia | B8: 482522.34 | C8: 34 | D8: 143657.24 | E8: L. Okafor | F8: =GETPIVOTDATA("Sum of Gross Revenue",$A$3,"Salesperson","L. Okafor")/GETPIVOTDATA("Count of OrderID",$A$3,"Salesperson","L. Okafor") -> 15871.241 | G8: =GETPIVOTDATA("Count of OrderID",$A$3,"Salesperson","E. Garcia")/12 -> 2.8333333 | H8: =GETPIVOTDATA("Sum of Gross Profit",$A$3,"Salesperson","E. Garcia")/G8 -> 50702.556
A9: F. Müller | B9: 1090799.7 | C9: 51 | D9: 529895.57 | E9: K. Singh | F9: =GETPIVOTDATA("Sum of Gross Revenue",$A$3,"Salesperson","K. Singh")/GETPIVOTDATA("Count of OrderID",$A$3,"Salesperson","K. Singh") -> 20529.39 | G9: =GETPIVOTDATA("Count of OrderID",$A$3,"Salesperson","F. Müller")/12 -> 4.25 | H9: =GETPIVOTDATA("Sum of Gross Profit",$A$3,"Salesperson","F. Müller")/G9 -> 124681.31
A10: G. Dubois | B10: 623151.52 | C10: 30 | D10: 284939.68 | E10: J. Njeri | F10: =GETPIVOTDATA("Sum of Gross Revenue",$A$3,"Salesperson","J. Njeri")/GETPIVOTDATA("Count of OrderID",$A$3,"Salesperson","J. Njeri") -> 15450.871 | G10: =GETPIVOTDATA("Count of OrderID",$A$3,"Salesperson","G. Dubois")/12 -> 2.5 | H10: =GETPIVOTDATA("Sum of Gross Profit",$A$3,"Salesperson","G. Dubois")/G10 -> 113975.87
A11: H. Kim | B11: 679594.41 | C11: 45 | D11: 119046.92 | E11: I. Johnson | F11: =GETPIVOTDATA("Sum of Gross Revenue",$A$3,"Salesperson","I. Johnson")/GETPIVOTDATA("Count of OrderID",$A$3,"Salesperson","I. Johnson") -> 15426.494 | G11: =GETPIVOTDATA("Count of OrderID",$A$3,"Salesperson","H. Kim")/12 -> 3.75 | H11: =GETPIVOTDATA("Sum of Gross Profit",$A$3,"Salesperson","H. Kim")/G11 -> 31745.847
A12: I. Johnson | B12: 586206.77 | C12: 38 | D12: 185062.79 | E12: H. Kim | F12: =GETPIVOTDATA("Sum of Gross Revenue",$A$3,"Salesperson","H. Kim")/GETPIVOTDATA("Count of OrderID",$A$3,"Salesperson","H. Kim") -> 15102.098 | G12: =GETPIVOTDATA("Count of OrderID",$A$3,"Salesperson","I. Johnson")/12 -> 3.1666667 | H12: =GETPIVOTDATA("Sum of Gross Profit",$A$3,"Salesperson","I. Johnson")/G12 -> 58440.88
A13: J. Njeri | B13: 772543.53 | C13: 50 | D13: 243271.98 | E13: G. Dubois | F13: =GETPIVOTDATA("Sum of Gross Revenue",$A$3,"Salesperson","G. Dubois")/GETPIVOTDATA("Count of OrderID",$A$3,"Salesperson","G. Dubois") -> 20771.717 | G13: =GETPIVOTDATA("Count of OrderID",$A$3,"Salesperson","J. Njeri")/12 -> 4.1666667 | H13: =GETPIVOTDATA("Sum of Gross Profit",$A$3,"Salesperson","J. Njeri")/G13 -> 58385.276
A14: K. Singh | B14: 903293.17 | C14: 44 | D14: 298707.31 | E14: F. Müller | F14: =GETPIVOTDATA("Sum of Gross Revenue",$A$3,"Salesperson","F. Müller")/GETPIVOTDATA("Count of OrderID",$A$3,"Salesperson","F. Müller") -> 21388.23 | G14: =GETPIVOTDATA("Count of OrderID",$A$3,"Salesperson","K. Singh")/12 -> 3.6666667 | H14: =GETPIVOTDATA("Sum of Gross Profit",$A$3,"Salesperson","K. Singh")/G14 -> 81465.63
A15: L. Okafor | B15: 730077.07 | C15: 46 | D15: 146755.1 | E15: E. Garcia | F15: =GETPIVOTDATA("Sum of Gross Revenue",$A$3,"Salesperson","E. Garcia")/GETPIVOTDATA("Count of OrderID",$A$3,"Salesperson","E. Garcia") -> 14191.834 | G15: =GETPIVOTDATA("Count of OrderID",$A$3,"Salesperson","L. Okafor")/12 -> 3.8333333 | H15: =GETPIVOTDATA("Sum of Gross Profit",$A$3,"Salesperson","L. Okafor")/G15 -> 38283.939
A16: M. Rossi | B16: 767983.21 | C16: 48 | D16: 104341.28 | E16: D. Smith | F16: =GETPIVOTDATA("Sum of Gross Revenue",$A$3,"Salesperson","D. Smith")/GETPIVOTDATA("Count of OrderID",$A$3,"Salesperson","D. Smith") -> 14805.831 | G16: =GETPIVOTDATA("Count of OrderID",$A$3,"Salesperson","M. Rossi")/12 -> 4 | H16: =GETPIVOTDATA("Sum of Gross Profit",$A$3,"Salesperson","M. Rossi")/G16 -> 26085.319
A17: N. Brown | B17: 521296.31 | C17: 32 | D17: 243617.63 | E17: C. Otieno | F17: =GETPIVOTDATA("Sum of Gross Revenue",$A$3,"Salesperson","C. Otieno")/GETPIVOTDATA("Count of OrderID",$A$3,"Salesperson","C. Otieno") -> 14511.758 | G17: =GETPIVOTDATA("Count of OrderID",$A$3,"Salesperson","N. Brown")/12 -> 2.6666667 | H17: =GETPIVOTDATA("Sum of Gross Profit",$A$3,"Salesperson","N. Brown")/G17 -> 91356.613
A18: Not Provided | B18: 192412.6 | C18: 8 | D18: 43483.749 | E18: B. Chen | F18: =GETPIVOTDATA("Sum of Gross Revenue",$A$3,"Salesperson","B. Chen")/GETPIVOTDATA("Count of OrderID",$A$3,"Salesperson","B. Chen") -> 16235.266 | G18: =GETPIVOTDATA("Count of OrderID",$A$3,"Salesperson","Not Provided")/12 -> 0.66666667 | H18: =GETPIVOTDATA("Sum of Gross Profit",$A$3,"Salesperson","Not Provided")/G18 -> 65225.624
A19: O. Wang | B19: 643379.83 | C19: 37 | D19: 180874.37 | E19: A. Patel | F19: =GETPIVOTDATA("Sum of Gross Revenue",$A$3,"Salesperson","A. Patel")/GETPIVOTDATA("Count of OrderID",$A$3,"Salesperson","A. Patel") -> 13029.913 | G19: =GETPIVOTDATA("Count of OrderID",$A$3,"Salesperson","O. Wang")/12 -> 3.0833333 | H19: =GETPIVOTDATA("Sum of Gross Profit",$A$3,"Salesperson","O. Wang")/G19 -> 58661.957 | K19: =IF(_xlfn.RANK.EQ(G4,G4:G19,0)>=1, "Bottom 3", "" ) -> Bottom 3
A20: Grand Total | B20: 10471486 | C20: 632 | D20: 2943738.2 | F20: =GETPIVOTDATA("Sum of Gross Revenue",$A$3)/GETPIVOTDATA("Count of OrderID",$A$3) -> 16568.807 | G20: =GETPIVOTDATA("Count of OrderID",$A$3)/12 -> 52.666667 | H20: =GETPIVOTDATA("Sum of Gross Profit",$A$3)/G20 -> 55893.764

Sheet Channel Mix Data
A1: ORD-2024-275203 | B1: 45362 | C1: 45388 | D1: =DATEDIF(B1,C1, "MD") -> 26 | E1: =TEXT(Data!B1,"MMM-YYYY") -> Mar-2024 | F1: ="Q"&ROUNDUP(MONTH(B1)/3,0)&"-"&YEAR(B1) -> Q1-2024 | G1: Africa | H1: Kenya | I1: Kisumu | J1: Corporate | K1: Retail | L1: C. Otieno | M1: Components | N1: CMP-8270 | O1: 279.24 | P1: =IF(Q1<50, "Low", IF(Q1<200, "Medium", "High")) -> High | Q1: 608.9 | R1: 0.112 | S1: 9 | T1: =(Q27*S1)*(1-R1) -> 1403.9546 | U1: =(O1*S1) -> 2513.16 | V1: =(T1-U1) -> -1109.2054 | W1: =IF(T1=0, 0, V1/T1) -> -0.79005783
A2: ORD-2024-358795 | B2: 45588 | C2: 45587 | D2: =DATEDIF(C2, B2, "MD") -> 1 | E2: =TEXT(Data!B2,"MMM-YYYY") -> Oct-2024 | F2: ="Q"&ROUNDUP(MONTH(B2)/3,0)&"-"&YEAR(B2) -> Q4-2024 | G2: Africa | H2: Nigeria | I2: Port Harcourt | J2: Education | K2: Online | L2: J. Njeri | M2: Printers | N2: PRN-9322 | O2: 1084.39 | P2: =IF(Q2<50, "Low", IF(Q2<200, "Medium", "High")) -> High | Q2: 759.33 | R2: 0.237 | S2: 31 | T2: =(Q28*S2)*(1-R2) -> 17934.414 | U2: =(O2*S2) -> 33616.09 | V2: =(T2-U2) -> -15681.676 | W2: =IF(T2=0, 0, V2/T2) -> -0.87439019
A3: ORD-2023-373538 | B3: 44985 | C3: 45010 | D3: =DATEDIF(B3,C3, "MD") -> 25 | E3: =TEXT(Data!B3,"MMM-YYYY") -> Feb-2023 | F3: ="Q"&ROUNDUP(MONTH(B3)/3,0)&"-"&YEAR(B3) -> Q1-2023 | G3: Africa | H3: Kenya | I3: Nairobi | J3: Corporate | K3: Retail | L3: I. Johnson | M3: Networking | N3: NET-9666 | O3: 1460.76 | P3: =IF(Q3<50, "Low", IF(Q3<200, "Medium", "High")) -> Low | Q3: -30.66 | R3: 0.131 | S3: 12 | T3: =(Q29*S3)*(1-R3) -> 4534.0944 | U3: =(O3*S3) -> 17529.12 | V3: =(T3-U3) -> -12995.026 | W3: =IF(T3=0, 0, V3/T3) -> -2.8660686
A4: ORD-2025-168148 | B4: 45745 | C4: 45749 | D4: =DATEDIF(B4,C4, "MD") -> 4 | E4: =TEXT(Data!B4,"MMM-YYYY") -> Mar-2025 | F4: ="Q"&ROUNDUP(MONTH(B4)/3,0)&"-"&YEAR(B4) -> Q1-2025 | G4: Africa | H4: Nigeria | I4: Lagos | J4: Non-Profit | K4: Marketplace | L4: G. Dubois | M4: Phones | N4: PHN-4556 | O4: 259.93 | P4: =IF(Q4<50, "Low", IF(Q4<200, "Medium", "High")) -> High | Q4: 255.94 | R4: 0.072 | S4: 22 | T4: =(Q30*S4)*(1-R4) -> 34016.731 | U4: =(O4*S4) -> 5718.46 | V4: =(T4-U4) -> 28298.271 | W4: =IF(T4=0, 0, V4/T4) -> 0.83189272
A5: ORD-2023-824839 | B5: 45266 | C5: 45291 | D5: =DATEDIF(B5,C5, "MD") -> 25 | E5: =TEXT(Data!B5,"MMM-YYYY") -> Dec-2023 | F5: ="Q"&ROUNDUP(MONTH(B5)/3,0)&"-"&YEAR(B5) -> Q4-2023 | G5: Asia | H5: Japan | I5: Osaka | J5: Consumer | K5: Retail | L5: L. Okafor | M5: Printers | N5: PRN-8041 | O5: 663.03 | P5: =IF(Q5<50, "Low", IF(Q5<200, "Medium", "High")) -> High | Q5: 813.51 | R5: 0.102 | S5: 15 | T5: =(Q31*S5)*(1-R5) -> 8510.0766 | U5: =(O5*S5) -> 9945.45 | V5: =(T5-U5) -> -1435.3734 | W5: =IF(T5=0, 0, V5/T5) -> -0.16866751
A6: ORD-2023-723587 | B6: 44928 | C6: 44931 | D6: =DATEDIF(B6,C6, "MD") -> 3 | E6: =TEXT(Data!B6,"MMM-YYYY") -> Jan-2023 | F6: ="Q"&ROUNDUP(MONTH(B6)/3,0)&"-"&YEAR(B6) -> Q1-2023 | G6: Americas | H6: Canada | I6: Toronto | J6: Corporate | K6: Distributor | L6: B. Chen | M6: Laptops | N6: LAP-8555 | O6: 315.87 | P6: =IF(Q6<50, "Low", IF(Q6<200, "Medium", "High")) -> High | Q6: 591.68 | R6: 0 | S6: 7 | T6: =(Q32*S6)*(1-R6) -> 12558.49 | U6: =(O6*S6) -> 2211.09 | V6: =(T6-U6) -> 10347.4 | W6: =IF(T6=0, 0, V6/T6) -> 0.82393664
A7: ORD-2024-336584 | B7: 45653 | C7: 45671 | D7: =DATEDIF(B7,C7, "MD") -> 18 | E7: =TEXT(Data!B7,"MMM-YYYY") -> Dec-2024 | F7: ="Q"&ROUNDUP(MONTH(B7)/3,0)&"-"&YEAR(B7) -> Q4-2024 | G7: Asia | H7: India | I7: Bengaluru | J7: Small Business | K7: Marketplace | L7: E. Garcia | M7: Monitors | N7: MON-8629 | O7: 586.07 | P7: =IF(Q7<50, "Low", IF(Q7<200, "Medium", "High")) -> High | Q7: 845.97 | R7: 0.147 | S7: 4 | T7: =(Q33*S7)*(1-R7) -> 8983.8642 | U7: =(O7*S7) -> 2344.28 | V7: =(T7-U7) -> 6639.5842 | W7: =IF(T7=0, 0, V7/T7) -> 0.73905661
A8: ORD-2023-112666 | B8: 44941 | C8: 44939 | D8: =DATEDIF(C8,B8, "MD") -> 2 | E8: =TEXT(Data!B8,"MMM-YYYY") -> Jan-2023 | F8: ="Q"&ROUNDUP(MONTH(B8)/3,0)&"-"&YEAR(B8) -> Q1-2023 | G8: Africa | H8: Nigeria | I8: Abuja | J8: Education | K8: Online | L8: O. Wang | M8: Printers | N8: PRN-6276 | O8: 28.38 | P8: =IF(Q8<50, "Low", IF(Q8<200, "Medium", "High")) -> Low | Q8: 47.22 | R8: 0.194 | S8: 18 | T8: =(Q34*S8)*(1-R8) -> 19177.4 | U8: =(O8*S8) -> 510.84 | V8: =(T8-U8) -> 18666.56 | W8: =IF(T8=0, 0, V8/T8) -> 0.9733624
A9: ORD-2024-589570 | B9: 45416 | C9: 45441 | D9: =DATEDIF(B9,C9, "MD") -> 25 | E9: =TEXT(Data!B9,"MMM-YYYY") -> May-2024 | F9: ="Q"&ROUNDUP(MONTH(B9)/3,0)&"-"&YEAR(B9) -> Q2-2024 | G9: Africa | H9: Nigeria | I9: Abuja | J9: Non-Profit | K9: Marketplace | L9: O. Wang | M9: Monitors | N9: MON-6892 | O9: 1295.34 | P9: =IF(Q9<50, "Low", IF(Q9<200, "Medium", "High")) -> High | Q9: 2530.81 | R9: 0.031 | S9: 6 | T9: =(Q35*S9)*(1-R9) -> 17656.362 | U9: =(O9*S9) -> 7772.04 | V9: =(T9-U9) -> 9884.3222 | W9: =IF(T9=0, 0, V9/T9) -> 0.55981646
A10: ORD-2025-997421 | B10: 45798 | C10: 45817 | D10: =DATEDIF(B10,C10, "MD") -> 19 | E10: =TEXT(Data!B10,"MMM-YYYY") -> May-2025 | F10: ="Q"&ROUNDUP(MONTH(B10)/3,0)&"-"&YEAR(B10) -> Q2-2025 | G10: Americas | H10: Brazil | I10: São Paulo | J10: Non-Profit | K10: Online | L10: A. Patel | M10: Components | N10: CMP-3731 | O10: 1331.38 | P10: =IF(Q10<50, "Low", IF(Q10<200, "Medium", "High")) -> High | Q10: 2309.56 | R10: 0.149 | S10: 31 | T10: =(Q36*S10)*(1-R10) -> 5259.58 | U10: =(O10*S10) -> 41272.78 | V10: =(T10-U10) -> -36013.2 | W10: =IF(T10=0, 0, V10/T10) -> -6.8471627
A11: ORD-2024-210687 | B11: 45319 | C11: 45331 | D11: =DATEDIF(B11,C11, "MD") -> 12 | E11: =TEXT(Data!B11,"MMM-YYYY") -> Jan-2024 | F11: ="Q"&ROUNDUP(MONTH(B11)/3,0)&"-"&YEAR(B11) -> Q1-2024 | G11: Europe | H11: Germany | I11: Berlin | J11: Corporate | K11: Online | L11: G. Dubois | M11: Accessories | N11: ACC-7938 | O11: 644.17 | P11: =IF(Q11<50, "Low", IF(Q11<200, "Medium", "High")) -> High | Q11: 700.12 | R11: 0.006 | S11: 23 | T11: =(Q37*S11)*(1-R11) -> 21204.734 | U11: =(O11*S11) -> 14815.91 | V11: =(T11-U11) -> 6388.8236 | W11: =IF(T11=0, 0, V11/T11) -> 0.30129233
A12: ORD-2025-515515 | B12: 45660 | C12: 45680 | D12: =DATEDIF(B12,C12, "MD") -> 20 | E12: =TEXT(Data!B12,"MMM-YYYY") -> Jan-2025 | F12: ="Q"&ROUNDUP(MONTH(B12)/3,0)&"-"&YEAR(B12) -> Q1-2025 | G12: Asia | H12: Japan | I12: Osaka | J12: Corporate | K12: Distributor | L12: F. Müller | M12: Phones | N12: PHN-7019 | O12: 908.6 | P12: =IF(Q12<50, "Low", IF(Q12<200, "Medium", "High")) -> High | Q12: 691.37 | R12: 0.25 | S12: 20 | T12: =(Q38*S12)*(1-R12) -> 26031.15 | U12: =(O12*S12) -> 18172 | V12: =(T12-U12) -> 7859.15 | W12: =IF(T12=0, 0, V12/T12) -> 0.30191328
A13: ORD-2025-487261 | B13: 45722 | C13: 45747 | D13: =DATEDIF(B13,C13, "MD") -> 25 | E13: =TEXT(Data!B13,"MMM-YYYY") -> Mar-2025 | F13: ="Q"&ROUNDUP(MONTH(B13)/3,0)&"-"&YEAR(B13) -> Q1-2025 | G13: Americas | H13: Brazil | I13: Brasília | J13: Non-Profit | K13: Online | L13: J. Njeri | M13: Components | N13: CMP-3693 | O13: 331.57 | P13: =IF(Q13<50, "Low", IF(Q13<200, "Medium", "High")) -> High | Q13: 548.4 | R13: 0.094 | S13: 10 | T13: =(Q39*S13)*(1-R13) -> 12644.498 | U13: =(O13*S13) -> 3315.7 | V13: =(T13-U13) -> 9328.7984 | W13: =IF(T13=0, 0, V13/T13) -> 0.73777528
A14: ORD-2024-890180 | B14: 45311 | C14: 45335 | D14: =DATEDIF(B14,C14, "MD") -> 24 | E14: =TEXT(Data!B14,"MMM-YYYY") -> Jan-2024 | F14: ="Q"&ROUNDUP(MONTH(B14)/3,0)&"-"&YEAR(B14) -> Q1-2024 | G14: Europe | H14: France | I14: Marseille | J14: Corporate | K14: Retail | L14: H. Kim | M14: Printers | N14: PRN-8392 | O14: 643.53 | P14: =IF(Q14<50, "Low", IF(Q14<200, "Medium", "High")) -> High | Q14: 1439.01 | R14: 0 | S14: 15 | T14: =(Q40*S14)*(1-R14) -> 6816.3 | U14: =(O14*S14) -> 9652.95 | V14: =(T14-U14) -> -2836.65 | W14: =IF(T14=0, 0, V14/T14) -> -0.41615686
A15: ORD-2025-840976 | B15: 45901 | C15: 45930 | D15: =DATEDIF(B15,C15, "MD") -> 29 | E15: =TEXT(Data!B15,"MMM-YYYY") -> Sep-2025 | F15: ="Q"&ROUNDUP(MONTH(B15)/3,0)&"-"&YEAR(B15) -> Q3-2025 | G15: Americas | H15: Brazil | I15: Brasília | J15: Education | K15: Retail | L15: K. Singh | M15: Accessories | N15: ACC-1663 | O15: 780.59 | P15: =IF(Q15<50, "Low", IF(Q15<200, "Medium", "High")) -> High | Q15: 631.57 | R15: 0 | S15: 12 | T15: =(Q41*S15)*(1-R15) -> 18971.64 | U15: =(O15*S15) -> 9367.08 | V15: =(T15-U15) -> 9604.56 | W15: =IF(T15=0, 0, V15/T15) -> 0.50625882
A16: ORD-2023-937291 | B16: 45039 | C16: 45038 | D16: =DATEDIF(C16, B16, "MD") -> 1 | E16: =TEXT(Data!B16,"MMM-YYYY") -> Apr-2023 | F16: ="Q"&ROUNDUP(MONTH(B16)/3,0)&"-"&YEAR(B16) -> Q2-2023 | G16: Africa | H16: Kenya | I16: Nairobi | J16: Small Business | K16: Direct | L16: E. Garcia | M16: Laptops | N16: LAP-1698 | O16: 756.51 | P16: =IF(Q16<50, "Low", IF(Q16<200, "Medium", "High")) -> High | Q16: 850.8 | R16: 0.074 | S16: 9 | T16: =(Q42*S16)*(1-R16) -> 14666.09 | U16: =(O16*S16) -> 6808.59 | V16: =(T16-U16) -> 7857.4999 | W16: =IF(T16=0, 0, V16/T16) -> 0.5357597
